Workbook

Sheet Начало
A1: СТАНДАРТИЗИРОВАННАЯ РАБОТА / И-ГЦ-02
A2: ДЕМО / ПРОЕКТ • Жёлтые ячейки — ваш ввод. Расчёты не являются утверждёнными нормативами.
A3: ← Начало
A4: Готовая расчётная модель: 18 продуктов · 3 программы SOLIA · 11 бланков ФЦК · критерии качества и чек-лист СОП. Все демонстрационные числа подписаны, обязательная технология отделена от предположений.
A7: 1. Откройте «Ввод» и «Ассортимент». Замените жёлтые значения своими. 2. Внесите реальные замеры в оба набора наблюдений и периодическую работу. 3. Проверьте «Контроль». Подробные бланки переключаются выбором продукта во «Ввод».
A10: План годного, кг | C10: ='Ассортимент'!F27 -> 107 | E10: ЖЁЛТЫЙ = ввод: заменяйте числа и текст. СИНИЙ = формулы: пересчёт автоматический. СЕРЫЙ = требования источника: не менять ради улучшений.
A11: Партий в смену | C11: ='Ввод'!B28 -> 32
A12: Доступно времени, с | C12: ='Ввод'!B27 -> 24600
A13: Такт, с/партию | C13: ='Ввод'!B30 -> 768.75
A14: Полных санобработок, событий | C14: ='Периодическая работа'!B20 -> 8 | E14: Модель исходно предполагает 1 машину и 1 оператора без перекрытия ручной работы с автоматической. Изменение числа ресурсов не строит новый производственный график. Подписи, обучение, результаты проверок и факты внедрения не вымышлены.
A15: Время ДО, мин/смену | C15: =IF(ISNUMBER('Расчет ДО'!B33),'Расчет ДО'!B33/60,"") -> 409.86267
A16: Время ЦЕЛЬ, мин/смену | C16: =IF(ISNUMBER('Расчет ЦЕЛЬ'!B33),'Расчет ЦЕЛЬ'!B33/60,"") -> 387.568
A17: Прогноз высвобождения, мин/смену | C17: ='Отчет об улучшении'!D28 -> 22.294667
A18: Критических ошибок ввода/формул | C18: ='Контроль'!C37 -> 0
A21: № | B21: Лист / раздел | C21: Назначение | D21: Где менять
A22: 1 | B22: Ввод | C22: Смена, ресурсы, реквизиты, выбор продукта | G22: Жёлтые клетки B
A23: 2 | B23: Режимы И-ГЦ-02 | C23: Неизменяемые программы мойки | G23: Серые требования источника
A24: 3 | B24: Ассортимент | C24: План, выходы, партии, сырьё и остатки | G24: F8:J25
A25: 4 | B25: Замеры ДО | C25: 10 замеров × 18 продуктов, исходная модель | G25: Жёлтые E:N каждого блока
A26: 5 | B26: Замеры ЦЕЛЬ | C26: Прогнозные / контрольные замеры | G26: Жёлтые E:N каждого блока
A27: 6 | B27: Периодическая работа | C27: Санобработка и подача тары | G27: Жёлтые длительности / частота тары
A28: 7 | B28: Расчет ДО | C28: Сводная нагрузка исходного состояния | G28: Формулы
A29: 8 | B29: Расчет ЦЕЛЬ | C29: Сводная нагрузка прогноза | G29: Формулы
A30: 9 | B30: Время такта | C30: Форма 1: такт по всем видам | G30: Ввод / Ассортимент
A31: 10 | B31: Лист наблюдений | C31: Форма 2: общие времена циклов | G31: Продукт / сценарий во Ввод
A32: 11 | B32: Ручная работа | C32: Форма 4: поэлементная регулировка | G32: Продукт / сценарий во Ввод
A33: 12 | B33: Карта СР | C33: Форма 3: маршрут, качество, безопасность, запас | G33: Жёлтые координаты C:F
... A48: 27 | B48: Лист ознакомления | C48: Реальные обучение и подписи | G48: Жёлтые поля после обучения
A51: Использование: Microsoft Excel (автовычисление включено) или LibreOffice Calc. Макросы не нужны. Формулы защищены без пароля от случайного изменения. Исходные PDF/XLSX лежат в sources/; книга представляет расчётную адаптацию шаблонов, а не изменённую методику.
A55: Перед вводом в работу: заменить ДЕМО-замеры, проверить состав этапов и натурную планировку, уточнить СИЗ и режимы санитарных средств, провести контрольные наблюдения, согласовать/утвердить СОП и обучить персонал. Числа прогноза не являются фактом внедрения и не подтверждают безопасность или соответствие стандартам.

Sheet Ввод
A1: 01 / ИСХОДНЫЕ ДАННЫЕ И ВЫБОР ПРОДУКТА
A2: ДЕМО / ПРОЕКТ • Жёлтые ячейки — ваш ввод. Расчёты не являются утверждёнными нормативами.
A3: ← Начало | B3: Синий фон — формула; серый — инструкция; жёлтый — ввод. Защита снимается без пароля.
A5: Параметр | B5: Ваше значение | C5: Единица | D5: Что заменить / источник
A6: Предприятие | B6: АО «ПП «Русский хлеб» — уточнить юрлицо | D6: В титуле И-ГЦ-02 также указано ООО «Курортное кафе». Перед утверждением сверить реквизиты.
A7: Цех | B7: Кулинарный цех | D7: Уточнить наименование цеха.
A8: Рабочее место | B8: Овощной участок / SOLIA | D8: Фактическое рабочее место и инвентарный номер оборудования.
A9: Подготовил | B9: Впишите ФИО составителя | D9: Без вымышленных подписей и подтверждения проведения наблюдений.
A10: Дата начала проекта | B10: 46270 | C10: дата | D10: Демонстрационная дата; от неё рассчитываются плановые сроки.
A11: Принятый тип работы | B11: II — многономенклатурная работа | C11: II | D11: Принят для модели; подтвердить наблюдением. Внутри каждого продукта используется поэлементный подход I типа.
A12: Продукт для подробных бланков | B12: Латук | D12: Выбор перестраивает наблюдения, ручную работу, ОТ, карту и СОП. Общие расчёты всегда учитывают все 18 продуктов.
A13: Сценарий подробных наблюдений | B13: ДО | D13: ДО — модель исходного состояния; ЦЕЛЬ — прогноз. Ни один не является фактом до замены замеров.
A14: Основание данных ДО | B14: ДЕМО: синтетические замеры; заменить фактическими | D14: Укажите дату, смену, исполнителя и ссылку на лист/видеозапись реальных замеров.
A15: Основание данных ЦЕЛЬ | B15: ДЕМО: прогноз; улучшения не внедрены | D15: Не переименовывать прогноз в факт без контрольных наблюдений.
A17: Продолжительность одной смены | B17: 480 | C17: мин/смену | D17: Модель рассчитывает ОДНУ смену. Для разных смен используйте отдельные копии книги.
A18: Обед | B18: 30 | C18: мин/смену | D18: Только регламентированное время. Не включайте сюда периодическую санобработку.
A19: Прочие регламентные перерывы | B19: 20 | C19: мин/смену | D19: Сумма перерывов; не учитывать повторно в периодической работе.
A20: Фиксированная подготовка смены | B20: 10 | C20: мин/смену | D20: Не включает подачу тары и санобработку бака, учтённые отдельно.
A21: Фиксированное завершение смены | B21: 10 | C21: мин/смену | D21: Не включает санобработку бака. Она целиком находится в периодической работе.
A22: Доступно моечных машин | B22: 1 | C22: ед. | D22: При значении не 1 ресурсные оценки агрегированные. ОТ и карта описывают только одну ячейку; нужен фактический график распределения.
A23: Операторов в смене | B23: 1 | C23: чел. | D23: В базовой схеме оператор не выполняет другую работу во время автоматической программы. Дополнительные люди не ускоряют машину автоматически.
A24: Обязательная периодичность санобработки | B24: 4 | C24: 4 помывки | D24: И-ГЦ-02, стр. 3. Частота — требование источника, не объект оптимизации.
A25: Помывок с последней санобработки к началу смены | B25: 0 | C25: 0…3 | D25: Фактический счётчик. 0 означает подготовленный чистый бак. Для неполного предыдущего блока введите 1–3.
A26: Резерв завершающей санобработки неполного блока | B26: 1 | C26: 1 / 0 | D26: ДЕМО: 1 — резерв полного комплекса после неполной четвёрки в конце смены. Это плановое допущение; уточнить по санпрограмме. Регулярную обработку после 4 помывок отключить нельзя.
A27: Фонд рабочего времени одной ячейки | B27: =IF(AND(COUNT(B17:B21)=5,MIN(B17:B21)>=0,B17>SUM(B18:B21)),(B17-SUM(B18:B21))*60,"") -> 24600 | C27: с/смену
A28: Всего партий в плане | B28: =IF(COUNT('Ассортимент'!O8:O25)=18,'Ассортимент'!O27,"") -> 32 | C28: партий/смену
A29: Индекс выбранного продукта | B29: =IFERROR(MATCH(B12,'Ассортимент'!B8:B25,0),0) -> 1
A30: Такт выпуска по всему ассортименту | B30: =IF(AND(ISNUMBER(B27),B27>0,ISNUMBER(B28),B28>0),B27/B28,"") -> 768.75 | C30: с/партию
A33: Ответственный за внедрение | B33: Начальник кулинарного цеха — впишите ФИО | D33: Проект распределения ролей, не назначение приказом.
A34: Ответственный за технологию | B34: Инженер-технолог — впишите ФИО | D34: Проверяет режимы, нормы загрузки, санпрограмму и качество.
A35: Исполнитель | B35: Оператор SOLIA — впишите ФИО | D35: Указать реально наблюдаемого и обученного исполнителя.
A36: Ответственный за ОТ | B36: Ответственный по ОТ — впишите ФИО | D36: Согласовать безопасные действия, СИЗ, инструкции и допуск.
A37: Утверждает | B37: Уполномоченный руководитель — впишите ФИО | D37: Утверждение выполняется вне расчётной модели в установленном порядке.
A38: Статус утверждения | B38: Не утверждено | D38: Редактировать только после реального согласования и утверждения; подпись не генерируется.
A40: Номер улучшения для отчёта | B40: 1 | C40: 1…6 | D40: Переключает подробный отчёт об улучшении.
A42: Проверяйте лист «Контроль» после каждого изменения. Количество людей не умножает время такта. Для нескольких ячеек нужна отдельная балансировка и распределение целых партий.

Sheet Режимы И-ГЦ-02
A1: 02 / ТЕХНОЛОГИЧЕСКИЕ ДАННЫЕ ИЗ ИНСТРУКЦИИ
A2: ДЕМО / ПРОЕКТ • Жёлтые ячейки — ваш ввод. Расчёты не являются утверждёнными нормативами.
A3: ← Начало | B3: Синий фон — формула; серый — инструкция; жёлтый — ввод. Защита снимается без пароля.
A7: Программа | B7: Мытьё, об/мин | C7: Мытьё, с | D7: Ополаск., об/мин | E7: Ополаск., с | F7: Вращение, об/мин | G7: Вращение, с | H7: Всего авто, с | I7: Тара после обработки | J7: Источник
A8: 1 | B8: 30 | C8: 60 | D8: 150 | E8: 30 | F8: 400 | G8: 360 | H8: =SUM(C8,E8,G8) -> 450 | I8: «ЗЕЛЕНЬ» для зелени; «СО» для овощей | J8: И-ГЦ-02, PDF стр. 3, таблица №1
A9: 2 | B9: 30 | C9: 60 | D9: 150 | E9: 60 | F9: 150 | G9: 60 | H9: =SUM(C9,E9,G9) -> 180 | I9: «ЗЕЛЕНЬ» для зелени; «СО» для овощей | J9: И-ГЦ-02, PDF стр. 3, таблица №1
A10: 3 | B10: 30 | C10: 120 | D10: 150 | E10: 60 | F10: 250 | G10: 120 | H10: =SUM(C10,E10,G10) -> 300 | I10: «ЗЕЛЕНЬ» для зелени; «СО» для овощей | J10: И-ГЦ-02, PDF стр. 3, таблица №1
A13: ВАЖНО: 01 = 450 с; 02 = 180 с; 03 = 300 с. Значения «1:00 мин:сек» переведены в 60 секунд, «6:00» — в 360 секунд. Это не 1 и не 6 секунд.
A16: После каждой 4-й помывки: слить бак → после слива выключить и обесточить оборудование → промыть бак моющими средствами и продезинфицировать. В книге это отдельный периодический комплекс, а не вычет из фонда времени.
A20: И-ГЦ-02 не задаёт средство, концентрацию, температуру и экспозицию дезинфекции, перечень СИЗ и длительности ручных действий. Они НЕ придуманы как технологические нормы. Демонстрационное время в периодических замерах служит только иллюстрацией расчёта.
A24: Названия и загрузки всех 18 позиций перенесены в «Ассортимент». Группировка для расчёта — проектная; отдельные названия («сельдерей ствол») сохранены как в источнике. Предел трактуется консервативно как верхняя масса одной загрузки.

Sheet Ассортимент
A1: 03 / ПЛАН СМЕНЫ · МАССОВЫЙ БАЛАНС · ЧИСЛО ПАРТИЙ
A2: ДЕМО / ПРОЕКТ • Жёлтые ячейки — ваш ввод. Расчёты не являются утверждёнными нормативами.
A3: ← Начало | B3: Синий фон — формула; серый — инструкция; жёлтый — ввод. Защита снимается без пароля.
A5: Меняйте F:J. План задаётся в кг годного после мойки. Выход подготовки и выход мойки — разные показатели. Партии считаются по массе, поступающей непосредственно в SOLIA.
A7: № | B7: Продукт | C7: Группа | D7: Программа | E7: Предел загрузки, кг | F7: План годного, кг | G7: Выход подготовки | H7: Выход мойки | I7: Партия план, кг | J7: Партия замера, кг | K7: В мойку, кг | L7: Исходное сырьё, кг | M7: Отсев до мойки, кг | N7: Потери при мойке, кг | O7: Партий, шт. | P7: Последняя партия, кг | Q7: Доля партий | R7: Авто, с/партию | S7: Контроль вводов | T7: Сопоставимость замеров
A8: 1 | B8: Латук | C8: Зелень | D8: 1 | E8: 1.5 | F8: 3 | G8: 0.95 | H8: 1 | I8: 1.5 | J8: 1.5 | K8: =IF(S8="ОК",F8/H8,"") -> 3 | L8: =IF(S8="ОК",K8/G8,"") -> 3.1578947 | M8: =IF(S8="ОК",L8-K8,"") -> 0.15789474 | N8: =IF(S8="ОК",K8-F8,"") -> 0 | O8: =IF(S8="ОК",ROUNDUP(ROUND(K8/I8,10),0),"") -> 2 | P8: =IF(S8="ОК",IF(O8>0,MAX(0,K8-(O8-1)*I8),0),"") -> 1.5 | Q8: =IF(AND(ISNUMBER(O8),ISNUMBER($O$27),$O$27>0),O8/$O$27,0) -> 0.0625 | R8: =VLOOKUP(D8,'Режимы И-ГЦ-02'!$A$8:$H$10,8,FALSE) -> 450 | S8: =IF(AND(COUNT(F8:J8)=5,F8>=0,G8>0,G8<=1,H8>0,H8<=1,I8>0,I8<=E8,J8>0,J8<=E8),"ОК","ОШИБКА: проверьте F:J") -> ОК | T8: =IF(S8<>"ОК","Исправьте ввод",IF(F8=0,"Нет в плане",IF(ABS(I8-J8)<0.000001,"Партия совпадает","НУЖЕН НОВЫЙ ХРОНОМЕТРАЖ"))) -> Партия совпадает
A9: 2 | B9: Базилик | C9: Зелень | D9: 1 | E9: 1.5 | F9: 1.5 | G9: 0.95 | H9: 1 | I9: 1.5 | J9: 1.5 | K9: =IF(S9="ОК",F9/H9,"") -> 1.5 | L9: =IF(S9="ОК",K9/G9,"") -> 1.5789474 | M9: =IF(S9="ОК",L9-K9,"") -> 0.078947368 | N9: =IF(S9="ОК",K9-F9,"") -> 0 | O9: =IF(S9="ОК",ROUNDUP(ROUND(K9/I9,10),0),"") -> 1 | P9: =IF(S9="ОК",IF(O9>0,MAX(0,K9-(O9-1)*I9),0),"") -> 1.5 | Q9: =IF(AND(ISNUMBER(O9),ISNUMBER($O$27),$O$27>0),O9/$O$27,0) -> 0.03125 | R9: =VLOOKUP(D9,'Режимы И-ГЦ-02'!$A$8:$H$10,8,FALSE) -> 450 | S9: =IF(AND(COUNT(F9:J9)=5,F9>=0,G9>0,G9<=1,H9>0,H9<=1,I9>0,I9<=E9,J9>0,J9<=E9),"ОК","ОШИБКА: проверьте F:J") -> ОК | T9: =IF(S9<>"ОК","Исправьте ввод",IF(F9=0,"Нет в плане",IF(ABS(I9-J9)<0.000001,"Партия совпадает","НУЖЕН НОВЫЙ ХРОНОМЕТРАЖ"))) -> Партия совпадает
A10: 3 | B10: Петрушка | C10: Зелень | D10: 1 | E10: 1.5 | F10: 1.5 | G10: 0.95 | H10: 1 | I10: 1.5 | J10: 1.5 | K10: =IF(S10="ОК",F10/H10,"") -> 1.5 | L10: =IF(S10="ОК",K10/G10,"") -> 1.5789474 | M10: =IF(S10="ОК",L10-K10,"") -> 0.078947368 | N10: =IF(S10="ОК",K10-F10,"") -> 0 | O10: =IF(S10="ОК",ROUNDUP(ROUND(K10/I10,10),0),"") -> 1 | P10: =IF(S10="ОК",IF(O10>0,MAX(0,K10-(O10-1)*I10),0),"") -> 1.5 | Q10: =IF(AND(ISNUMBER(O10),ISNUMBER($O$27),$O$27>0),O10/$O$27,0) -> 0.03125 | R10: =VLOOKUP(D10,'Режимы И-ГЦ-02'!$A$8:$H$10,8,FALSE) -> 450 | S10: =IF(AND(COUNT(F10:J10)=5,F10>=0,G10>0,G10<=1,H10>0,H10<=1,I10>0,I10<=E10,J10>0,J10<=E10),"ОК","ОШИБКА: проверьте F:J") -> ОК | T10: =IF(S10<>"ОК","Исправьте ввод",IF(F10=0,"Нет в плане",IF(ABS(I10-J10)<0.000001,"Партия совпадает","НУЖЕН НОВЫЙ ХРОНОМЕТРАЖ"))) -> Партия совпадает
A11: 4 | B11: Томат | C11: Овощи и прочее | D11: 2 | E11: 5 | F11: 25 | G11: 0.98 | H11: 1 | I11: 5 | J11: 5 | K11: =IF(S11="ОК",F11/H11,"") -> 25 | L11: =IF(S11="ОК",K11/G11,"") -> 25.510204 | M11: =IF(S11="ОК",L11-K11,"") -> 0.51020408 | N11: =IF(S11="ОК",K11-F11,"") -> 0 | O11: =IF(S11="ОК",ROUNDUP(ROUND(K11/I11,10),0),"") -> 5 | P11: =IF(S11="ОК",IF(O11>0,MAX(0,K11-(O11-1)*I11),0),"") -> 5 | Q11: =IF(AND(ISNUMBER(O11),ISNUMBER($O$27),$O$27>0),O11/$O$27,0) -> 0.15625 | R11: =VLOOKUP(D11,'Режимы И-ГЦ-02'!$A$8:$H$10,8,FALSE) -> 180 | S11: =IF(AND(COUNT(F11:J11)=5,F11>=0,G11>0,G11<=1,H11>0,H11<=1,I11>0,I11<=E11,J11>0,J11<=E11),"ОК","ОШИБКА: проверьте F:J") -> ОК | T11: =IF(S11<>"ОК","Исправьте ввод",IF(F11=0,"Нет в плане",IF(ABS(I11-J11)<0.000001,"Партия совпадает","НУЖЕН НОВЫЙ ХРОНОМЕТРАЖ"))) -> Партия совпадает
A12: 5 | B12: Белокочанная капуста | C12: Овощи и прочее | D12: 2 | E12: 3 | F12: 9 | G12: 0.98 | H12: 1 | I12: 3 | J12: 3 | K12: =IF(S12="ОК",F12/H12,"") -> 9 | L12: =IF(S12="ОК",K12/G12,"") -> 9.1836735 | M12: =IF(S12="ОК",L12-K12,"") -> 0.18367347 | N12: =IF(S12="ОК",K12-F12,"") -> 0 | O12: =IF(S12="ОК",ROUNDUP(ROUND(K12/I12,10),0),"") -> 3 | P12: =IF(S12="ОК",IF(O12>0,MAX(0,K12-(O12-1)*I12),0),"") -> 3 | Q12: =IF(AND(ISNUMBER(O12),ISNUMBER($O$27),$O$27>0),O12/$O$27,0) -> 0.09375 | R12: =VLOOKUP(D12,'Режимы И-ГЦ-02'!$A$8:$H$10,8,FALSE) -> 180 | S12: =IF(AND(COUNT(F12:J12)=5,F12>=0,G12>0,G12<=1,H12>0,H12<=1,I12>0,I12<=E12,J12>0,J12<=E12),"ОК","ОШИБКА: проверьте F:J") -> ОК | T12: =IF(S12<>"ОК","Исправьте ввод",IF(F12=0,"Нет в плане",IF(ABS(I12-J12)<0.000001,"Партия совпадает","НУЖЕН НОВЫЙ ХРОНОМЕТРАЖ"))) -> Партия совпадает
A13: 6 | B13: Укроп | C13: Зелень | D13: 3 | E13: 1.5 | F13: 3 | G13: 0.95 | H13: 1 | I13: 1.5 | J13: 1.5 | K13: =IF(S13="ОК",F13/H13,"") -> 3 | L13: =IF(S13="ОК",K13/G13,"") -> 3.1578947 | M13: =IF(S13="ОК",L13-K13,"") -> 0.15789474 | N13: =IF(S13="ОК",K13-F13,"") -> 0 | O13: =IF(S13="ОК",ROUNDUP(ROUND(K13/I13,10),0),"") -> 2 | P13: =IF(S13="ОК",IF(O13>0,MAX(0,K13-(O13-1)*I13),0),"") -> 1.5 | Q13: =IF(AND(ISNUMBER(O13),ISNUMBER($O$27),$O$27>0),O13/$O$27,0) -> 0.0625 | R13: =VLOOKUP(D13,'Режимы И-ГЦ-02'!$A$8:$H$10,8,FALSE) -> 300 | S13: =IF(AND(COUNT(F13:J13)=5,F13>=0,G13>0,G13<=1,H13>0,H13<=1,I13>0,I13<=E13,J13>0,J13<=E13),"ОК","ОШИБКА: проверьте F:J") -> ОК | T13: =IF(S13<>"ОК","Исправьте ввод",IF(F13=0,"Нет в плане",IF(ABS(I13-J13)<0.000001,"Партия совпадает","НУЖЕН НОВЫЙ ХРОНОМЕТРАЖ"))) -> Партия совпадает
A14: 7 | B14: Зеленый лук | C14: Зелень | D14: 3 | E14: 1.5 | F14: 1.5 | G14: 0.95 | H14: 1 | I14: 1.5 | J14: 1.5 | K14: =IF(S14="ОК",F14/H14,"") -> 1.5 | L14: =IF(S14="ОК",K14/G14,"") -> 1.5789474 | M14: =IF(S14="ОК",L14-K14,"") -> 0.078947368 | N14: =IF(S14="ОК",K14-F14,"") -> 0 | O14: =IF(S14="ОК",ROUNDUP(ROUND(K14/I14,10),0),"") -> 1 | P14: =IF(S14="ОК",IF(O14>0,MAX(0,K14-(O14-1)*I14),0),"") -> 1.5 | Q14: =IF(AND(ISNUMBER(O14),ISNUMBER($O$27),$O$27>0),O14/$O$27,0) -> 0.03125 | R14: =VLOOKUP(D14,'Режимы И-ГЦ-02'!$A$8:$H$10,8,FALSE) -> 300 | S14: =IF(AND(COUNT(F14:J14)=5,F14>=0,G14>0,G14<=1,H14>0,H14<=1,I14>0,I14<=E14,J14>0,J14<=E14),"ОК","ОШИБКА: проверьте F:J") -> ОК | T14: =IF(S14<>"ОК","Исправьте ввод",IF(F14=0,"Нет в плане",IF(ABS(I14-J14)<0.000001,"Партия совпадает","НУЖЕН НОВЫЙ ХРОНОМЕТРАЖ"))) -> Партия совпадает
A15: 8 | B15: Кинза | C15: Зелень | D15: 3 | E15: 1.5 | F15: 1.5 | G15: 0.95 | H15: 1 | I15: 1.5 | J15: 1.5 | K15: =IF(S15="ОК",F15/H15,"") -> 1.5 | L15: =IF(S15="ОК",K15/G15,"") -> 1.5789474 | M15: =IF(S15="ОК",L15-K15,"") -> 0.078947368 | N15: =IF(S15="ОК",K15-F15,"") -> 0 | O15: =IF(S15="ОК",ROUNDUP(ROUND(K15/I15,10),0),"") -> 1 | P15: =IF(S15="ОК",IF(O15>0,MAX(0,K15-(O15-1)*I15),0),"") -> 1.5 | Q15: =IF(AND(ISNUMBER(O15),ISNUMBER($O$27),$O$27>0),O15/$O$27,0) -> 0.03125 | R15: =VLOOKUP(D15,'Режимы И-ГЦ-02'!$A$8:$H$10,8,FALSE) -> 300 | S15: =IF(AND(COUNT(F15:J15)=5,F15>=0,G15>0,G15<=1,H15>0,H15<=1,I15>0,I15<=E15,J15>0,J15<=E15),"ОК","ОШИБКА: проверьте F:J") -> ОК | T15: =IF(S15<>"ОК","Исправьте ввод",IF(F15=0,"Нет в плане",IF(ABS(I15-J15)<0.000001,"Партия совпадает","НУЖЕН НОВЫЙ ХРОНОМЕТРАЖ"))) -> Партия совпадает
A16: 9 | B16: Шампиньоны | C16: Овощи и прочее | D16: 3 | E16: 5 | F16: 10 | G16: 0.98 | H16: 1 | I16: 5 | J16: 5 | K16: =IF(S16="ОК",F16/H16,"") -> 10 | L16: =IF(S16="ОК",K16/G16,"") -> 10.204082 | M16: =IF(S16="ОК",L16-K16,"") -> 0.20408163 | N16: =IF(S16="ОК",K16-F16,"") -> 0 | O16: =IF(S16="ОК",ROUNDUP(ROUND(K16/I16,10),0),"") -> 2 | P16: =IF(S16="ОК",IF(O16>0,MAX(0,K16-(O16-1)*I16),0),"") -> 5 | Q16: =IF(AND(ISNUMBER(O16),ISNUMBER($O$27),$O$27>0),O16/$O$27,0) -> 0.0625 | R16: =VLOOKUP(D16,'Режимы И-ГЦ-02'!$A$8:$H$10,8,FALSE) -> 300 | S16: =IF(AND(COUNT(F16:J16)=5,F16>=0,G16>0,G16<=1,H16>0,H16<=1,I16>0,I16<=E16,J16>0,J16<=E16),"ОК","ОШИБКА: проверьте F:J") -> ОК | T16: =IF(S16<>"ОК","Исправьте ввод",IF(F16=0,"Нет в плане",IF(ABS(I16-J16)<0.000001,"Партия совпадает","НУЖЕН НОВЫЙ ХРОНОМЕТРАЖ"))) -> Партия совпадает
A17: 10 | B17: Перец болгарский красный | C17: Овощи и прочее | D17: 3 | E17: 5 | F17: 15 | G17: 0.98 | H17: 1 | I17: 5 | J17: 5 | K17: =IF(S17="ОК",F17/H17,"") -> 15 | L17: =IF(S17="ОК",K17/G17,"") -> 15.306122 | M17: =IF(S17="ОК",L17-K17,"") -> 0.30612245 | N17: =IF(S17="ОК",K17-F17,"") -> 0 | O17: =IF(S17="ОК",ROUNDUP(ROUND(K17/I17,10),0),"") -> 3 | P17: =IF(S17="ОК",IF(O17>0,MAX(0,K17-(O17-1)*I17),0),"") -> 5 | Q17: =IF(AND(ISNUMBER(O17),ISNUMBER($O$27),$O$27>0),O17/$O$27,0) -> 0.09375 | R17: =VLOOKUP(D17,'Режимы И-ГЦ-02'!$A$8:$H$10,8,FALSE) -> 300 | S17: =IF(AND(COUNT(F17:J17)=5,F17>=0,G17>0,G17<=1,H17>0,H17<=1,I17>0,I17<=E17,J17>0,J17<=E17),"ОК","ОШИБКА: проверьте F:J") -> ОК | T17: =IF(S17<>"ОК","Исправьте ввод",IF(F17=0,"Нет в плане",IF(ABS(I17-J17)<0.000001,"Партия совпадает","НУЖЕН НОВЫЙ ХРОНОМЕТРАЖ"))) -> Партия совпадает
A18: 11 | B18: Огурец | C18: Овощи и прочее | D18: 3 | E18: 5 | F18: 20 | G18: 0.98 | H18: 1 | I18: 5 | J18: 5 | K18: =IF(S18="ОК",F18/H18,"") -> 20 | L18: =IF(S18="ОК",K18/G18,"") -> 20.408163 | M18: =IF(S18="ОК",L18-K18,"") -> 0.40816327 | N18: =IF(S18="ОК",K18-F18,"") -> 0 | O18: =IF(S18="ОК",ROUNDUP(ROUND(K18/I18,10),0),"") -> 4 | P18: =IF(S18="ОК",IF(O18>0,MAX(0,K18-(O18-1)*I18),0),"") -> 5 | Q18: =IF(AND(ISNUMBER(O18),ISNUMBER($O$27),$O$27>0),O18/$O$27,0) -> 0.125 | R18: =VLOOKUP(D18,'Режимы И-ГЦ-02'!$A$8:$H$10,8,FALSE) -> 300 | S18: =IF(AND(COUNT(F18:J18)=5,F18>=0,G18>0,G18<=1,H18>0,H18<=1,I18>0,I18<=E18,J18>0,J18<=E18),"ОК","ОШИБКА: проверьте F:J") -> ОК | T18: =IF(S18<>"ОК","Исправьте ввод",IF(F18=0,"Нет в плане",IF(ABS(I18-J18)<0.000001,"Партия совпадает","НУЖЕН НОВЫЙ ХРОНОМЕТРАЖ"))) -> Партия совпадает
A19: 12 | B19: Редис | C19: Овощи и прочее | D19: 3 | E19: 3 | F19: 3 | G19: 0.98 | H19: 1 | I19: 3 | J19: 3 | K19: =IF(S19="ОК",F19/H19,"") -> 3 | L19: =IF(S19="ОК",K19/G19,"") -> 3.0612245 | M19: =IF(S19="ОК",L19-K19,"") -> 0.06122449 | N19: =IF(S19="ОК",K19-F19,"") -> 0 | O19: =IF(S19="ОК",ROUNDUP(ROUND(K19/I19,10),0),"") -> 1 | P19: =IF(S19="ОК",IF(O19>0,MAX(0,K19-(O19-1)*I19),0),"") -> 3 | Q19: =IF(AND(ISNUMBER(O19),ISNUMBER($O$27),$O$27>0),O19/$O$27,0) -> 0.03125 | R19: =VLOOKUP(D19,'Режимы И-ГЦ-02'!$A$8:$H$10,8,FALSE) -> 300 | S19: =IF(AND(COUNT(F19:J19)=5,F19>=0,G19>0,G19<=1,H19>0,H19<=1,I19>0,I19<=E19,J19>0,J19<=E19),"ОК","ОШИБКА: проверьте F:J") -> ОК | T19: =IF(S19<>"ОК","Исправьте ввод",IF(F19=0,"Нет в плане",IF(ABS(I19-J19)<0.000001,"Партия совпадает","НУЖЕН НОВЫЙ ХРОНОМЕТРАЖ"))) -> Партия совпадает
... A25: 18 | B25: Апельсин | C25: Овощи и прочее | D25: 3 | E25: 2 | F25: 2 | G25: 0.98 | H25: 1 | I25: 2 | J25: 2 | K25: =IF(S25="ОК",F25/H25,"") -> 2 | L25: =IF(S25="ОК",K25/G25,"") -> 2.0408163 | M25: =IF(S25="ОК",L25-K25,"") -> 0.040816327 | N25: =IF(S25="ОК",K25-F25,"") -> 0 | O25: =IF(S25="ОК",ROUNDUP(ROUND(K25/I25,10),0),"") -> 1 | P25: =IF(S25="ОК",IF(O25>0,MAX(0,K25-(O25-1)*I25),0),"") -> 2 | Q25: =IF(AND(ISNUMBER(O25),ISNUMBER($O$27),$O$27>0),O25/$O$27,0) -> 0.03125 | R25: =VLOOKUP(D25,'Режимы И-ГЦ-02'!$A$8:$H$10,8,FALSE) -> 300 | S25: =IF(AND(COUNT(F25:J25)=5,F25>=0,G25>0,G25<=1,H25>0,H25<=1,I25>0,I25<=E25,J25>0,J25<=E25),"ОК","ОШИБКА: проверьте F:J") -> ОК | T25: =IF(S25<>"ОК","Исправьте ввод",IF(F25=0,"Нет в плане",IF(ABS(I25-J25)<0.000001,"Партия совпадает","НУЖЕН НОВЫЙ ХРОНОМЕТРАЖ"))) -> Партия совпадает
B27: ИТОГО | F27: =IF(COUNT(F8:F25)=18,SUM(F8:F25),"") -> 107 | K27: =IF(COUNT(K8:K25)=18,SUM(K8:K25),"") -> 107 | L27: =IF(COUNT(L8:L25)=18,SUM(L8:L25),"") -> 109.57035 | M27: =IF(COUNT(M8:M25)=18,SUM(M8:M25),"") -> 2.5703545 | N27: =IF(COUNT(N8:N25)=18,SUM(N8:N25),"") -> 0 | O27: =IF(COUNT(O8:O25)=18,SUM(O8:O25),"") -> 32 | Q27: =SUM(Q8:Q25) -> 1
A29: Число партий = ROUNDUP(масса в мойку / плановая партия). Усреднение времени ведётся по количеству партий, НЕ по кг. Для неполной партии сохранены полные ручные и автоматические времена — консервативное допущение. Значение 0 в плане допустимо; пустые/ошибочные исходные данные не означают нулевой спрос.

Sheet Замеры ДО
A1: 04 / ПОЭЛЕМЕНТНЫЕ ЗАМЕРЫ · ДО · ВСЕ 18 ПРОДУКТОВ
A2: ДЕМО / ПРОЕКТ • Жёлтые ячейки — ваш ввод. Расчёты не являются утверждёнными нормативами.
A3: ← Начало | B3: Синий фон — формула; серый — инструкция; жёлтый — ввод. Защита снимается без пароля.
A5: Вводите длительность каждого элемента в секундах, НЕ накопительные отсечки. Флаг 0 исключает ВЕСЬ цикл. Если хотя бы один элемент пустой/ошибочный — весь цикл автоматически исключается.
A7: 01. Латук · ДО · 10 демонстрационных циклов, заменить реальными
A8: ="Масса замера, кг: "&'Ассортимент'!J8&". Все замеры одной партии/исполнителя/условий. Основание: "&'Ввод'!B14 -> Масса замера, кг: 1.5. Все замеры одной партии/исполнителя/условий. Основание: ДЕМО: синтетические замеры; заменить фактическими
A9: № | B9: Рабочий элемент | C9: Тип | D9: Точка отсчёта | E9: 1 | F9: 2 | G9: 3 | H9: 4 | I9: 5 | J9: 6 | K9: 7 | L9: 8 | M9: 9 | N9: 10 | O9: t min | P9: t max | Q9: Размах | R9: Рег. с | S9: t отрег. | T9: Колебания | U9: Среднее | V9: Контроль | W9: Служебно | X9: Статус
B10: Учитывать цикл: 1 / 0 | E10: 1 | F10: 1 | G10: 1 | H10: 1 | I10: 1 | J10: 1 | K10: 1 | L10: 1 | M10: 1 | N10: 1
B11: Причина исключения / условия | E11: ДЕМО | F11: ДЕМО | G11: ДЕМО | H11: ДЕМО | I11: ДЕМО | J11: ДЕМО | K11: ДЕМО | L11: ДЕМО | M11: ДЕМО | N11: ДЕМО
A12: 1 | B12: Осмотреть упаковку и сырьё | C12: Ручная | D12: Осмотр партии завершён | E12: 25 | F12: 26 | G12: 27 | H12: 25.5 | I12: 26.5 | J12: 27.5 | K12: 25.75 | L12: 26.75 | M12: 25.25 | N12: 26.25 | O12: =IF(COUNT(AG12:AP12)>0,MIN(AG12:AP12),"") -> 25 | P12: =IF(COUNT(AG12:AP12)>0,MAX(AG12:AP12),"") -> 27.5 | Q12: =IF(ISNUMBER(O12),P12-O12,"") -> 2.5 | R12: =IF(ISNUMBER(O12),IF(C12="Ручная",IF($S$24>0,$R$24*Q12/$S$24,IF($W$24=1,$R$24,0)),0),"") -> 0.91086957 | S12: =IF(ISNUMBER(O12),O12+R12,"") -> 25.91087 | T12: =IF(ISNUMBER(S12),P12-S12,"") -> 1.5891304 | U12: =IF(COUNT(AG12:AP12)>0,AVERAGE(AG12:AP12),"") -> 26.15 | AG12: =IF(ISNUMBER(E$24),E12,"") -> 25 | AH12: =IF(ISNUMBER(F$24),F12,"") -> 26 | AI12: =IF(ISNUMBER(G$24),G12,"") -> 27 | AJ12: =IF(ISNUMBER(H$24),H12,"") -> 25.5 | AK12: =IF(ISNUMBER(I$24),I12,"") -> 26.5 | AL12: =IF(ISNUMBER(J$24),J12,"") -> 27.5 | AM12: =IF(ISNUMBER(K$24),K12,"") -> 25.75 | AN12: =IF(ISNUMBER(L$24),L12,"") -> 26.75 | ... AP12: =IF(ISNUMBER(N$24),N12,"") -> 26.25 | AQ12: =IF(C12="Ручная",O12,0) -> 25
A13: 2 | B13: Отсортировать / подготовить сырьё | C13: Ручная | D13: Подготовленное сырьё отложено | E13: 102 | F13: 106 | G13: 110 | H13: 103 | I13: 107 | J13: 101 | K13: 105 | L13: 100 | M13: 104 | N13: 108 | O13: =IF(COUNT(AG13:AP13)>0,MIN(AG13:AP13),"") -> 100 | P13: =IF(COUNT(AG13:AP13)>0,MAX(AG13:AP13),"") -> 110 | Q13: =IF(ISNUMBER(O13),P13-O13,"") -> 10 | R13: =IF(ISNUMBER(O13),IF(C13="Ручная",IF($S$24>0,$R$24*Q13/$S$24,IF($W$24=2,$R$24,0)),0),"") -> 3.6434783 | S13: =IF(ISNUMBER(O13),O13+R13,"") -> 103.64348 | T13: =IF(ISNUMBER(S13),P13-S13,"") -> 6.3565217 | U13: =IF(COUNT(AG13:AP13)>0,AVERAGE(AG13:AP13),"") -> 104.6 | AG13: =IF(ISNUMBER(E$24),E13,"") -> 102 | AH13: =IF(ISNUMBER(F$24),F13,"") -> 106 | AI13: =IF(ISNUMBER(G$24),G13,"") -> 110 | AJ13: =IF(ISNUMBER(H$24),H13,"") -> 103 | AK13: =IF(ISNUMBER(I$24),I13,"") -> 107 | AL13: =IF(ISNUMBER(J$24),J13,"") -> 101 | AM13: =IF(ISNUMBER(K$24),K13,"") -> 105 | AN13: =IF(ISNUMBER(L$24),L13,"") -> 100 | ... AP13: =IF(ISNUMBER(N$24),N13,"") -> 108 | AQ13: =IF(C13="Ручная",O13,0) -> 100
A14: 3 | B14: Отвесить допустимую партию | C14: Ручная | D14: Масса партии проверена | E14: 22.66 | F14: 23.54 | G14: 22.22 | H14: 23.1 | I14: 22 | J14: 22.88 | K14: 23.76 | L14: 22.44 | M14: 23.32 | N14: 24.2 | O14: =IF(COUNT(AG14:AP14)>0,MIN(AG14:AP14),"") -> 22 | P14: =IF(COUNT(AG14:AP14)>0,MAX(AG14:AP14),"") -> 24.2 | Q14: =IF(ISNUMBER(O14),P14-O14,"") -> 2.2 | R14: =IF(ISNUMBER(O14),IF(C14="Ручная",IF($S$24>0,$R$24*Q14/$S$24,IF($W$24=3,$R$24,0)),0),"") -> 0.80156522 | S14: =IF(ISNUMBER(O14),O14+R14,"") -> 22.801565 | T14: =IF(ISNUMBER(S14),P14-S14,"") -> 1.3984348 | U14: =IF(COUNT(AG14:AP14)>0,AVERAGE(AG14:AP14),"") -> 23.012 | AG14: =IF(ISNUMBER(E$24),E14,"") -> 22.66 | AH14: =IF(ISNUMBER(F$24),F14,"") -> 23.54 | AI14: =IF(ISNUMBER(G$24),G14,"") -> 22.22 | AJ14: =IF(ISNUMBER(H$24),H14,"") -> 23.1 | AK14: =IF(ISNUMBER(I$24),I14,"") -> 22 | AL14: =IF(ISNUMBER(J$24),J14,"") -> 22.88 | AM14: =IF(ISNUMBER(K$24),K14,"") -> 23.76 | AN14: =IF(ISNUMBER(L$24),L14,"") -> 22.44 | ... AP14: =IF(ISNUMBER(N$24),N14,"") -> 24.2 | AQ14: =IF(C14="Ручная",O14,0) -> 22
A15: — | B15: Перейти с партией к SOLIA | C15: Переход | D15: Оператор у SOLIA | E15: 12.6 | F15: 12 | G15: 12.48 | H15: 12.96 | I15: 12.24 | J15: 12.72 | K15: 13.2 | L15: 12.36 | M15: 12.84 | N15: 12.12 | O15: =IF(COUNT(AG15:AP15)>0,MIN(AG15:AP15),"") -> 12 | P15: =IF(COUNT(AG15:AP15)>0,MAX(AG15:AP15),"") -> 13.2 | Q15: =IF(ISNUMBER(O15),P15-O15,"") -> 1.2 | R15: =IF(ISNUMBER(O15),IF(C15="Ручная",IF($S$24>0,$R$24*Q15/$S$24,IF($W$24=4,$R$24,0)),0),"") -> 0 | S15: =IF(ISNUMBER(O15),O15+R15,"") -> 12 | T15: =IF(ISNUMBER(S15),P15-S15,"") -> 1.2 | U15: =IF(COUNT(AG15:AP15)>0,AVERAGE(AG15:AP15),"") -> 12.552 | AG15: =IF(ISNUMBER(E$24),E15,"") -> 12.6 | AH15: =IF(ISNUMBER(F$24),F15,"") -> 12 | AI15: =IF(ISNUMBER(G$24),G15,"") -> 12.48 | AJ15: =IF(ISNUMBER(H$24),H15,"") -> 12.96 | AK15: =IF(ISNUMBER(I$24),I15,"") -> 12.24 | AL15: =IF(ISNUMBER(J$24),J15,"") -> 12.72 | AM15: =IF(ISNUMBER(K$24),K15,"") -> 13.2 | AN15: =IF(ISNUMBER(L$24),L15,"") -> 12.36 | ... AP15: =IF(ISNUMBER(N$24),N15,"") -> 12.12 | AQ15: =IF(C15="Ручная",O15,0) -> 0
A16: 5 | B16: Загрузить, выбрать программу, запустить | C16: Ручная | D16: Программа запущена | E16: 37.8 | F16: 35.7 | G16: 37.1 | H16: 38.5 | I16: 36.05 | J16: 37.45 | K16: 35.35 | L16: 36.75 | M16: 35 | N16: 36.4 | O16: =IF(COUNT(AG16:AP16)>0,MIN(AG16:AP16),"") -> 35 | P16: =IF(COUNT(AG16:AP16)>0,MAX(AG16:AP16),"") -> 38.5 | Q16: =IF(ISNUMBER(O16),P16-O16,"") -> 3.5 | R16: =IF(ISNUMBER(O16),IF(C16="Ручная",IF($S$24>0,$R$24*Q16/$S$24,IF($W$24=5,$R$24,0)),0),"") -> 1.2752174 | S16: =IF(ISNUMBER(O16),O16+R16,"") -> 36.275217 | T16: =IF(ISNUMBER(S16),P16-S16,"") -> 2.2247826 | U16: =IF(COUNT(AG16:AP16)>0,AVERAGE(AG16:AP16),"") -> 36.61 | AG16: =IF(ISNUMBER(E$24),E16,"") -> 37.8 | AH16: =IF(ISNUMBER(F$24),F16,"") -> 35.7 | AI16: =IF(ISNUMBER(G$24),G16,"") -> 37.1 | AJ16: =IF(ISNUMBER(H$24),H16,"") -> 38.5 | AK16: =IF(ISNUMBER(I$24),I16,"") -> 36.05 | AL16: =IF(ISNUMBER(J$24),J16,"") -> 37.45 | AM16: =IF(ISNUMBER(K$24),K16,"") -> 35.35 | AN16: =IF(ISNUMBER(L$24),L16,"") -> 36.75 | ... AP16: =IF(ISNUMBER(N$24),N16,"") -> 36.4 | AQ16: =IF(C16="Ручная",O16,0) -> 35
A17: — | B17: Автоматическая программа / ожидание | C17: Авто/ожидание | D17: Полный цикл программы завершён | E17: ='Ассортимент'!R8 -> 450 | F17: ='Ассортимент'!R8 -> 450 | G17: ='Ассортимент'!R8 -> 450 | H17: ='Ассортимент'!R8 -> 450 | I17: ='Ассортимент'!R8 -> 450 | J17: ='Ассортимент'!R8 -> 450 | K17: ='Ассортимент'!R8 -> 450 | L17: ='Ассортимент'!R8 -> 450 | M17: ='Ассортимент'!R8 -> 450 | N17: ='Ассортимент'!R8 -> 450 | O17: =IF(COUNT(AG17:AP17)>0,MIN(AG17:AP17),"") -> 450 | P17: =IF(COUNT(AG17:AP17)>0,MAX(AG17:AP17),"") -> 450 | Q17: =IF(ISNUMBER(O17),P17-O17,"") -> 0 | R17: =IF(ISNUMBER(O17),IF(C17="Ручная",IF($S$24>0,$R$24*Q17/$S$24,IF($W$24=6,$R$24,0)),0),"") -> 0 | S17: =IF(ISNUMBER(O17),O17+R17,"") -> 450 | T17: =IF(ISNUMBER(S17),P17-S17,"") -> 0 | U17: =IF(COUNT(AG17:AP17)>0,AVERAGE(AG17:AP17),"") -> 450 | AG17: =IF(ISNUMBER(E$24),E17,"") -> 450 | AH17: =IF(ISNUMBER(F$24),F17,"") -> 450 | AI17: =IF(ISNUMBER(G$24),G17,"") -> 450 | AJ17: =IF(ISNUMBER(H$24),H17,"") -> 450 | AK17: =IF(ISNUMBER(I$24),I17,"") -> 450 | AL17: =IF(ISNUMBER(J$24),J17,"") -> 450 | AM17: =IF(ISNUMBER(K$24),K17,"") -> 450 | AN17: =IF(ISNUMBER(L$24),L17,"") -> 450 | ... AP17: =IF(ISNUMBER(N$24),N17,"") -> 450 | AQ17: =IF(C17="Ручная",O17,0) -> 0
A18: 7 | B18: Выгрузить в чистую маркированную тару | C18: Ручная | D18: Выгрузка завершена | E18: 30.3 | F18: 31.5 | G18: 30 | H18: 31.2 | I18: 32.4 | J18: 30.6 | K18: 31.8 | L18: 33 | M18: 30.9 | N18: 32.1 | O18: =IF(COUNT(AG18:AP18)>0,MIN(AG18:AP18),"") -> 30 | P18: =IF(COUNT(AG18:AP18)>0,MAX(AG18:AP18),"") -> 33 | Q18: =IF(ISNUMBER(O18),P18-O18,"") -> 3 | R18: =IF(ISNUMBER(O18),IF(C18="Ручная",IF($S$24>0,$R$24*Q18/$S$24,IF($W$24=7,$R$24,0)),0),"") -> 1.0930435 | S18: =IF(ISNUMBER(O18),O18+R18,"") -> 31.093043 | T18: =IF(ISNUMBER(S18),P18-S18,"") -> 1.9069565 | U18: =IF(COUNT(AG18:AP18)>0,AVERAGE(AG18:AP18),"") -> 31.38 | AG18: =IF(ISNUMBER(E$24),E18,"") -> 30.3 | AH18: =IF(ISNUMBER(F$24),F18,"") -> 31.5 | AI18: =IF(ISNUMBER(G$24),G18,"") -> 30 | AJ18: =IF(ISNUMBER(H$24),H18,"") -> 31.2 | AK18: =IF(ISNUMBER(I$24),I18,"") -> 32.4 | AL18: =IF(ISNUMBER(J$24),J18,"") -> 30.6 | AM18: =IF(ISNUMBER(K$24),K18,"") -> 31.8 | AN18: =IF(ISNUMBER(L$24),L18,"") -> 33 | ... AP18: =IF(ISNUMBER(N$24),N18,"") -> 32.1 | AQ18: =IF(C18="Ручная",O18,0) -> 30
A19: 8 | B19: Проверить качество и маркировку | C19: Ручная | D19: Результат проверки подтверждён | E19: 18.72 | F19: 19.44 | G19: 18.36 | H19: 19.08 | I19: 19.8 | J19: 18.54 | K19: 19.26 | L19: 18.18 | M19: 18.9 | N19: 18 | O19: =IF(COUNT(AG19:AP19)>0,MIN(AG19:AP19),"") -> 18 | P19: =IF(COUNT(AG19:AP19)>0,MAX(AG19:AP19),"") -> 19.8 | Q19: =IF(ISNUMBER(O19),P19-O19,"") -> 1.8 | R19: =IF(ISNUMBER(O19),IF(C19="Ручная",IF($S$24>0,$R$24*Q19/$S$24,IF($W$24=8,$R$24,0)),0),"") -> 0.65582609 | S19: =IF(ISNUMBER(O19),O19+R19,"") -> 18.655826 | T19: =IF(ISNUMBER(S19),P19-S19,"") -> 1.1441739 | U19: =IF(COUNT(AG19:AP19)>0,AVERAGE(AG19:AP19),"") -> 18.828 | AG19: =IF(ISNUMBER(E$24),E19,"") -> 18.72 | AH19: =IF(ISNUMBER(F$24),F19,"") -> 19.44 | AI19: =IF(ISNUMBER(G$24),G19,"") -> 18.36 | AJ19: =IF(ISNUMBER(H$24),H19,"") -> 19.08 | AK19: =IF(ISNUMBER(I$24),I19,"") -> 19.8 | AL19: =IF(ISNUMBER(J$24),J19,"") -> 18.54 | AM19: =IF(ISNUMBER(K$24),K19,"") -> 19.26 | AN19: =IF(ISNUMBER(L$24),L19,"") -> 18.18 | ... AP19: =IF(ISNUMBER(N$24),N19,"") -> 18 | AQ19: =IF(C19="Ручная",O19,0) -> 18
A20: — | B20: Передать в зону чистой продукции | C20: Переход | D20: Партия передана | E20: 10.6 | F20: 11 | G20: 10.3 | H20: 10.7 | I20: 10.1 | J20: 10.5 | K20: 10 | L20: 10.4 | M20: 10.8 | N20: 10.2 | O20: =IF(COUNT(AG20:AP20)>0,MIN(AG20:AP20),"") -> 10 | P20: =IF(COUNT(AG20:AP20)>0,MAX(AG20:AP20),"") -> 11 | Q20: =IF(ISNUMBER(O20),P20-O20,"") -> 1 | R20: =IF(ISNUMBER(O20),IF(C20="Ручная",IF($S$24>0,$R$24*Q20/$S$24,IF($W$24=9,$R$24,0)),0),"") -> 0 | S20: =IF(ISNUMBER(O20),O20+R20,"") -> 10 | T20: =IF(ISNUMBER(S20),P20-S20,"") -> 1 | U20: =IF(COUNT(AG20:AP20)>0,AVERAGE(AG20:AP20),"") -> 10.46 | AG20: =IF(ISNUMBER(E$24),E20,"") -> 10.6 | AH20: =IF(ISNUMBER(F$24),F20,"") -> 11 | AI20: =IF(ISNUMBER(G$24),G20,"") -> 10.3 | AJ20: =IF(ISNUMBER(H$24),H20,"") -> 10.7 | AK20: =IF(ISNUMBER(I$24),I20,"") -> 10.1 | AL20: =IF(ISNUMBER(J$24),J20,"") -> 10.5 | AM20: =IF(ISNUMBER(K$24),K20,"") -> 10 | AN20: =IF(ISNUMBER(L$24),L20,"") -> 10.4 | ... AP20: =IF(ISNUMBER(N$24),N20,"") -> 10.2 | AQ20: =IF(C20="Ручная",O20,0) -> 0
A21: — | B21: Вернуться к началу цикла | C21: Переход | D21: Возврат на исходную позицию | E21: 10.7 | F21: 10.1 | G21: 10.5 | H21: 10 | I21: 10.4 | J21: 10.8 | K21: 10.2 | L21: 10.6 | M21: 11 | N21: 10.3 | O21: =IF(COUNT(AG21:AP21)>0,MIN(AG21:AP21),"") -> 10 | P21: =IF(COUNT(AG21:AP21)>0,MAX(AG21:AP21),"") -> 11 | Q21: =IF(ISNUMBER(O21),P21-O21,"") -> 1 | R21: =IF(ISNUMBER(O21),IF(C21="Ручная",IF($S$24>0,$R$24*Q21/$S$24,IF($W$24=10,$R$24,0)),0),"") -> 0 | S21: =IF(ISNUMBER(O21),O21+R21,"") -> 10 | T21: =IF(ISNUMBER(S21),P21-S21,"") -> 1 | U21: =IF(COUNT(AG21:AP21)>0,AVERAGE(AG21:AP21),"") -> 10.46 | AG21: =IF(ISNUMBER(E$24),E21,"") -> 10.7 | AH21: =IF(ISNUMBER(F$24),F21,"") -> 10.1 | AI21: =IF(ISNUMBER(G$24),G21,"") -> 10.5 | AJ21: =IF(ISNUMBER(H$24),H21,"") -> 10 | AK21: =IF(ISNUMBER(I$24),I21,"") -> 10.4 | AL21: =IF(ISNUMBER(J$24),J21,"") -> 10.8 | AM21: =IF(ISNUMBER(K$24),K21,"") -> 10.2 | AN21: =IF(ISNUMBER(L$24),L21,"") -> 10.6 | ... AP21: =IF(ISNUMBER(N$24),N21,"") -> 10.3 | AQ21: =IF(C21="Ручная",O21,0) -> 0
A22: — | B22: Внеплановый поиск тары / ожидание | C22: Потери | D22: Причина задержки устранена | E22: 12 | F22: 12.48 | G22: 12.96 | H22: 12.24 | I22: 12.72 | J22: 13.2 | K22: 12.36 | L22: 12.84 | M22: 12.12 | N22: 12.6 | O22: =IF(COUNT(AG22:AP22)>0,MIN(AG22:AP22),"") -> 12 | P22: =IF(COUNT(AG22:AP22)>0,MAX(AG22:AP22),"") -> 13.2 | Q22: =IF(ISNUMBER(O22),P22-O22,"") -> 1.2 | R22: =IF(ISNUMBER(O22),IF(C22="Ручная",IF($S$24>0,$R$24*Q22/$S$24,IF($W$24=11,$R$24,0)),0),"") -> 0 | S22: =IF(ISNUMBER(O22),O22+R22,"") -> 12 | T22: =IF(ISNUMBER(S22),P22-S22,"") -> 1.2 | U22: =IF(COUNT(AG22:AP22)>0,AVERAGE(AG22:AP22),"") -> 12.552 | AG22: =IF(ISNUMBER(E$24),E22,"") -> 12 | AH22: =IF(ISNUMBER(F$24),F22,"") -> 12.48 | AI22: =IF(ISNUMBER(G$24),G22,"") -> 12.96 | AJ22: =IF(ISNUMBER(H$24),H22,"") -> 12.24 | AK22: =IF(ISNUMBER(I$24),I22,"") -> 12.72 | AL22: =IF(ISNUMBER(J$24),J22,"") -> 13.2 | AM22: =IF(ISNUMBER(K$24),K22,"") -> 12.36 | AN22: =IF(ISNUMBER(L$24),L22,"") -> 12.84 | ... AP22: =IF(ISNUMBER(N$24),N22,"") -> 12.6 | AQ22: =IF(C22="Ручная",O22,0) -> 0
B23: ИТОГИ: все элементы цикла | E23: =IF(COUNT(E12:E22)=11,SUM(E12:E22),"") -> 732.38 | F23: =IF(COUNT(F12:F22)=11,SUM(F12:F22),"") -> 737.76 | G23: =IF(COUNT(G12:G22)=11,SUM(G12:G22),"") -> 740.92 | H23: =IF(COUNT(H12:H22)=11,SUM(H12:H22),"") -> 736.28 | I23: =IF(COUNT(I12:I22)=11,SUM(I12:I22),"") -> 739.21 | J23: =IF(COUNT(J12:J22)=11,SUM(J12:J22),"") -> 735.19 | K23: =IF(COUNT(K12:K22)=11,SUM(K12:K22),"") -> 736.68 | L23: =IF(COUNT(L12:L22)=11,SUM(L12:L22),"") -> 733.32 | ... U23: =IF(COUNT(U12:U22)=11,SUM(U12:U22),"") -> 736.604
B24: ТОЛЬКО полные учтённые циклы | E24: =IF(AND(E10=1,COUNT(E12:E22)=11,MIN(E12:E22)>=0),E23,"") -> 732.38 | F24: =IF(AND(F10=1,COUNT(F12:F22)=11,MIN(F12:F22)>=0),F23,"") -> 737.76 | G24: =IF(AND(G10=1,COUNT(G12:G22)=11,MIN(G12:G22)>=0),G23,"") -> 740.92 | H24: =IF(AND(H10=1,COUNT(H12:H22)=11,MIN(H12:H22)>=0),H23,"") -> 736.28 | I24: =IF(AND(I10=1,COUNT(I12:I22)=11,MIN(I12:I22)>=0),I23,"") -> 739.21 | J24: =IF(AND(J10=1,COUNT(J12:J22)=11,MIN(J12:J22)>=0),J23,"") -> 735.19 | K24: =IF(AND(K10=1,COUNT(K12:K22)=11,MIN(K12:K22)>=0),K23,"") -> 736.68 | L24: =IF(AND(L10=1,COUNT(L12:L22)=11,MIN(L12:L22)>=0),L23,"") -> 733.32 | ... N24: =IF(AND(N10=1,COUNT(N12:N22)=11,MIN(N12:N22)>=0),N23,"") -> 740.17 | O24: =IF(COUNT(E24:N24)>0,MIN(E24:N24),"") -> 732.38 | P24: =IF(COUNT(E24:N24)>0,MAX(E24:N24),"") -> 740.92 | Q24: =IF(ISNUMBER(O24),P24-O24,"") -> 8.54 | R24: =IF(ISNUMBER(O24),MAX(0,O24-O23),"") -> 8.38 | S24: =SUMIF(C12:C22,"Ручная",Q12:Q22) -> 23 | T24: =COUNT(E24:N24) -> 10 | U24: =IF(COUNT(E24:N24)>0,AVERAGE(E24:N24),"") -> 736.604 | V24: =IF(ISNUMBER(O24),S23-O24,"") -> 0 | W24: =MATCH(MAX(AQ12:AQ22),AQ12:AQ22,0) -> 2 | X24: =IF(T24=0,"НЕТ ЗАМЕРОВ",IF(T24<10,"МЕНЕЕ 10 ЦИКЛОВ",IF(ABS(V24)<0.000001,"ОК","ОШИБКА РЕГУЛИРОВКИ"))) -> ОК
A25: В строке учтённых циклов: O = T min; P = T max; Q = размах цикла; R = T min − сумма t min; S = сумма размахов ручных элементов; T = число циклов; U = среднее; V = сумма t отрег − T min (должно быть 0).
A28: 02. Базилик · ДО · 10 демонстрационных циклов, заменить реальными
A29: ="Масса замера, кг: "&'Ассортимент'!J9&". Все замеры одной партии/исполнителя/условий. Основание: "&'Ввод'!B14 -> Масса замера, кг: 1.5. Все замеры одной партии/исполнителя/условий. Основание: ДЕМО: синтетические замеры; заменить фактическими
A30: № | B30: Рабочий элемент | C30: Тип | D30: Точка отсчёта | E30: 1 | F30: 2 | G30: 3 | H30: 4 | I30: 5 | J30: 6 | K30: 7 | L30: 8 | M30: 9 | N30: 10 | O30: t min | P30: t max | Q30: Размах | R30: Рег. с | S30: t отрег. | T30: Колебания | U30: Среднее | V30: Контроль | W30: Служебно | X30: Статус
B31: Учитывать цикл: 1 / 0 | E31: 1 | F31: 1 | G31: 1 | H31: 1 | I31: 1 | J31: 1 | K31: 1 | L31: 1 | M31: 1 | N31: 1
B32: Причина исключения / условия | E32: ДЕМО | F32: ДЕМО | G32: ДЕМО | H32: ДЕМО | I32: ДЕМО | J32: ДЕМО | K32: ДЕМО | L32: ДЕМО | M32: ДЕМО | N32: ДЕМО
A33: 1 | B33: Осмотреть упаковку и сырьё | C33: Ручная | D33: Осмотр партии завершён | E33: 26 | F33: 27 | G33: 25.5 | H33: 26.5 | I33: 27.5 | J33: 25.75 | K33: 26.75 | L33: 25.25 | M33: 26.25 | N33: 25 | O33: =IF(COUNT(AG33:AP33)>0,MIN(AG33:AP33),"") -> 25 | P33: =IF(COUNT(AG33:AP33)>0,MAX(AG33:AP33),"") -> 27.5 | Q33: =IF(ISNUMBER(O33),P33-O33,"") -> 2.5 | R33: =IF(ISNUMBER(O33),IF(C33="Ручная",IF($S$45>0,$R$45*Q33/$S$45,IF($W$45=1,$R$45,0)),0),"") -> 0.89375 | S33: =IF(ISNUMBER(O33),O33+R33,"") -> 25.89375 | T33: =IF(ISNUMBER(S33),P33-S33,"") -> 1.60625 | U33: =IF(COUNT(AG33:AP33)>0,AVERAGE(AG33:AP33),"") -> 26.15 | AG33: =IF(ISNUMBER(E$45),E33,"") -> 26 | AH33: =IF(ISNUMBER(F$45),F33,"") -> 27 | AI33: =IF(ISNUMBER(G$45),G33,"") -> 25.5 | AJ33: =IF(ISNUMBER(H$45),H33,"") -> 26.5 | AK33: =IF(ISNUMBER(I$45),I33,"") -> 27.5 | AL33: =IF(ISNUMBER(J$45),J33,"") -> 25.75 | AM33: =IF(ISNUMBER(K$45),K33,"") -> 26.75 | AN33: =IF(ISNUMBER(L$45),L33,"") -> 25.25 | ... AP33: =IF(ISNUMBER(N$45),N33,"") -> 25 | AQ33: =IF(C33="Ручная",O33,0) -> 25
A34: 2 | B34: Отсортировать / подготовить сырьё | C34: Ручная | D34: Подготовленное сырьё отложено | E34: 116.6 | F34: 121 | G34: 113.3 | H34: 117.7 | I34: 111.1 | J34: 115.5 | K34: 110 | L34: 114.4 | M34: 118.8 | N34: 112.2 | O34: =IF(COUNT(AG34:AP34)>0,MIN(AG34:AP34),"") -> 110 | P34: =IF(COUNT(AG34:AP34)>0,MAX(AG34:AP34),"") -> 121 | Q34: =IF(ISNUMBER(O34),P34-O34,"") -> 11 | R34: =IF(ISNUMBER(O34),IF(C34="Ручная",IF($S$45>0,$R$45*Q34/$S$45,IF($W$45=2,$R$45,0)),0),"") -> 3.9325 | S34: =IF(ISNUMBER(O34),O34+R34,"") -> 113.9325 | T34: =IF(ISNUMBER(S34),P34-S34,"") -> 7.0675 | U34: =IF(COUNT(AG34:AP34)>0,AVERAGE(AG34:AP34),"") -> 115.06 | AG34: =IF(ISNUMBER(E$45),E34,"") -> 116.6 | AH34: =IF(ISNUMBER(F$45),F34,"") -> 121 | AI34: =IF(ISNUMBER(G$45),G34,"") -> 113.3 | AJ34: =IF(ISNUMBER(H$45),H34,"") -> 117.7 | AK34: =IF(ISNUMBER(I$45),I34,"") -> 111.1 | AL34: =IF(ISNUMBER(J$45),J34,"") -> 115.5 | AM34: =IF(ISNUMBER(K$45),K34,"") -> 110 | AN34: =IF(ISNUMBER(L$45),L34,"") -> 114.4 | ... AP34: =IF(ISNUMBER(N$45),N34,"") -> 112.2 | AQ34: =IF(C34="Ручная",O34,0) -> 110
A35: 3 | B35: Отвесить допустимую партию | C35: Ручная | D35: Масса партии проверена | E35: 23.54 | F35: 22.22 | G35: 23.1 | H35: 22 | I35: 22.88 | J35: 23.76 | K35: 22.44 | L35: 23.32 | M35: 24.2 | N35: 22.66 | O35: =IF(COUNT(AG35:AP35)>0,MIN(AG35:AP35),"") -> 22 | P35: =IF(COUNT(AG35:AP35)>0,MAX(AG35:AP35),"") -> 24.2 | Q35: =IF(ISNUMBER(O35),P35-O35,"") -> 2.2 | R35: =IF(ISNUMBER(O35),IF(C35="Ручная",IF($S$45>0,$R$45*Q35/$S$45,IF($W$45=3,$R$45,0)),0),"") -> 0.7865 | S35: =IF(ISNUMBER(O35),O35+R35,"") -> 22.7865 | T35: =IF(ISNUMBER(S35),P35-S35,"") -> 1.4135 | U35: =IF(COUNT(AG35:AP35)>0,AVERAGE(AG35:AP35),"") -> 23.012 | AG35: =IF(ISNUMBER(E$45),E35,"") -> 23.54 | AH35: =IF(ISNUMBER(F$45),F35,"") -> 22.22 | AI35: =IF(ISNUMBER(G$45),G35,"") -> 23.1 | AJ35: =IF(ISNUMBER(H$45),H35,"") -> 22 | AK35: =IF(ISNUMBER(I$45),I35,"") -> 22.88 | AL35: =IF(ISNUMBER(J$45),J35,"") -> 23.76 | AM35: =IF(ISNUMBER(K$45),K35,"") -> 22.44 | AN35: =IF(ISNUMBER(L$45),L35,"") -> 23.32 | ... AP35: =IF(ISNUMBER(N$45),N35,"") -> 22.66 | AQ35: =IF(C35="Ручная",O35,0) -> 22
A36: — | B36: Перейти с партией к SOLIA | C36: Переход | D36: Оператор у SOLIA | E36: 12 | F36: 12.48 | G36: 12.96 | H36: 12.24 | I36: 12.72 | J36: 13.2 | K36: 12.36 | L36: 12.84 | M36: 12.12 | N36: 12.6 | O36: =IF(COUNT(AG36:AP36)>0,MIN(AG36:AP36),"") -> 12 | P36: =IF(COUNT(AG36:AP36)>0,MAX(AG36:AP36),"") -> 13.2 | Q36: =IF(ISNUMBER(O36),P36-O36,"") -> 1.2 | R36: =IF(ISNUMBER(O36),IF(C36="Ручная",IF($S$45>0,$R$45*Q36/$S$45,IF($W$45=4,$R$45,0)),0),"") -> 0 | S36: =IF(ISNUMBER(O36),O36+R36,"") -> 12 | T36: =IF(ISNUMBER(S36),P36-S36,"") -> 1.2 | U36: =IF(COUNT(AG36:AP36)>0,AVERAGE(AG36:AP36),"") -> 12.552 | AG36: =IF(ISNUMBER(E$45),E36,"") -> 12 | AH36: =IF(ISNUMBER(F$45),F36,"") -> 12.48 | AI36: =IF(ISNUMBER(G$45),G36,"") -> 12.96 | AJ36: =IF(ISNUMBER(H$45),H36,"") -> 12.24 | AK36: =IF(ISNUMBER(I$45),I36,"") -> 12.72 | AL36: =IF(ISNUMBER(J$45),J36,"") -> 13.2 | AM36: =IF(ISNUMBER(K$45),K36,"") -> 12.36 | AN36: =IF(ISNUMBER(L$45),L36,"") -> 12.84 | ... AP36: =IF(ISNUMBER(N$45),N36,"") -> 12.6 | AQ36: =IF(C36="Ручная",O36,0) -> 0
A37: 5 | B37: Загрузить, выбрать программу, запустить | C37: Ручная | D37: Программа запущена | E37: 35.7 | F37: 37.1 | G37: 38.5 | H37: 36.05 | I37: 37.45 | J37: 35.35 | K37: 36.75 | L37: 35 | M37: 36.4 | N37: 37.8 | O37: =IF(COUNT(AG37:AP37)>0,MIN(AG37:AP37),"") -> 35 | P37: =IF(COUNT(AG37:AP37)>0,MAX(AG37:AP37),"") -> 38.5 | Q37: =IF(ISNUMBER(O37),P37-O37,"") -> 3.5 | R37: =IF(ISNUMBER(O37),IF(C37="Ручная",IF($S$45>0,$R$45*Q37/$S$45,IF($W$45=5,$R$45,0)),0),"") -> 1.25125 | S37: =IF(ISNUMBER(O37),O37+R37,"") -> 36.25125 | T37: =IF(ISNUMBER(S37),P37-S37,"") -> 2.24875 | U37: =IF(COUNT(AG37:AP37)>0,AVERAGE(AG37:AP37),"") -> 36.61 | AG37: =IF(ISNUMBER(E$45),E37,"") -> 35.7 | AH37: =IF(ISNUMBER(F$45),F37,"") -> 37.1 | AI37: =IF(ISNUMBER(G$45),G37,"") -> 38.5 | AJ37: =IF(ISNUMBER(H$45),H37,"") -> 36.05 | AK37: =IF(ISNUMBER(I$45),I37,"") -> 37.45 | AL37: =IF(ISNUMBER(J$45),J37,"") -> 35.35 | AM37: =IF(ISNUMBER(K$45),K37,"") -> 36.75 | AN37: =IF(ISNUMBER(L$45),L37,"") -> 35 | ... AP37: =IF(ISNUMBER(N$45),N37,"") -> 37.8 | AQ37: =IF(C37="Ручная",O37,0) -> 35
A38: — | B38: Автоматическая программа / ожидание | C38: Авто/ожидание | D38: Полный цикл программы завершён | E38: ='Ассортимент'!R9 -> 450 | F38: ='Ассортимент'!R9 -> 450 | G38: ='Ассортимент'!R9 -> 450 | H38: ='Ассортимент'!R9 -> 450 | I38: ='Ассортимент'!R9 -> 450 | J38: ='Ассортимент'!R9 -> 450 | K38: ='Ассортимент'!R9 -> 450 | L38: ='Ассортимент'!R9 -> 450 | M38: ='Ассортимент'!R9 -> 450 | N38: ='Ассортимент'!R9 -> 450 | O38: =IF(COUNT(AG38:AP38)>0,MIN(AG38:AP38),"") -> 450 | P38: =IF(COUNT(AG38:AP38)>0,MAX(AG38:AP38),"") -> 450 | Q38: =IF(ISNUMBER(O38),P38-O38,"") -> 0 | R38: =IF(ISNUMBER(O38),IF(C38="Ручная",IF($S$45>0,$R$45*Q38/$S$45,IF($W$45=6,$R$45,0)),0),"") -> 0 | S38: =IF(ISNUMBER(O38),O38+R38,"") -> 450 | T38: =IF(ISNUMBER(S38),P38-S38,"") -> 0 | U38: =IF(COUNT(AG38:AP38)>0,AVERAGE(AG38:AP38),"") -> 450 | AG38: =IF(ISNUMBER(E$45),E38,"") -> 450 | AH38: =IF(ISNUMBER(F$45),F38,"") -> 450 | AI38: =IF(ISNUMBER(G$45),G38,"") -> 450 | AJ38: =IF(ISNUMBER(H$45),H38,"") -> 450 | AK38: =IF(ISNUMBER(I$45),I38,"") -> 450 | AL38: =IF(ISNUMBER(J$45),J38,"") -> 450 | AM38: =IF(ISNUMBER(K$45),K38,"") -> 450 | AN38: =IF(ISNUMBER(L$45),L38,"") -> 450 | ... AP38: =IF(ISNUMBER(N$45),N38,"") -> 450 | AQ38: =IF(C38="Ручная",O38,0) -> 0
A39: 7 | B39: Выгрузить в чистую маркированную тару | C39: Ручная | D39: Выгрузка завершена | E39: 31.5 | F39: 30 | G39: 31.2 | H39: 32.4 | I39: 30.6 | J39: 31.8 | K39: 33 | L39: 30.9 | M39: 32.1 | N39: 30.3 | O39: =IF(COUNT(AG39:AP39)>0,MIN(AG39:AP39),"") -> 30 | P39: =IF(COUNT(AG39:AP39)>0,MAX(AG39:AP39),"") -> 33 | Q39: =IF(ISNUMBER(O39),P39-O39,"") -> 3 | R39: =IF(ISNUMBER(O39),IF(C39="Ручная",IF($S$45>0,$R$45*Q39/$S$45,IF($W$45=7,$R$45,0)),0),"") -> 1.0725 | S39: =IF(ISNUMBER(O39),O39+R39,"") -> 31.0725 | T39: =IF(ISNUMBER(S39),P39-S39,"") -> 1.9275 | U39: =IF(COUNT(AG39:AP39)>0,AVERAGE(AG39:AP39),"") -> 31.38 | AG39: =IF(ISNUMBER(E$45),E39,"") -> 31.5 | AH39: =IF(ISNUMBER(F$45),F39,"") -> 30 | AI39: =IF(ISNUMBER(G$45),G39,"") -> 31.2 | AJ39: =IF(ISNUMBER(H$45),H39,"") -> 32.4 | AK39: =IF(ISNUMBER(I$45),I39,"") -> 30.6 | AL39: =IF(ISNUMBER(J$45),J39,"") -> 31.8 | AM39: =IF(ISNUMBER(K$45),K39,"") -> 33 | AN39: =IF(ISNUMBER(L$45),L39,"") -> 30.9 | ... AP39: =IF(ISNUMBER(N$45),N39,"") -> 30.3 | AQ39: =IF(C39="Ручная",O39,0) -> 30
A40: 8 | B40: Проверить качество и маркировку | C40: Ручная | D40: Результат проверки подтверждён | E40: 19.44 | F40: 18.36 | G40: 19.08 | H40: 19.8 | I40: 18.54 | J40: 19.26 | K40: 18.18 | L40: 18.9 | M40: 18 | N40: 18.72 | O40: =IF(COUNT(AG40:AP40)>0,MIN(AG40:AP40),"") -> 18 | P40: =IF(COUNT(AG40:AP40)>0,MAX(AG40:AP40),"") -> 19.8 | Q40: =IF(ISNUMBER(O40),P40-O40,"") -> 1.8 | R40: =IF(ISNUMBER(O40),IF(C40="Ручная",IF($S$45>0,$R$45*Q40/$S$45,IF($W$45=8,$R$45,0)),0),"") -> 0.6435 | S40: =IF(ISNUMBER(O40),O40+R40,"") -> 18.6435 | T40: =IF(ISNUMBER(S40),P40-S40,"") -> 1.1565 | U40: =IF(COUNT(AG40:AP40)>0,AVERAGE(AG40:AP40),"") -> 18.828 | AG40: =IF(ISNUMBER(E$45),E40,"") -> 19.44 | AH40: =IF(ISNUMBER(F$45),F40,"") -> 18.36 | AI40: =IF(ISNUMBER(G$45),G40,"") -> 19.08 | AJ40: =IF(ISNUMBER(H$45),H40,"") -> 19.8 | AK40: =IF(ISNUMBER(I$45),I40,"") -> 18.54 | AL40: =IF(ISNUMBER(J$45),J40,"") -> 19.26 | AM40: =IF(ISNUMBER(K$45),K40,"") -> 18.18 | AN40: =IF(ISNUMBER(L$45),L40,"") -> 18.9 | ... AP40: =IF(ISNUMBER(N$45),N40,"") -> 18.72 | AQ40: =IF(C40="Ручная",O40,0) -> 18
A41: — | B41: Передать в зону чистой продукции | C41: Переход | D41: Партия передана | E41: 11 | F41: 10.3 | G41: 10.7 | H41: 10.1 | I41: 10.5 | J41: 10 | K41: 10.4 | L41: 10.8 | M41: 10.2 | N41: 10.6 | O41: =IF(COUNT(AG41:AP41)>0,MIN(AG41:AP41),"") -> 10 | P41: =IF(COUNT(AG41:AP41)>0,MAX(AG41:AP41),"") -> 11 | Q41: =IF(ISNUMBER(O41),P41-O41,"") -> 1 | R41: =IF(ISNUMBER(O41),IF(C41="Ручная",IF($S$45>0,$R$45*Q41/$S$45,IF($W$45=9,$R$45,0)),0),"") -> 0 | S41: =IF(ISNUMBER(O41),O41+R41,"") -> 10 | T41: =IF(ISNUMBER(S41),P41-S41,"") -> 1 | U41: =IF(COUNT(AG41:AP41)>0,AVERAGE(AG41:AP41),"") -> 10.46 | AG41: =IF(ISNUMBER(E$45),E41,"") -> 11 | AH41: =IF(ISNUMBER(F$45),F41,"") -> 10.3 | AI41: =IF(ISNUMBER(G$45),G41,"") -> 10.7 | AJ41: =IF(ISNUMBER(H$45),H41,"") -> 10.1 | AK41: =IF(ISNUMBER(I$45),I41,"") -> 10.5 | AL41: =IF(ISNUMBER(J$45),J41,"") -> 10 | AM41: =IF(ISNUMBER(K$45),K41,"") -> 10.4 | AN41: =IF(ISNUMBER(L$45),L41,"") -> 10.8 | ... AP41: =IF(ISNUMBER(N$45),N41,"") -> 10.6 | AQ41: =IF(C41="Ручная",O41,0) -> 0
A42: — | B42: Вернуться к началу цикла | C42: Переход | D42: Возврат на исходную позицию | E42: 10.1 | F42: 10.5 | G42: 10 | H42: 10.4 | I42: 10.8 | J42: 10.2 | K42: 10.6 | L42: 11 | M42: 10.3 | N42: 10.7 | O42: =IF(COUNT(AG42:AP42)>0,MIN(AG42:AP42),"") -> 10 | P42: =IF(COUNT(AG42:AP42)>0,MAX(AG42:AP42),"") -> 11 | Q42: =IF(ISNUMBER(O42),P42-O42,"") -> 1 | R42: =IF(ISNUMBER(O42),IF(C42="Ручная",IF($S$45>0,$R$45*Q42/$S$45,IF($W$45=10,$R$45,0)),0),"") -> 0 | S42: =IF(ISNUMBER(O42),O42+R42,"") -> 10 | T42: =IF(ISNUMBER(S42),P42-S42,"") -> 1 | U42: =IF(COUNT(AG42:AP42)>0,AVERAGE(AG42:AP42),"") -> 10.46 | AG42: =IF(ISNUMBER(E$45),E42,"") -> 10.1 | AH42: =IF(ISNUMBER(F$45),F42,"") -> 10.5 | AI42: =IF(ISNUMBER(G$45),G42,"") -> 10 | AJ42: =IF(ISNUMBER(H$45),H42,"") -> 10.4 | AK42: =IF(ISNUMBER(I$45),I42,"") -> 10.8 | AL42: =IF(ISNUMBER(J$45),J42,"") -> 10.2 | AM42: =IF(ISNUMBER(K$45),K42,"") -> 10.6 | AN42: =IF(ISNUMBER(L$45),L42,"") -> 11 | ... AP42: =IF(ISNUMBER(N$45),N42,"") -> 10.7 | AQ42: =IF(C42="Ручная",O42,0) -> 0
A43: — | B43: Внеплановый поиск тары / ожидание | C43: Потери | D43: Причина задержки устранена | E43: 12.48 | F43: 12.96 | G43: 12.24 | H43: 12.72 | I43: 13.2 | J43: 12.36 | K43: 12.84 | L43: 12.12 | M43: 12.6 | N43: 12 | O43: =IF(COUNT(AG43:AP43)>0,MIN(AG43:AP43),"") -> 12 | P43: =IF(COUNT(AG43:AP43)>0,MAX(AG43:AP43),"") -> 13.2 | Q43: =IF(ISNUMBER(O43),P43-O43,"") -> 1.2 | R43: =IF(ISNUMBER(O43),IF(C43="Ручная",IF($S$45>0,$R$45*Q43/$S$45,IF($W$45=11,$R$45,0)),0),"") -> 0 | S43: =IF(ISNUMBER(O43),O43+R43,"") -> 12 | T43: =IF(ISNUMBER(S43),P43-S43,"") -> 1.2 | U43: =IF(COUNT(AG43:AP43)>0,AVERAGE(AG43:AP43),"") -> 12.552 | AG43: =IF(ISNUMBER(E$45),E43,"") -> 12.48 | AH43: =IF(ISNUMBER(F$45),F43,"") -> 12.96 | AI43: =IF(ISNUMBER(G$45),G43,"") -> 12.24 | AJ43: =IF(ISNUMBER(H$45),H43,"") -> 12.72 | AK43: =IF(ISNUMBER(I$45),I43,"") -> 13.2 | AL43: =IF(ISNUMBER(J$45),J43,"") -> 12.36 | AM43: =IF(ISNUMBER(K$45),K43,"") -> 12.84 | AN43: =IF(ISNUMBER(L$45),L43,"") -> 12.12 | ... AP43: =IF(ISNUMBER(N$45),N43,"") -> 12 | AQ43: =IF(C43="Ручная",O43,0) -> 0
B44: ИТОГИ: все элементы цикла | E44: =IF(COUNT(E33:E43)=11,SUM(E33:E43),"") -> 748.36 | F44: =IF(COUNT(F33:F43)=11,SUM(F33:F43),"") -> 751.92 | G44: =IF(COUNT(G33:G43)=11,SUM(G33:G43),"") -> 746.58 | H44: =IF(COUNT(H33:H43)=11,SUM(H33:H43),"") -> 749.91 | I44: =IF(COUNT(I33:I43)=11,SUM(I33:I43),"") -> 745.29 | J44: =IF(COUNT(J33:J43)=11,SUM(J33:J43),"") -> 747.18 | K44: =IF(COUNT(K33:K43)=11,SUM(K33:K43),"") -> 743.32 | L44: =IF(COUNT(L33:L43)=11,SUM(L33:L43),"") -> 744.53 | ... U44: =IF(COUNT(U33:U43)=11,SUM(U33:U43),"") -> 747.064
B45: ТОЛЬКО полные учтённые циклы | E45: =IF(AND(E31=1,COUNT(E33:E43)=11,MIN(E33:E43)>=0),E44,"") -> 748.36 | F45: =IF(AND(F31=1,COUNT(F33:F43)=11,MIN(F33:F43)>=0),F44,"") -> 751.92 | G45: =IF(AND(G31=1,COUNT(G33:G43)=11,MIN(G33:G43)>=0),G44,"") -> 746.58 | H45: =IF(AND(H31=1,COUNT(H33:H43)=11,MIN(H33:H43)>=0),H44,"") -> 749.91 | I45: =IF(AND(I31=1,COUNT(I33:I43)=11,MIN(I33:I43)>=0),I44,"") -> 745.29 | J45: =IF(AND(J31=1,COUNT(J33:J43)=11,MIN(J33:J43)>=0),J44,"") -> 747.18 | K45: =IF(AND(K31=1,COUNT(K33:K43)=11,MIN(K33:K43)>=0),K44,"") -> 743.32 | L45: =IF(AND(L31=1,COUNT(L33:L43)=11,MIN(L33:L43)>=0),L44,"") -> 744.53 | ... N45: =IF(AND(N31=1,COUNT(N33:N43)=11,MIN(N33:N43)>=0),N44,"") -> 742.58 | O45: =IF(COUNT(E45:N45)>0,MIN(E45:N45),"") -> 742.58 | P45: =IF(COUNT(E45:N45)>0,MAX(E45:N45),"") -> 751.92 | Q45: =IF(ISNUMBER(O45),P45-O45,"") -> 9.34 | R45: =IF(ISNUMBER(O45),MAX(0,O45-O44),"") -> 8.58 | S45: =SUMIF(C33:C43,"Ручная",Q33:Q43) -> 24 | T45: =COUNT(E45:N45) -> 10 | U45: =IF(COUNT(E45:N45)>0,AVERAGE(E45:N45),"") -> 747.064 | V45: =IF(ISNUMBER(O45),S44-O45,"") -> 0 | W45: =MATCH(MAX(AQ33:AQ43),AQ33:AQ43,0) -> 2 | X45: =IF(T45=0,"НЕТ ЗАМЕРОВ",IF(T45<10,"МЕНЕЕ 10 ЦИКЛОВ",IF(ABS(V45)<0.000001,"ОК","ОШИБКА РЕГУЛИРОВКИ"))) -> ОК
A46: В строке учтённых циклов: O = T min; P = T max; Q = размах цикла; R = T min − сумма t min; S = сумма размахов ручных элементов; T = число циклов; U = среднее; V = сумма t отрег − T min (должно быть 0).
A49: 03. Петрушка · ДО · 10 демонстрационных циклов, заменить реальными
A50: ="Масса замера, кг: "&'Ассортимент'!J10&". Все замеры одной партии/исполнителя/условий. Основание: "&'Ввод'!B14 -> Масса замера, кг: 1.5. Все замеры одной партии/исполнителя/условий. Основание: ДЕМО: синтетические замеры; заменить фактическими
A51: № | B51: Рабочий элемент | C51: Тип | D51: Точка отсчёта | E51: 1 | F51: 2 | G51: 3 | H51: 4 | I51: 5 | J51: 6 | K51: 7 | L51: 8 | M51: 9 | N51: 10 | O51: t min | P51: t max | Q51: Размах | R51: Рег. с | S51: t отрег. | T51: Колебания | U51: Среднее | V51: Контроль | W51: Служебно | X51: Статус
B52: Учитывать цикл: 1 / 0 | E52: 1 | F52: 1 | G52: 1 | H52: 1 | I52: 1 | J52: 1 | K52: 1 | L52: 1 | M52: 1 | N52: 1
B53: Причина исключения / условия | E53: ДЕМО | F53: ДЕМО | G53: ДЕМО | H53: ДЕМО | I53: ДЕМО | J53: ДЕМО | K53: ДЕМО | L53: ДЕМО | M53: ДЕМО | N53: ДЕМО
A54: 1 | B54: Осмотреть упаковку и сырьё | C54: Ручная | D54: Осмотр партии завершён | E54: 27 | F54: 25.5 | G54: 26.5 | H54: 27.5 | I54: 25.75 | J54: 26.75 | K54: 25.25 | L54: 26.25 | M54: 25 | N54: 26 | O54: =IF(COUNT(AG54:AP54)>0,MIN(AG54:AP54),"") -> 25 | P54: =IF(COUNT(AG54:AP54)>0,MAX(AG54:AP54),"") -> 27.5 | Q54: =IF(ISNUMBER(O54),P54-O54,"") -> 2.5 | R54: =IF(ISNUMBER(O54),IF(C54="Ручная",IF($S$66>0,$R$66*Q54/$S$66,IF($W$66=1,$R$66,0)),0),"") -> 0.878 | S54: =IF(ISNUMBER(O54),O54+R54,"") -> 25.878 | T54: =IF(ISNUMBER(S54),P54-S54,"") -> 1.622 | U54: =IF(COUNT(AG54:AP54)>0,AVERAGE(AG54:AP54),"") -> 26.15 | AG54: =IF(ISNUMBER(E$66),E54,"") -> 27 | AH54: =IF(ISNUMBER(F$66),F54,"") -> 25.5 | AI54: =IF(ISNUMBER(G$66),G54,"") -> 26.5 | AJ54: =IF(ISNUMBER(H$66),H54,"") -> 27.5 | AK54: =IF(ISNUMBER(I$66),I54,"") -> 25.75 | AL54: =IF(ISNUMBER(J$66),J54,"") -> 26.75 | AM54: =IF(ISNUMBER(K$66),K54,"") -> 25.25 | AN54: =IF(ISNUMBER(L$66),L54,"") -> 26.25 | ... AP54: =IF(ISNUMBER(N$66),N54,"") -> 26 | AQ54: =IF(C54="Ручная",O54,0) -> 25
A55: 2 | B55: Отсортировать / подготовить сырьё | C55: Ручная | D55: Подготовленное сырьё отложено | E55: 132 | F55: 123.6 | G55: 128.4 | H55: 121.2 | I55: 126 | J55: 120 | K55: 124.8 | L55: 129.6 | M55: 122.4 | N55: 127.2 | O55: =IF(COUNT(AG55:AP55)>0,MIN(AG55:AP55),"") -> 120 | P55: =IF(COUNT(AG55:AP55)>0,MAX(AG55:AP55),"") -> 132 | Q55: =IF(ISNUMBER(O55),P55-O55,"") -> 12 | R55: =IF(ISNUMBER(O55),IF(C55="Ручная",IF($S$66>0,$R$66*Q55/$S$66,IF($W$66=2,$R$66,0)),0),"") -> 4.2144 | S55: =IF(ISNUMBER(O55),O55+R55,"") -> 124.2144 | T55: =IF(ISNUMBER(S55),P55-S55,"") -> 7.7856 | U55: =IF(COUNT(AG55:AP55)>0,AVERAGE(AG55:AP55),"") -> 125.52 | AG55: =IF(ISNUMBER(E$66),E55,"") -> 132 | AH55: =IF(ISNUMBER(F$66),F55,"") -> 123.6 | AI55: =IF(ISNUMBER(G$66),G55,"") -> 128.4 | AJ55: =IF(ISNUMBER(H$66),H55,"") -> 121.2 | AK55: =IF(ISNUMBER(I$66),I55,"") -> 126 | AL55: =IF(ISNUMBER(J$66),J55,"") -> 120 | AM55: =IF(ISNUMBER(K$66),K55,"") -> 124.8 | AN55: =IF(ISNUMBER(L$66),L55,"") -> 129.6 | ... AP55: =IF(ISNUMBER(N$66),N55,"") -> 127.2 | AQ55: =IF(C55="Ручная",O55,0) -> 120
A56: 3 | B56: Отвесить допустимую партию | C56: Ручная | D56: Масса партии проверена | E56: 22.22 | F56: 23.1 | G56: 22 | H56: 22.88 | I56: 23.76 | J56: 22.44 | K56: 23.32 | L56: 24.2 | M56: 22.66 | N56: 23.54 | O56: =IF(COUNT(AG56:AP56)>0,MIN(AG56:AP56),"") -> 22 | P56: =IF(COUNT(AG56:AP56)>0,MAX(AG56:AP56),"") -> 24.2 | Q56: =IF(ISNUMBER(O56),P56-O56,"") -> 2.2 | R56: =IF(ISNUMBER(O56),IF(C56="Ручная",IF($S$66>0,$R$66*Q56/$S$66,IF($W$66=3,$R$66,0)),0),"") -> 0.77264 | S56: =IF(ISNUMBER(O56),O56+R56,"") -> 22.77264 | T56: =IF(ISNUMBER(S56),P56-S56,"") -> 1.42736 | U56: =IF(COUNT(AG56:AP56)>0,AVERAGE(AG56:AP56),"") -> 23.012 | AG56: =IF(ISNUMBER(E$66),E56,"") -> 22.22 | AH56: =IF(ISNUMBER(F$66),F56,"") -> 23.1 | AI56: =IF(ISNUMBER(G$66),G56,"") -> 22 | AJ56: =IF(ISNUMBER(H$66),H56,"") -> 22.88 | AK56: =IF(ISNUMBER(I$66),I56,"") -> 23.76 | AL56: =IF(ISNUMBER(J$66),J56,"") -> 22.44 | AM56: =IF(ISNUMBER(K$66),K56,"") -> 23.32 | AN56: =IF(ISNUMBER(L$66),L56,"") -> 24.2 | ... AP56: =IF(ISNUMBER(N$66),N56,"") -> 23.54 | AQ56: =IF(C56="Ручная",O56,0) -> 22
A57: — | B57: Перейти с партией к SOLIA | C57: Переход | D57: Оператор у SOLIA | E57: 12.48 | F57: 12.96 | G57: 12.24 | H57: 12.72 | I57: 13.2 | J57: 12.36 | K57: 12.84 | L57: 12.12 | M57: 12.6 | N57: 12 | O57: =IF(COUNT(AG57:AP57)>0,MIN(AG57:AP57),"") -> 12 | P57: =IF(COUNT(AG57:AP57)>0,MAX(AG57:AP57),"") -> 13.2 | Q57: =IF(ISNUMBER(O57),P57-O57,"") -> 1.2 | R57: =IF(ISNUMBER(O57),IF(C57="Ручная",IF($S$66>0,$R$66*Q57/$S$66,IF($W$66=4,$R$66,0)),0),"") -> 0 | S57: =IF(ISNUMBER(O57),O57+R57,"") -> 12 | T57: =IF(ISNUMBER(S57),P57-S57,"") -> 1.2 | U57: =IF(COUNT(AG57:AP57)>0,AVERAGE(AG57:AP57),"") -> 12.552 | AG57: =IF(ISNUMBER(E$66),E57,"") -> 12.48 | AH57: =IF(ISNUMBER(F$66),F57,"") -> 12.96 | AI57: =IF(ISNUMBER(G$66),G57,"") -> 12.24 | AJ57: =IF(ISNUMBER(H$66),H57,"") -> 12.72 | AK57: =IF(ISNUMBER(I$66),I57,"") -> 13.2 | AL57: =IF(ISNUMBER(J$66),J57,"") -> 12.36 | AM57: =IF(ISNUMBER(K$66),K57,"") -> 12.84 | AN57: =IF(ISNUMBER(L$66),L57,"") -> 12.12 | ... AP57: =IF(ISNUMBER(N$66),N57,"") -> 12 | AQ57: =IF(C57="Ручная",O57,0) -> 0
A58: 5 | B58: Загрузить, выбрать программу, запустить | C58: Ручная | D58: Программа запущена | E58: 37.1 | F58: 38.5 | G58: 36.05 | H58: 37.45 | I58: 35.35 | J58: 36.75 | K58: 35 | L58: 36.4 | M58: 37.8 | N58: 35.7 | O58: =IF(COUNT(AG58:AP58)>0,MIN(AG58:AP58),"") -> 35 | P58: =IF(COUNT(AG58:AP58)>0,MAX(AG58:AP58),"") -> 38.5 | Q58: =IF(ISNUMBER(O58),P58-O58,"") -> 3.5 | R58: =IF(ISNUMBER(O58),IF(C58="Ручная",IF($S$66>0,$R$66*Q58/$S$66,IF($W$66=5,$R$66,0)),0),"") -> 1.2292 | S58: =IF(ISNUMBER(O58),O58+R58,"") -> 36.2292 | T58: =IF(ISNUMBER(S58),P58-S58,"") -> 2.2708 | U58: =IF(COUNT(AG58:AP58)>0,AVERAGE(AG58:AP58),"") -> 36.61 | AG58: =IF(ISNUMBER(E$66),E58,"") -> 37.1 | AH58: =IF(ISNUMBER(F$66),F58,"") -> 38.5 | AI58: =IF(ISNUMBER(G$66),G58,"") -> 36.05 | AJ58: =IF(ISNUMBER(H$66),H58,"") -> 37.45 | AK58: =IF(ISNUMBER(I$66),I58,"") -> 35.35 | AL58: =IF(ISNUMBER(J$66),J58,"") -> 36.75 | AM58: =IF(ISNUMBER(K$66),K58,"") -> 35 | AN58: =IF(ISNUMBER(L$66),L58,"") -> 36.4 | ... AP58: =IF(ISNUMBER(N$66),N58,"") -> 35.7 | AQ58: =IF(C58="Ручная",O58,0) -> 35
A59: — | B59: Автоматическая программа / ожидание | C59: Авто/ожидание | D59: Полный цикл программы завершён | E59: ='Ассортимент'!R10 -> 450 | F59: ='Ассортимент'!R10 -> 450 | G59: ='Ассортимент'!R10 -> 450 | H59: ='Ассортимент'!R10 -> 450 | I59: ='Ассортимент'!R10 -> 450 | J59: ='Ассортимент'!R10 -> 450 | K59: ='Ассортимент'!R10 -> 450 | L59: ='Ассортимент'!R10 -> 450 | M59: ='Ассортимент'!R10 -> 450 | N59: ='Ассортимент'!R10 -> 450 | O59: =IF(COUNT(AG59:AP59)>0,MIN(AG59:AP59),"") -> 450 | P59: =IF(COUNT(AG59:AP59)>0,MAX(AG59:AP59),"") -> 450 | Q59: =IF(ISNUMBER(O59),P59-O59,"") -> 0 | R59: =IF(ISNUMBER(O59),IF(C59="Ручная",IF($S$66>0,$R$66*Q59/$S$66,IF($W$66=6,$R$66,0)),0),"") -> 0 | S59: =IF(ISNUMBER(O59),O59+R59,"") -> 450 | T59: =IF(ISNUMBER(S59),P59-S59,"") -> 0 | U59: =IF(COUNT(AG59:AP59)>0,AVERAGE(AG59:AP59),"") -> 450 | AG59: =IF(ISNUMBER(E$66),E59,"") -> 450 | AH59: =IF(ISNUMBER(F$66),F59,"") -> 450 | AI59: =IF(ISNUMBER(G$66),G59,"") -> 450 | AJ59: =IF(ISNUMBER(H$66),H59,"") -> 450 | AK59: =IF(ISNUMBER(I$66),I59,"") -> 450 | AL59: =IF(ISNUMBER(J$66),J59,"") -> 450 | AM59: =IF(ISNUMBER(K$66),K59,"") -> 450 | AN59: =IF(ISNUMBER(L$66),L59,"") -> 450 | ... AP59: =IF(ISNUMBER(N$66),N59,"") -> 450 | AQ59: =IF(C59="Ручная",O59,0) -> 0
A60: 7 | B60: Выгрузить в чистую маркированную тару | C60: Ручная | D60: Выгрузка завершена | E60: 30 | F60: 31.2 | G60: 32.4 | H60: 30.6 | I60: 31.8 | J60: 33 | K60: 30.9 | L60: 32.1 | M60: 30.3 | N60: 31.5 | O60: =IF(COUNT(AG60:AP60)>0,MIN(AG60:AP60),"") -> 30 | P60: =IF(COUNT(AG60:AP60)>0,MAX(AG60:AP60),"") -> 33 | Q60: =IF(ISNUMBER(O60),P60-O60,"") -> 3 | R60: =IF(ISNUMBER(O60),IF(C60="Ручная",IF($S$66>0,$R$66*Q60/$S$66,IF($W$66=7,$R$66,0)),0),"") -> 1.0536 | S60: =IF(ISNUMBER(O60),O60+R60,"") -> 31.0536 | T60: =IF(ISNUMBER(S60),P60-S60,"") -> 1.9464 | U60: =IF(COUNT(AG60:AP60)>0,AVERAGE(AG60:AP60),"") -> 31.38 | AG60: =IF(ISNUMBER(E$66),E60,"") -> 30 | AH60: =IF(ISNUMBER(F$66),F60,"") -> 31.2 | AI60: =IF(ISNUMBER(G$66),G60,"") -> 32.4 | AJ60: =IF(ISNUMBER(H$66),H60,"") -> 30.6 | AK60: =IF(ISNUMBER(I$66),I60,"") -> 31.8 | AL60: =IF(ISNUMBER(J$66),J60,"") -> 33 | AM60: =IF(ISNUMBER(K$66),K60,"") -> 30.9 | AN60: =IF(ISNUMBER(L$66),L60,"") -> 32.1 | ... AP60: =IF(ISNUMBER(N$66),N60,"") -> 31.5 | AQ60: =IF(C60="Ручная",O60,0) -> 30
A61: 8 | B61: Проверить качество и маркировку | C61: Ручная | D61: Результат проверки подтверждён | E61: 18.36 | F61: 19.08 | G61: 19.8 | H61: 18.54 | I61: 19.26 | J61: 18.18 | K61: 18.9 | L61: 18 | M61: 18.72 | N61: 19.44 | O61: =IF(COUNT(AG61:AP61)>0,MIN(AG61:AP61),"") -> 18 | P61: =IF(COUNT(AG61:AP61)>0,MAX(AG61:AP61),"") -> 19.8 | Q61: =IF(ISNUMBER(O61),P61-O61,"") -> 1.8 | R61: =IF(ISNUMBER(O61),IF(C61="Ручная",IF($S$66>0,$R$66*Q61/$S$66,IF($W$66=8,$R$66,0)),0),"") -> 0.63216 | S61: =IF(ISNUMBER(O61),O61+R61,"") -> 18.63216 | T61: =IF(ISNUMBER(S61),P61-S61,"") -> 1.16784 | U61: =IF(COUNT(AG61:AP61)>0,AVERAGE(AG61:AP61),"") -> 18.828 | AG61: =IF(ISNUMBER(E$66),E61,"") -> 18.36 | AH61: =IF(ISNUMBER(F$66),F61,"") -> 19.08 | AI61: =IF(ISNUMBER(G$66),G61,"") -> 19.8 | AJ61: =IF(ISNUMBER(H$66),H61,"") -> 18.54 | AK61: =IF(ISNUMBER(I$66),I61,"") -> 19.26 | AL61: =IF(ISNUMBER(J$66),J61,"") -> 18.18 | AM61: =IF(ISNUMBER(K$66),K61,"") -> 18.9 | AN61: =IF(ISNUMBER(L$66),L61,"") -> 18 | ... AP61: =IF(ISNUMBER(N$66),N61,"") -> 19.44 | AQ61: =IF(C61="Ручная",O61,0) -> 18
A62: — | B62: Передать в зону чистой продукции | C62: Переход | D62: Партия передана | E62: 10.3 | F62: 10.7 | G62: 10.1 | H62: 10.5 | I62: 10 | J62: 10.4 | K62: 10.8 | L62: 10.2 | M62: 10.6 | N62: 11 | O62: =IF(COUNT(AG62:AP62)>0,MIN(AG62:AP62),"") -> 10 | P62: =IF(COUNT(AG62:AP62)>0,MAX(AG62:AP62),"") -> 11 | Q62: =IF(ISNUMBER(O62),P62-O62,"") -> 1 | R62: =IF(ISNUMBER(O62),IF(C62="Ручная",IF($S$66>0,$R$66*Q62/$S$66,IF($W$66=9,$R$66,0)),0),"") -> 0 | S62: =IF(ISNUMBER(O62),O62+R62,"") -> 10 | T62: =IF(ISNUMBER(S62),P62-S62,"") -> 1 | U62: =IF(COUNT(AG62:AP62)>0,AVERAGE(AG62:AP62),"") -> 10.46 | AG62: =IF(ISNUMBER(E$66),E62,"") -> 10.3 | AH62: =IF(ISNUMBER(F$66),F62,"") -> 10.7 | AI62: =IF(ISNUMBER(G$66),G62,"") -> 10.1 | AJ62: =IF(ISNUMBER(H$66),H62,"") -> 10.5 | AK62: =IF(ISNUMBER(I$66),I62,"") -> 10 | AL62: =IF(ISNUMBER(J$66),J62,"") -> 10.4 | AM62: =IF(ISNUMBER(K$66),K62,"") -> 10.8 | AN62: =IF(ISNUMBER(L$66),L62,"") -> 10.2 | ... AP62: =IF(ISNUMBER(N$66),N62,"") -> 11 | AQ62: =IF(C62="Ручная",O62,0) -> 0
A63: — | B63: Вернуться к началу цикла | C63: Переход | D63: Возврат на исходную позицию | E63: 10.5 | F63: 10 | G63: 10.4 | H63: 10.8 | I63: 10.2 | J63: 10.6 | K63: 11 | L63: 10.3 | M63: 10.7 | N63: 10.1 | O63: =IF(COUNT(AG63:AP63)>0,MIN(AG63:AP63),"") -> 10 | P63: =IF(COUNT(AG63:AP63)>0,MAX(AG63:AP63),"") -> 11 | Q63: =IF(ISNUMBER(O63),P63-O63,"") -> 1 | R63: =IF(ISNUMBER(O63),IF(C63="Ручная",IF($S$66>0,$R$66*Q63/$S$66,IF($W$66=10,$R$66,0)),0),"") -> 0 | S63: =IF(ISNUMBER(O63),O63+R63,"") -> 10 | T63: =IF(ISNUMBER(S63),P63-S63,"") -> 1 | U63: =IF(COUNT(AG63:AP63)>0,AVERAGE(AG63:AP63),"") -> 10.46 | AG63: =IF(ISNUMBER(E$66),E63,"") -> 10.5 | AH63: =IF(ISNUMBER(F$66),F63,"") -> 10 | AI63: =IF(ISNUMBER(G$66),G63,"") -> 10.4 | AJ63: =IF(ISNUMBER(H$66),H63,"") -> 10.8 | AK63: =IF(ISNUMBER(I$66),I63,"") -> 10.2 | AL63: =IF(ISNUMBER(J$66),J63,"") -> 10.6 | AM63: =IF(ISNUMBER(K$66),K63,"") -> 11 | AN63: =IF(ISNUMBER(L$66),L63,"") -> 10.3 | ... AP63: =IF(ISNUMBER(N$66),N63,"") -> 10.1 | AQ63: =IF(C63="Ручная",O63,0) -> 0
A64: — | B64: Внеплановый поиск тары / ожидание | C64: Потери | D64: Причина задержки устранена | E64: 12.96 | F64: 12.24 | G64: 12.72 | H64: 13.2 | I64: 12.36 | J64: 12.84 | K64: 12.12 | L64: 12.6 | M64: 12 | N64: 12.48 | O64: =IF(COUNT(AG64:AP64)>0,MIN(AG64:AP64),"") -> 12 | P64: =IF(COUNT(AG64:AP64)>0,MAX(AG64:AP64),"") -> 13.2 | Q64: =IF(ISNUMBER(O64),P64-O64,"") -> 1.2 | R64: =IF(ISNUMBER(O64),IF(C64="Ручная",IF($S$66>0,$R$66*Q64/$S$66,IF($W$66=11,$R$66,0)),0),"") -> 0 | S64: =IF(ISNUMBER(O64),O64+R64,"") -> 12 | T64: =IF(ISNUMBER(S64),P64-S64,"") -> 1.2 | U64: =IF(COUNT(AG64:AP64)>0,AVERAGE(AG64:AP64),"") -> 12.552 | AG64: =IF(ISNUMBER(E$66),E64,"") -> 12.96 | AH64: =IF(ISNUMBER(F$66),F64,"") -> 12.24 | AI64: =IF(ISNUMBER(G$66),G64,"") -> 12.72 | AJ64: =IF(ISNUMBER(H$66),H64,"") -> 13.2 | AK64: =IF(ISNUMBER(I$66),I64,"") -> 12.36 | AL64: =IF(ISNUMBER(J$66),J64,"") -> 12.84 | AM64: =IF(ISNUMBER(K$66),K64,"") -> 12.12 | AN64: =IF(ISNUMBER(L$66),L64,"") -> 12.6 | ... AP64: =IF(ISNUMBER(N$66),N64,"") -> 12.48 | AQ64: =IF(C64="Ручная",O64,0) -> 0
B65: ИТОГИ: все элементы цикла | E65: =IF(COUNT(E54:E64)=11,SUM(E54:E64),"") -> 762.92 | F65: =IF(COUNT(F54:F64)=11,SUM(F54:F64),"") -> 756.88 | G65: =IF(COUNT(G54:G64)=11,SUM(G54:G64),"") -> 760.61 | H65: =IF(COUNT(H54:H64)=11,SUM(H54:H64),"") -> 755.39 | I65: =IF(COUNT(I54:I64)=11,SUM(I54:I64),"") -> 757.68 | J65: =IF(COUNT(J54:J64)=11,SUM(J54:J64),"") -> 753.32 | K65: =IF(COUNT(K54:K64)=11,SUM(K54:K64),"") -> 754.93 | L65: =IF(COUNT(L54:L64)=11,SUM(L54:L64),"") -> 761.77 | ... U65: =IF(COUNT(U54:U64)=11,SUM(U54:U64),"") -> 757.524
B66: ТОЛЬКО полные учтённые циклы | E66: =IF(AND(E52=1,COUNT(E54:E64)=11,MIN(E54:E64)>=0),E65,"") -> 762.92 | F66: =IF(AND(F52=1,COUNT(F54:F64)=11,MIN(F54:F64)>=0),F65,"") -> 756.88 | G66: =IF(AND(G52=1,COUNT(G54:G64)=11,MIN(G54:G64)>=0),G65,"") -> 760.61 | H66: =IF(AND(H52=1,COUNT(H54:H64)=11,MIN(H54:H64)>=0),H65,"") -> 755.39 | I66: =IF(AND(I52=1,COUNT(I54:I64)=11,MIN(I54:I64)>=0),I65,"") -> 757.68 | J66: =IF(AND(J52=1,COUNT(J54:J64)=11,MIN(J54:J64)>=0),J65,"") -> 753.32 | K66: =IF(AND(K52=1,COUNT(K54:K64)=11,MIN(K54:K64)>=0),K65,"") -> 754.93 | L66: =IF(AND(L52=1,COUNT(L54:L64)=11,MIN(L54:L64)>=0),L65,"") -> 761.77 | ... N66: =IF(AND(N52=1,COUNT(N54:N64)=11,MIN(N54:N64)>=0),N65,"") -> 758.96 | O66: =IF(COUNT(E66:N66)>0,MIN(E66:N66),"") -> 752.78 | P66: =IF(COUNT(E66:N66)>0,MAX(E66:N66),"") -> 762.92 | Q66: =IF(ISNUMBER(O66),P66-O66,"") -> 10.14 | R66: =IF(ISNUMBER(O66),MAX(0,O66-O65),"") -> 8.78 | S66: =SUMIF(C54:C64,"Ручная",Q54:Q64) -> 25 | T66: =COUNT(E66:N66) -> 10 | U66: =IF(COUNT(E66:N66)>0,AVERAGE(E66:N66),"") -> 757.524 | V66: =IF(ISNUMBER(O66),S65-O66,"") -> 1.1368684e-13 | W66: =MATCH(MAX(AQ54:AQ64),AQ54:AQ64,0) -> 2 | X66: =IF(T66=0,"НЕТ ЗАМЕРОВ",IF(T66<10,"МЕНЕЕ 10 ЦИКЛОВ",IF(ABS(V66)<0.000001,"ОК","ОШИБКА РЕГУЛИРОВКИ"))) -> ОК
A67: В строке учтённых циклов: O = T min; P = T max; Q = размах цикла; R = T min − сумма t min; S = сумма размахов ручных элементов; T = число циклов; U = среднее; V = сумма t отрег − T min (должно быть 0).
A70: 04. Томат · ДО · 10 демонстрационных циклов, заменить реальными
A71: ="Масса замера, кг: "&'Ассортимент'!J11&". Все замеры одной партии/исполнителя/условий. Основание: "&'Ввод'!B14 -> Масса замера, кг: 5. Все замеры одной партии/исполнителя/условий. Основание: ДЕМО: синтетические замеры; заменить фактическими
A72: № | B72: Рабочий элемент | C72: Тип | D72: Точка отсчёта | E72: 1 | F72: 2 | G72: 3 | H72: 4 | I72: 5 | J72: 6 | K72: 7 | L72: 8 | M72: 9 | N72: 10 | O72: t min | P72: t max | Q72: Размах | R72: Рег. с | S72: t отрег. | T72: Колебания | U72: Среднее | V72: Контроль | W72: Служебно | X72: Статус
B73: Учитывать цикл: 1 / 0 | E73: 1 | F73: 1 | G73: 1 | H73: 1 | I73: 1 | J73: 1 | K73: 1 | L73: 1 | M73: 1 | N73: 1
B74: Причина исключения / условия | E74: ДЕМО | F74: ДЕМО | G74: ДЕМО | H74: ДЕМО | I74: ДЕМО | J74: ДЕМО | K74: ДЕМО | L74: ДЕМО | M74: ДЕМО | N74: ДЕМО
A75: 1 | B75: Осмотреть упаковку и сырьё | C75: Ручная | D75: Осмотр партии завершён | E75: 25.5 | F75: 26.5 | G75: 27.5 | H75: 25.75 | I75: 26.75 | J75: 25.25 | K75: 26.25 | L75: 25 | M75: 26 | N75: 27 | O75: =IF(COUNT(AG75:AP75)>0,MIN(AG75:AP75),"") -> 25 | P75: =IF(COUNT(AG75:AP75)>0,MAX(AG75:AP75),"") -> 27.5 | Q75: =IF(ISNUMBER(O75),P75-O75,"") -> 2.5 | R75: =IF(ISNUMBER(O75),IF(C75="Ручная",IF($S$87>0,$R$87*Q75/$S$87,IF($W$87=1,$R$87,0)),0),"") -> 1.0727273 | S75: =IF(ISNUMBER(O75),O75+R75,"") -> 26.072727 | T75: =IF(ISNUMBER(S75),P75-S75,"") -> 1.4272727 | U75: =IF(COUNT(AG75:AP75)>0,AVERAGE(AG75:AP75),"") -> 26.15 | AG75: =IF(ISNUMBER(E$87),E75,"") -> 25.5 | AH75: =IF(ISNUMBER(F$87),F75,"") -> 26.5 | AI75: =IF(ISNUMBER(G$87),G75,"") -> 27.5 | AJ75: =IF(ISNUMBER(H$87),H75,"") -> 25.75 | AK75: =IF(ISNUMBER(I$87),I75,"") -> 26.75 | AL75: =IF(ISNUMBER(J$87),J75,"") -> 25.25 | AM75: =IF(ISNUMBER(K$87),K75,"") -> 26.25 | AN75: =IF(ISNUMBER(L$87),L75,"") -> 25 | ... AP75: =IF(ISNUMBER(N$87),N75,"") -> 27 | AQ75: =IF(C75="Ручная",O75,0) -> 25
A76: 2 | B76: Отсортировать / подготовить сырьё | C76: Ручная | D76: Подготовленное сырьё отложено | E76: 36.05 | F76: 37.45 | G76: 35.35 | H76: 36.75 | I76: 35 | J76: 36.4 | K76: 37.8 | L76: 35.7 | M76: 37.1 | N76: 38.5 | O76: =IF(COUNT(AG76:AP76)>0,MIN(AG76:AP76),"") -> 35 | P76: =IF(COUNT(AG76:AP76)>0,MAX(AG76:AP76),"") -> 38.5 | Q76: =IF(ISNUMBER(O76),P76-O76,"") -> 3.5 | R76: =IF(ISNUMBER(O76),IF(C76="Ручная",IF($S$87>0,$R$87*Q76/$S$87,IF($W$87=2,$R$87,0)),0),"") -> 1.5018182 | S76: =IF(ISNUMBER(O76),O76+R76,"") -> 36.501818 | T76: =IF(ISNUMBER(S76),P76-S76,"") -> 1.9981818 | U76: =IF(COUNT(AG76:AP76)>0,AVERAGE(AG76:AP76),"") -> 36.61 | AG76: =IF(ISNUMBER(E$87),E76,"") -> 36.05 | AH76: =IF(ISNUMBER(F$87),F76,"") -> 37.45 | AI76: =IF(ISNUMBER(G$87),G76,"") -> 35.35 | AJ76: =IF(ISNUMBER(H$87),H76,"") -> 36.75 | AK76: =IF(ISNUMBER(I$87),I76,"") -> 35 | AL76: =IF(ISNUMBER(J$87),J76,"") -> 36.4 | AM76: =IF(ISNUMBER(K$87),K76,"") -> 37.8 | AN76: =IF(ISNUMBER(L$87),L76,"") -> 35.7 | ... AP76: =IF(ISNUMBER(N$87),N76,"") -> 38.5 | AQ76: =IF(C76="Ручная",O76,0) -> 35
A77: 3 | B77: Отвесить допустимую партию | C77: Ручная | D77: Масса партии проверена | E77: 23.1 | F77: 22 | G77: 22.88 | H77: 23.76 | I77: 22.44 | J77: 23.32 | K77: 24.2 | L77: 22.66 | M77: 23.54 | N77: 22.22 | O77: =IF(COUNT(AG77:AP77)>0,MIN(AG77:AP77),"") -> 22 | P77: =IF(COUNT(AG77:AP77)>0,MAX(AG77:AP77),"") -> 24.2 | Q77: =IF(ISNUMBER(O77),P77-O77,"") -> 2.2 | R77: =IF(ISNUMBER(O77),IF(C77="Ручная",IF($S$87>0,$R$87*Q77/$S$87,IF($W$87=3,$R$87,0)),0),"") -> 0.944 | S77: =IF(ISNUMBER(O77),O77+R77,"") -> 22.944 | T77: =IF(ISNUMBER(S77),P77-S77,"") -> 1.256 | U77: =IF(COUNT(AG77:AP77)>0,AVERAGE(AG77:AP77),"") -> 23.012 | AG77: =IF(ISNUMBER(E$87),E77,"") -> 23.1 | AH77: =IF(ISNUMBER(F$87),F77,"") -> 22 | AI77: =IF(ISNUMBER(G$87),G77,"") -> 22.88 | AJ77: =IF(ISNUMBER(H$87),H77,"") -> 23.76 | AK77: =IF(ISNUMBER(I$87),I77,"") -> 22.44 | AL77: =IF(ISNUMBER(J$87),J77,"") -> 23.32 | AM77: =IF(ISNUMBER(K$87),K77,"") -> 24.2 | AN77: =IF(ISNUMBER(L$87),L77,"") -> 22.66 | ... AP77: =IF(ISNUMBER(N$87),N77,"") -> 22.22 | AQ77: =IF(C77="Ручная",O77,0) -> 22
A78: — | B78: Перейти с партией к SOLIA | C78: Переход | D78: Оператор у SOLIA | E78: 12.96 | F78: 12.24 | G78: 12.72 | H78: 13.2 | I78: 12.36 | J78: 12.84 | K78: 12.12 | L78: 12.6 | M78: 12 | N78: 12.48 | O78: =IF(COUNT(AG78:AP78)>0,MIN(AG78:AP78),"") -> 12 | P78: =IF(COUNT(AG78:AP78)>0,MAX(AG78:AP78),"") -> 13.2 | Q78: =IF(ISNUMBER(O78),P78-O78,"") -> 1.2 | R78: =IF(ISNUMBER(O78),IF(C78="Ручная",IF($S$87>0,$R$87*Q78/$S$87,IF($W$87=4,$R$87,0)),0),"") -> 0 | S78: =IF(ISNUMBER(O78),O78+R78,"") -> 12 | T78: =IF(ISNUMBER(S78),P78-S78,"") -> 1.2 | U78: =IF(COUNT(AG78:AP78)>0,AVERAGE(AG78:AP78),"") -> 12.552 | AG78: =IF(ISNUMBER(E$87),E78,"") -> 12.96 | AH78: =IF(ISNUMBER(F$87),F78,"") -> 12.24 | AI78: =IF(ISNUMBER(G$87),G78,"") -> 12.72 | AJ78: =IF(ISNUMBER(H$87),H78,"") -> 13.2 | AK78: =IF(ISNUMBER(I$87),I78,"") -> 12.36 | AL78: =IF(ISNUMBER(J$87),J78,"") -> 12.84 | AM78: =IF(ISNUMBER(K$87),K78,"") -> 12.12 | AN78: =IF(ISNUMBER(L$87),L78,"") -> 12.6 | ... AP78: =IF(ISNUMBER(N$87),N78,"") -> 12.48 | AQ78: =IF(C78="Ручная",O78,0) -> 0
A79: 5 | B79: Загрузить, выбрать программу, запустить | C79: Ручная | D79: Программа запущена | E79: 38.5 | F79: 36.05 | G79: 37.45 | H79: 35.35 | I79: 36.75 | J79: 35 | K79: 36.4 | L79: 37.8 | M79: 35.7 | N79: 37.1 | O79: =IF(COUNT(AG79:AP79)>0,MIN(AG79:AP79),"") -> 35 | P79: =IF(COUNT(AG79:AP79)>0,MAX(AG79:AP79),"") -> 38.5 | Q79: =IF(ISNUMBER(O79),P79-O79,"") -> 3.5 | R79: =IF(ISNUMBER(O79),IF(C79="Ручная",IF($S$87>0,$R$87*Q79/$S$87,IF($W$87=5,$R$87,0)),0),"") -> 1.5018182 | S79: =IF(ISNUMBER(O79),O79+R79,"") -> 36.501818 | T79: =IF(ISNUMBER(S79),P79-S79,"") -> 1.9981818 | U79: =IF(COUNT(AG79:AP79)>0,AVERAGE(AG79:AP79),"") -> 36.61 | AG79: =IF(ISNUMBER(E$87),E79,"") -> 38.5 | AH79: =IF(ISNUMBER(F$87),F79,"") -> 36.05 | AI79: =IF(ISNUMBER(G$87),G79,"") -> 37.45 | AJ79: =IF(ISNUMBER(H$87),H79,"") -> 35.35 | AK79: =IF(ISNUMBER(I$87),I79,"") -> 36.75 | AL79: =IF(ISNUMBER(J$87),J79,"") -> 35 | AM79: =IF(ISNUMBER(K$87),K79,"") -> 36.4 | AN79: =IF(ISNUMBER(L$87),L79,"") -> 37.8 | ... AP79: =IF(ISNUMBER(N$87),N79,"") -> 37.1 | AQ79: =IF(C79="Ручная",O79,0) -> 35
A80: — | B80: Автоматическая программа / ожидание | C80: Авто/ожидание | D80: Полный цикл программы завершён | E80: ='Ассортимент'!R11 -> 180 | F80: ='Ассортимент'!R11 -> 180 | G80: ='Ассортимент'!R11 -> 180 | H80: ='Ассортимент'!R11 -> 180 | I80: ='Ассортимент'!R11 -> 180 | J80: ='Ассортимент'!R11 -> 180 | K80: ='Ассортимент'!R11 -> 180 | L80: ='Ассортимент'!R11 -> 180 | M80: ='Ассортимент'!R11 -> 180 | N80: ='Ассортимент'!R11 -> 180 | O80: =IF(COUNT(AG80:AP80)>0,MIN(AG80:AP80),"") -> 180 | P80: =IF(COUNT(AG80:AP80)>0,MAX(AG80:AP80),"") -> 180 | Q80: =IF(ISNUMBER(O80),P80-O80,"") -> 0 | R80: =IF(ISNUMBER(O80),IF(C80="Ручная",IF($S$87>0,$R$87*Q80/$S$87,IF($W$87=6,$R$87,0)),0),"") -> 0 | S80: =IF(ISNUMBER(O80),O80+R80,"") -> 180 | T80: =IF(ISNUMBER(S80),P80-S80,"") -> 0 | U80: =IF(COUNT(AG80:AP80)>0,AVERAGE(AG80:AP80),"") -> 180 | AG80: =IF(ISNUMBER(E$87),E80,"") -> 180 | AH80: =IF(ISNUMBER(F$87),F80,"") -> 180 | AI80: =IF(ISNUMBER(G$87),G80,"") -> 180 | AJ80: =IF(ISNUMBER(H$87),H80,"") -> 180 | AK80: =IF(ISNUMBER(I$87),I80,"") -> 180 | AL80: =IF(ISNUMBER(J$87),J80,"") -> 180 | AM80: =IF(ISNUMBER(K$87),K80,"") -> 180 | AN80: =IF(ISNUMBER(L$87),L80,"") -> 180 | ... AP80: =IF(ISNUMBER(N$87),N80,"") -> 180 | AQ80: =IF(C80="Ручная",O80,0) -> 0
A81: 7 | B81: Выгрузить в чистую маркированную тару | C81: Ручная | D81: Выгрузка завершена | E81: 31.2 | F81: 32.4 | G81: 30.6 | H81: 31.8 | I81: 33 | J81: 30.9 | K81: 32.1 | L81: 30.3 | M81: 31.5 | N81: 30 | O81: =IF(COUNT(AG81:AP81)>0,MIN(AG81:AP81),"") -> 30 | P81: =IF(COUNT(AG81:AP81)>0,MAX(AG81:AP81),"") -> 33 | Q81: =IF(ISNUMBER(O81),P81-O81,"") -> 3 | R81: =IF(ISNUMBER(O81),IF(C81="Ручная",IF($S$87>0,$R$87*Q81/$S$87,IF($W$87=7,$R$87,0)),0),"") -> 1.2872727 | S81: =IF(ISNUMBER(O81),O81+R81,"") -> 31.287273 | T81: =IF(ISNUMBER(S81),P81-S81,"") -> 1.7127273 | U81: =IF(COUNT(AG81:AP81)>0,AVERAGE(AG81:AP81),"") -> 31.38 | AG81: =IF(ISNUMBER(E$87),E81,"") -> 31.2 | AH81: =IF(ISNUMBER(F$87),F81,"") -> 32.4 | AI81: =IF(ISNUMBER(G$87),G81,"") -> 30.6 | AJ81: =IF(ISNUMBER(H$87),H81,"") -> 31.8 | AK81: =IF(ISNUMBER(I$87),I81,"") -> 33 | AL81: =IF(ISNUMBER(J$87),J81,"") -> 30.9 | AM81: =IF(ISNUMBER(K$87),K81,"") -> 32.1 | AN81: =IF(ISNUMBER(L$87),L81,"") -> 30.3 | ... AP81: =IF(ISNUMBER(N$87),N81,"") -> 30 | AQ81: =IF(C81="Ручная",O81,0) -> 30
A82: 8 | B82: Проверить качество и маркировку | C82: Ручная | D82: Результат проверки подтверждён | E82: 19.08 | F82: 19.8 | G82: 18.54 | H82: 19.26 | I82: 18.18 | J82: 18.9 | K82: 18 | L82: 18.72 | M82: 19.44 | N82: 18.36 | O82: =IF(COUNT(AG82:AP82)>0,MIN(AG82:AP82),"") -> 18 | P82: =IF(COUNT(AG82:AP82)>0,MAX(AG82:AP82),"") -> 19.8 | Q82: =IF(ISNUMBER(O82),P82-O82,"") -> 1.8 | R82: =IF(ISNUMBER(O82),IF(C82="Ручная",IF($S$87>0,$R$87*Q82/$S$87,IF($W$87=8,$R$87,0)),0),"") -> 0.77236364 | S82: =IF(ISNUMBER(O82),O82+R82,"") -> 18.772364 | T82: =IF(ISNUMBER(S82),P82-S82,"") -> 1.0276364 | U82: =IF(COUNT(AG82:AP82)>0,AVERAGE(AG82:AP82),"") -> 18.828 | AG82: =IF(ISNUMBER(E$87),E82,"") -> 19.08 | AH82: =IF(ISNUMBER(F$87),F82,"") -> 19.8 | AI82: =IF(ISNUMBER(G$87),G82,"") -> 18.54 | AJ82: =IF(ISNUMBER(H$87),H82,"") -> 19.26 | AK82: =IF(ISNUMBER(I$87),I82,"") -> 18.18 | AL82: =IF(ISNUMBER(J$87),J82,"") -> 18.9 | AM82: =IF(ISNUMBER(K$87),K82,"") -> 18 | AN82: =IF(ISNUMBER(L$87),L82,"") -> 18.72 | ... AP82: =IF(ISNUMBER(N$87),N82,"") -> 18.36 | AQ82: =IF(C82="Ручная",O82,0) -> 18
A83: — | B83: Передать в зону чистой продукции | C83: Переход | D83: Партия передана | E83: 10.7 | F83: 10.1 | G83: 10.5 | H83: 10 | I83: 10.4 | J83: 10.8 | K83: 10.2 | L83: 10.6 | M83: 11 | N83: 10.3 | O83: =IF(COUNT(AG83:AP83)>0,MIN(AG83:AP83),"") -> 10 | P83: =IF(COUNT(AG83:AP83)>0,MAX(AG83:AP83),"") -> 11 | Q83: =IF(ISNUMBER(O83),P83-O83,"") -> 1 | R83: =IF(ISNUMBER(O83),IF(C83="Ручная",IF($S$87>0,$R$87*Q83/$S$87,IF($W$87=9,$R$87,0)),0),"") -> 0 | S83: =IF(ISNUMBER(O83),O83+R83,"") -> 10 | T83: =IF(ISNUMBER(S83),P83-S83,"") -> 1 | U83: =IF(COUNT(AG83:AP83)>0,AVERAGE(AG83:AP83),"") -> 10.46 | AG83: =IF(ISNUMBER(E$87),E83,"") -> 10.7 | AH83: =IF(ISNUMBER(F$87),F83,"") -> 10.1 | AI83: =IF(ISNUMBER(G$87),G83,"") -> 10.5 | AJ83: =IF(ISNUMBER(H$87),H83,"") -> 10 | AK83: =IF(ISNUMBER(I$87),I83,"") -> 10.4 | AL83: =IF(ISNUMBER(J$87),J83,"") -> 10.8 | AM83: =IF(ISNUMBER(K$87),K83,"") -> 10.2 | AN83: =IF(ISNUMBER(L$87),L83,"") -> 10.6 | ... AP83: =IF(ISNUMBER(N$87),N83,"") -> 10.3 | AQ83: =IF(C83="Ручная",O83,0) -> 0
A84: — | B84: Вернуться к началу цикла | C84: Переход | D84: Возврат на исходную позицию | E84: 10 | F84: 10.4 | G84: 10.8 | H84: 10.2 | I84: 10.6 | J84: 11 | K84: 10.3 | L84: 10.7 | M84: 10.1 | N84: 10.5 | O84: =IF(COUNT(AG84:AP84)>0,MIN(AG84:AP84),"") -> 10 | P84: =IF(COUNT(AG84:AP84)>0,MAX(AG84:AP84),"") -> 11 | Q84: =IF(ISNUMBER(O84),P84-O84,"") -> 1 | R84: =IF(ISNUMBER(O84),IF(C84="Ручная",IF($S$87>0,$R$87*Q84/$S$87,IF($W$87=10,$R$87,0)),0),"") -> 0 | S84: =IF(ISNUMBER(O84),O84+R84,"") -> 10 | T84: =IF(ISNUMBER(S84),P84-S84,"") -> 1 | U84: =IF(COUNT(AG84:AP84)>0,AVERAGE(AG84:AP84),"") -> 10.46 | AG84: =IF(ISNUMBER(E$87),E84,"") -> 10 | AH84: =IF(ISNUMBER(F$87),F84,"") -> 10.4 | AI84: =IF(ISNUMBER(G$87),G84,"") -> 10.8 | AJ84: =IF(ISNUMBER(H$87),H84,"") -> 10.2 | AK84: =IF(ISNUMBER(I$87),I84,"") -> 10.6 | AL84: =IF(ISNUMBER(J$87),J84,"") -> 11 | AM84: =IF(ISNUMBER(K$87),K84,"") -> 10.3 | AN84: =IF(ISNUMBER(L$87),L84,"") -> 10.7 | ... AP84: =IF(ISNUMBER(N$87),N84,"") -> 10.5 | AQ84: =IF(C84="Ручная",O84,0) -> 0
A85: — | B85: Внеплановый поиск тары / ожидание | C85: Потери | D85: Причина задержки устранена | E85: 12.24 | F85: 12.72 | G85: 13.2 | H85: 12.36 | I85: 12.84 | J85: 12.12 | K85: 12.6 | L85: 12 | M85: 12.48 | N85: 12.96 | O85: =IF(COUNT(AG85:AP85)>0,MIN(AG85:AP85),"") -> 12 | P85: =IF(COUNT(AG85:AP85)>0,MAX(AG85:AP85),"") -> 13.2 | Q85: =IF(ISNUMBER(O85),P85-O85,"") -> 1.2 | R85: =IF(ISNUMBER(O85),IF(C85="Ручная",IF($S$87>0,$R$87*Q85/$S$87,IF($W$87=11,$R$87,0)),0),"") -> 0 | S85: =IF(ISNUMBER(O85),O85+R85,"") -> 12 | T85: =IF(ISNUMBER(S85),P85-S85,"") -> 1.2 | U85: =IF(COUNT(AG85:AP85)>0,AVERAGE(AG85:AP85),"") -> 12.552 | AG85: =IF(ISNUMBER(E$87),E85,"") -> 12.24 | AH85: =IF(ISNUMBER(F$87),F85,"") -> 12.72 | AI85: =IF(ISNUMBER(G$87),G85,"") -> 13.2 | AJ85: =IF(ISNUMBER(H$87),H85,"") -> 12.36 | AK85: =IF(ISNUMBER(I$87),I85,"") -> 12.84 | AL85: =IF(ISNUMBER(J$87),J85,"") -> 12.12 | AM85: =IF(ISNUMBER(K$87),K85,"") -> 12.6 | AN85: =IF(ISNUMBER(L$87),L85,"") -> 12 | ... AP85: =IF(ISNUMBER(N$87),N85,"") -> 12.96 | AQ85: =IF(C85="Ручная",O85,0) -> 0
B86: ИТОГИ: все элементы цикла | E86: =IF(COUNT(E75:E85)=11,SUM(E75:E85),"") -> 399.33 | F86: =IF(COUNT(F75:F85)=11,SUM(F75:F85),"") -> 399.66 | G86: =IF(COUNT(G75:G85)=11,SUM(G75:G85),"") -> 399.54 | H86: =IF(COUNT(H75:H85)=11,SUM(H75:H85),"") -> 398.43 | I86: =IF(COUNT(I75:I85)=11,SUM(I75:I85),"") -> 398.32 | J86: =IF(COUNT(J75:J85)=11,SUM(J75:J85),"") -> 396.53 | K86: =IF(COUNT(K75:K85)=11,SUM(K75:K85),"") -> 399.97 | L86: =IF(COUNT(L75:L85)=11,SUM(L75:L85),"") -> 396.08 | ... U86: =IF(COUNT(U75:U85)=11,SUM(U75:U85),"") -> 398.614
B87: ТОЛЬКО полные учтённые циклы | E87: =IF(AND(E73=1,COUNT(E75:E85)=11,MIN(E75:E85)>=0),E86,"") -> 399.33 | F87: =IF(AND(F73=1,COUNT(F75:F85)=11,MIN(F75:F85)>=0),F86,"") -> 399.66 | G87: =IF(AND(G73=1,COUNT(G75:G85)=11,MIN(G75:G85)>=0),G86,"") -> 399.54 | H87: =IF(AND(H73=1,COUNT(H75:H85)=11,MIN(H75:H85)>=0),H86,"") -> 398.43 | I87: =IF(AND(I73=1,COUNT(I75:I85)=11,MIN(I75:I85)>=0),I86,"") -> 398.32 | J87: =IF(AND(J73=1,COUNT(J75:J85)=11,MIN(J75:J85)>=0),J86,"") -> 396.53 | K87: =IF(AND(K73=1,COUNT(K75:K85)=11,MIN(K75:K85)>=0),K86,"") -> 399.97 | L87: =IF(AND(L73=1,COUNT(L75:L85)=11,MIN(L75:L85)>=0),L86,"") -> 396.08 | ... N87: =IF(AND(N73=1,COUNT(N75:N85)=11,MIN(N75:N85)>=0),N86,"") -> 399.42 | O87: =IF(COUNT(E87:N87)>0,MIN(E87:N87),"") -> 396.08 | P87: =IF(COUNT(E87:N87)>0,MAX(E87:N87),"") -> 399.97 | Q87: =IF(ISNUMBER(O87),P87-O87,"") -> 3.89 | R87: =IF(ISNUMBER(O87),MAX(0,O87-O86),"") -> 7.08 | S87: =SUMIF(C75:C85,"Ручная",Q75:Q85) -> 16.5 | T87: =COUNT(E87:N87) -> 10 | U87: =IF(COUNT(E87:N87)>0,AVERAGE(E87:N87),"") -> 398.614 | V87: =IF(ISNUMBER(O87),S86-O87,"") -> 0 | W87: =MATCH(MAX(AQ75:AQ85),AQ75:AQ85,0) -> 2 | X87: =IF(T87=0,"НЕТ ЗАМЕРОВ",IF(T87<10,"МЕНЕЕ 10 ЦИКЛОВ",IF(ABS(V87)<0.000001,"ОК","ОШИБКА РЕГУЛИРОВКИ"))) -> ОК
A88: В строке учтённых циклов: O = T min; P = T max; Q = размах цикла; R = T min − сумма t min; S = сумма размахов ручных элементов; T = число циклов; U = среднее; V = сумма t отрег − T min (должно быть 0).
A91: 05. Белокочанная капуста · ДО · 10 демонстрационных циклов, заменить реальными
A92: ="Масса замера, кг: "&'Ассортимент'!J12&". Все замеры одной партии/исполнителя/условий. Основание: "&'Ввод'!B14 -> Масса замера, кг: 3. Все замеры одной партии/исполнителя/условий. Основание: ДЕМО: синтетические замеры; заменить фактическими
A93: № | B93: Рабочий элемент | C93: Тип | D93: Точка отсчёта | E93: 1 | F93: 2 | G93: 3 | H93: 4 | I93: 5 | J93: 6 | K93: 7 | L93: 8 | M93: 9 | N93: 10 | O93: t min | P93: t max | Q93: Размах | R93: Рег. с | S93: t отрег. | T93: Колебания | U93: Среднее | V93: Контроль | W93: Служебно | X93: Статус
B94: Учитывать цикл: 1 / 0 | E94: 1 | F94: 1 | G94: 1 | H94: 1 | I94: 1 | J94: 1 | K94: 1 | L94: 1 | M94: 1 | N94: 1
B95: Причина исключения / условия | E95: ДЕМО | F95: ДЕМО | G95: ДЕМО | H95: ДЕМО | I95: ДЕМО | J95: ДЕМО | K95: ДЕМО | L95: ДЕМО | M95: ДЕМО | N95: ДЕМО
A96: 1 | B96: Осмотреть упаковку и сырьё | C96: Ручная | D96: Осмотр партии завершён | E96: 26.5 | F96: 27.5 | G96: 25.75 | H96: 26.75 | I96: 25.25 | J96: 26.25 | K96: 25 | L96: 26 | M96: 27 | N96: 25.5 | O96: =IF(COUNT(AG96:AP96)>0,MIN(AG96:AP96),"") -> 25 | P96: =IF(COUNT(AG96:AP96)>0,MAX(AG96:AP96),"") -> 27.5 | Q96: =IF(ISNUMBER(O96),P96-O96,"") -> 2.5 | R96: =IF(ISNUMBER(O96),IF(C96="Ручная",IF($S$108>0,$R$108*Q96/$S$108,IF($W$108=1,$R$108,0)),0),"") -> 1.0108108 | S96: =IF(ISNUMBER(O96),O96+R96,"") -> 26.010811 | T96: =IF(ISNUMBER(S96),P96-S96,"") -> 1.4891892 | U96: =IF(COUNT(AG96:AP96)>0,AVERAGE(AG96:AP96),"") -> 26.15 | AG96: =IF(ISNUMBER(E$108),E96,"") -> 26.5 | AH96: =IF(ISNUMBER(F$108),F96,"") -> 27.5 | AI96: =IF(ISNUMBER(G$108),G96,"") -> 25.75 | AJ96: =IF(ISNUMBER(H$108),H96,"") -> 26.75 | AK96: =IF(ISNUMBER(I$108),I96,"") -> 25.25 | AL96: =IF(ISNUMBER(J$108),J96,"") -> 26.25 | AM96: =IF(ISNUMBER(K$108),K96,"") -> 25 | AN96: =IF(ISNUMBER(L$108),L96,"") -> 26 | ... AP96: =IF(ISNUMBER(N$108),N96,"") -> 25.5 | AQ96: =IF(C96="Ручная",O96,0) -> 25
A97: 2 | B97: Отсортировать / подготовить сырьё | C97: Ручная | D97: Подготовленное сырьё отложено | E97: 58.85 | F97: 55.55 | G97: 57.75 | H97: 55 | I97: 57.2 | J97: 59.4 | K97: 56.1 | L97: 58.3 | M97: 60.5 | N97: 56.65 | O97: =IF(COUNT(AG97:AP97)>0,MIN(AG97:AP97),"") -> 55 | P97: =IF(COUNT(AG97:AP97)>0,MAX(AG97:AP97),"") -> 60.5 | Q97: =IF(ISNUMBER(O97),P97-O97,"") -> 5.5 | R97: =IF(ISNUMBER(O97),IF(C97="Ручная",IF($S$108>0,$R$108*Q97/$S$108,IF($W$108=2,$R$108,0)),0),"") -> 2.2237838 | S97: =IF(ISNUMBER(O97),O97+R97,"") -> 57.223784 | T97: =IF(ISNUMBER(S97),P97-S97,"") -> 3.2762162 | U97: =IF(COUNT(AG97:AP97)>0,AVERAGE(AG97:AP97),"") -> 57.53 | AG97: =IF(ISNUMBER(E$108),E97,"") -> 58.85 | AH97: =IF(ISNUMBER(F$108),F97,"") -> 55.55 | AI97: =IF(ISNUMBER(G$108),G97,"") -> 57.75 | AJ97: =IF(ISNUMBER(H$108),H97,"") -> 55 | AK97: =IF(ISNUMBER(I$108),I97,"") -> 57.2 | AL97: =IF(ISNUMBER(J$108),J97,"") -> 59.4 | AM97: =IF(ISNUMBER(K$108),K97,"") -> 56.1 | AN97: =IF(ISNUMBER(L$108),L97,"") -> 58.3 | ... AP97: =IF(ISNUMBER(N$108),N97,"") -> 56.65 | AQ97: =IF(C97="Ручная",O97,0) -> 55
A98: 3 | B98: Отвесить допустимую партию | C98: Ручная | D98: Масса партии проверена | E98: 22 | F98: 22.88 | G98: 23.76 | H98: 22.44 | I98: 23.32 | J98: 24.2 | K98: 22.66 | L98: 23.54 | M98: 22.22 | N98: 23.1 | O98: =IF(COUNT(AG98:AP98)>0,MIN(AG98:AP98),"") -> 22 | P98: =IF(COUNT(AG98:AP98)>0,MAX(AG98:AP98),"") -> 24.2 | Q98: =IF(ISNUMBER(O98),P98-O98,"") -> 2.2 | R98: =IF(ISNUMBER(O98),IF(C98="Ручная",IF($S$108>0,$R$108*Q98/$S$108,IF($W$108=3,$R$108,0)),0),"") -> 0.88951351 | S98: =IF(ISNUMBER(O98),O98+R98,"") -> 22.889514 | T98: =IF(ISNUMBER(S98),P98-S98,"") -> 1.3104865 | U98: =IF(COUNT(AG98:AP98)>0,AVERAGE(AG98:AP98),"") -> 23.012 | AG98: =IF(ISNUMBER(E$108),E98,"") -> 22 | AH98: =IF(ISNUMBER(F$108),F98,"") -> 22.88 | AI98: =IF(ISNUMBER(G$108),G98,"") -> 23.76 | AJ98: =IF(ISNUMBER(H$108),H98,"") -> 22.44 | AK98: =IF(ISNUMBER(I$108),I98,"") -> 23.32 | AL98: =IF(ISNUMBER(J$108),J98,"") -> 24.2 | AM98: =IF(ISNUMBER(K$108),K98,"") -> 22.66 | AN98: =IF(ISNUMBER(L$108),L98,"") -> 23.54 | ... AP98: =IF(ISNUMBER(N$108),N98,"") -> 23.1 | AQ98: =IF(C98="Ручная",O98,0) -> 22
A99: — | B99: Перейти с партией к SOLIA | C99: Переход | D99: Оператор у SOLIA | E99: 12.24 | F99: 12.72 | G99: 13.2 | H99: 12.36 | I99: 12.84 | J99: 12.12 | K99: 12.6 | L99: 12 | M99: 12.48 | N99: 12.96 | O99: =IF(COUNT(AG99:AP99)>0,MIN(AG99:AP99),"") -> 12 | P99: =IF(COUNT(AG99:AP99)>0,MAX(AG99:AP99),"") -> 13.2 | Q99: =IF(ISNUMBER(O99),P99-O99,"") -> 1.2 | R99: =IF(ISNUMBER(O99),IF(C99="Ручная",IF($S$108>0,$R$108*Q99/$S$108,IF($W$108=4,$R$108,0)),0),"") -> 0 | S99: =IF(ISNUMBER(O99),O99+R99,"") -> 12 | T99: =IF(ISNUMBER(S99),P99-S99,"") -> 1.2 | U99: =IF(COUNT(AG99:AP99)>0,AVERAGE(AG99:AP99),"") -> 12.552 | AG99: =IF(ISNUMBER(E$108),E99,"") -> 12.24 | AH99: =IF(ISNUMBER(F$108),F99,"") -> 12.72 | AI99: =IF(ISNUMBER(G$108),G99,"") -> 13.2 | AJ99: =IF(ISNUMBER(H$108),H99,"") -> 12.36 | AK99: =IF(ISNUMBER(I$108),I99,"") -> 12.84 | AL99: =IF(ISNUMBER(J$108),J99,"") -> 12.12 | AM99: =IF(ISNUMBER(K$108),K99,"") -> 12.6 | AN99: =IF(ISNUMBER(L$108),L99,"") -> 12 | ... AP99: =IF(ISNUMBER(N$108),N99,"") -> 12.96 | AQ99: =IF(C99="Ручная",O99,0) -> 0
A100: 5 | B100: Загрузить, выбрать программу, запустить | C100: Ручная | D100: Программа запущена | E100: 36.05 | F100: 37.45 | G100: 35.35 | H100: 36.75 | I100: 35 | J100: 36.4 | K100: 37.8 | L100: 35.7 | M100: 37.1 | N100: 38.5 | O100: =IF(COUNT(AG100:AP100)>0,MIN(AG100:AP100),"") -> 35 | P100: =IF(COUNT(AG100:AP100)>0,MAX(AG100:AP100),"") -> 38.5 | Q100: =IF(ISNUMBER(O100),P100-O100,"") -> 3.5 | R100: =IF(ISNUMBER(O100),IF(C100="Ручная",IF($S$108>0,$R$108*Q100/$S$108,IF($W$108=5,$R$108,0)),0),"") -> 1.4151351 | S100: =IF(ISNUMBER(O100),O100+R100,"") -> 36.415135 | T100: =IF(ISNUMBER(S100),P100-S100,"") -> 2.0848649 | U100: =IF(COUNT(AG100:AP100)>0,AVERAGE(AG100:AP100),"") -> 36.61 | AG100: =IF(ISNUMBER(E$108),E100,"") -> 36.05 | AH100: =IF(ISNUMBER(F$108),F100,"") -> 37.45 | AI100: =IF(ISNUMBER(G$108),G100,"") -> 35.35 | AJ100: =IF(ISNUMBER(H$108),H100,"") -> 36.75 | AK100: =IF(ISNUMBER(I$108),I100,"") -> 35 | AL100: =IF(ISNUMBER(J$108),J100,"") -> 36.4 | AM100: =IF(ISNUMBER(K$108),K100,"") -> 37.8 | AN100: =IF(ISNUMBER(L$108),L100,"") -> 35.7 | ... AP100: =IF(ISNUMBER(N$108),N100,"") -> 38.5 | AQ100: =IF(C100="Ручная",O100,0) -> 35
A101: — | B101: Автоматическая программа / ожидание | C101: Авто/ожидание | D101: Полный цикл программы завершён | E101: ='Ассортимент'!R12 -> 180 | F101: ='Ассортимент'!R12 -> 180 | G101: ='Ассортимент'!R12 -> 180 | H101: ='Ассортимент'!R12 -> 180 | I101: ='Ассортимент'!R12 -> 180 | J101: ='Ассортимент'!R12 -> 180 | K101: ='Ассортимент'!R12 -> 180 | L101: ='Ассортимент'!R12 -> 180 | M101: ='Ассортимент'!R12 -> 180 | N101: ='Ассортимент'!R12 -> 180 | O101: =IF(COUNT(AG101:AP101)>0,MIN(AG101:AP101),"") -> 180 | P101: =IF(COUNT(AG101:AP101)>0,MAX(AG101:AP101),"") -> 180 | Q101: =IF(ISNUMBER(O101),P101-O101,"") -> 0 | R101: =IF(ISNUMBER(O101),IF(C101="Ручная",IF($S$108>0,$R$108*Q101/$S$108,IF($W$108=6,$R$108,0)),0),"") -> 0 | S101: =IF(ISNUMBER(O101),O101+R101,"") -> 180 | T101: =IF(ISNUMBER(S101),P101-S101,"") -> 0 | U101: =IF(COUNT(AG101:AP101)>0,AVERAGE(AG101:AP101),"") -> 180 | AG101: =IF(ISNUMBER(E$108),E101,"") -> 180 | AH101: =IF(ISNUMBER(F$108),F101,"") -> 180 | AI101: =IF(ISNUMBER(G$108),G101,"") -> 180 | AJ101: =IF(ISNUMBER(H$108),H101,"") -> 180 | AK101: =IF(ISNUMBER(I$108),I101,"") -> 180 | AL101: =IF(ISNUMBER(J$108),J101,"") -> 180 | AM101: =IF(ISNUMBER(K$108),K101,"") -> 180 | AN101: =IF(ISNUMBER(L$108),L101,"") -> 180 | ... AP101: =IF(ISNUMBER(N$108),N101,"") -> 180 | AQ101: =IF(C101="Ручная",O101,0) -> 0
A102: 7 | B102: Выгрузить в чистую маркированную тару | C102: Ручная | D102: Выгрузка завершена | E102: 32.4 | F102: 30.6 | G102: 31.8 | H102: 33 | I102: 30.9 | J102: 32.1 | K102: 30.3 | L102: 31.5 | M102: 30 | N102: 31.2 | O102: =IF(COUNT(AG102:AP102)>0,MIN(AG102:AP102),"") -> 30 | P102: =IF(COUNT(AG102:AP102)>0,MAX(AG102:AP102),"") -> 33 | Q102: =IF(ISNUMBER(O102),P102-O102,"") -> 3 | R102: =IF(ISNUMBER(O102),IF(C102="Ручная",IF($S$108>0,$R$108*Q102/$S$108,IF($W$108=7,$R$108,0)),0),"") -> 1.212973 | S102: =IF(ISNUMBER(O102),O102+R102,"") -> 31.212973 | T102: =IF(ISNUMBER(S102),P102-S102,"") -> 1.787027 | U102: =IF(COUNT(AG102:AP102)>0,AVERAGE(AG102:AP102),"") -> 31.38 | AG102: =IF(ISNUMBER(E$108),E102,"") -> 32.4 | AH102: =IF(ISNUMBER(F$108),F102,"") -> 30.6 | AI102: =IF(ISNUMBER(G$108),G102,"") -> 31.8 | AJ102: =IF(ISNUMBER(H$108),H102,"") -> 33 | AK102: =IF(ISNUMBER(I$108),I102,"") -> 30.9 | AL102: =IF(ISNUMBER(J$108),J102,"") -> 32.1 | AM102: =IF(ISNUMBER(K$108),K102,"") -> 30.3 | AN102: =IF(ISNUMBER(L$108),L102,"") -> 31.5 | ... AP102: =IF(ISNUMBER(N$108),N102,"") -> 31.2 | AQ102: =IF(C102="Ручная",O102,0) -> 30
A103: 8 | B103: Проверить качество и маркировку | C103: Ручная | D103: Результат проверки подтверждён | E103: 19.8 | F103: 18.54 | G103: 19.26 | H103: 18.18 | I103: 18.9 | J103: 18 | K103: 18.72 | L103: 19.44 | M103: 18.36 | N103: 19.08 | O103: =IF(COUNT(AG103:AP103)>0,MIN(AG103:AP103),"") -> 18 | P103: =IF(COUNT(AG103:AP103)>0,MAX(AG103:AP103),"") -> 19.8 | Q103: =IF(ISNUMBER(O103),P103-O103,"") -> 1.8 | R103: =IF(ISNUMBER(O103),IF(C103="Ручная",IF($S$108>0,$R$108*Q103/$S$108,IF($W$108=8,$R$108,0)),0),"") -> 0.72778378 | S103: =IF(ISNUMBER(O103),O103+R103,"") -> 18.727784 | T103: =IF(ISNUMBER(S103),P103-S103,"") -> 1.0722162 | U103: =IF(COUNT(AG103:AP103)>0,AVERAGE(AG103:AP103),"") -> 18.828 | AG103: =IF(ISNUMBER(E$108),E103,"") -> 19.8 | AH103: =IF(ISNUMBER(F$108),F103,"") -> 18.54 | AI103: =IF(ISNUMBER(G$108),G103,"") -> 19.26 | AJ103: =IF(ISNUMBER(H$108),H103,"") -> 18.18 | AK103: =IF(ISNUMBER(I$108),I103,"") -> 18.9 | AL103: =IF(ISNUMBER(J$108),J103,"") -> 18 | AM103: =IF(ISNUMBER(K$108),K103,"") -> 18.72 | AN103: =IF(ISNUMBER(L$108),L103,"") -> 19.44 | ... AP103: =IF(ISNUMBER(N$108),N103,"") -> 19.08 | AQ103: =IF(C103="Ручная",O103,0) -> 18
A104: — | B104: Передать в зону чистой продукции | C104: Переход | D104: Партия передана | E104: 10.1 | F104: 10.5 | G104: 10 | H104: 10.4 | I104: 10.8 | J104: 10.2 | K104: 10.6 | L104: 11 | M104: 10.3 | N104: 10.7 | O104: =IF(COUNT(AG104:AP104)>0,MIN(AG104:AP104),"") -> 10 | P104: =IF(COUNT(AG104:AP104)>0,MAX(AG104:AP104),"") -> 11 | Q104: =IF(ISNUMBER(O104),P104-O104,"") -> 1 | R104: =IF(ISNUMBER(O104),IF(C104="Ручная",IF($S$108>0,$R$108*Q104/$S$108,IF($W$108=9,$R$108,0)),0),"") -> 0 | S104: =IF(ISNUMBER(O104),O104+R104,"") -> 10 | T104: =IF(ISNUMBER(S104),P104-S104,"") -> 1 | U104: =IF(COUNT(AG104:AP104)>0,AVERAGE(AG104:AP104),"") -> 10.46 | AG104: =IF(ISNUMBER(E$108),E104,"") -> 10.1 | AH104: =IF(ISNUMBER(F$108),F104,"") -> 10.5 | AI104: =IF(ISNUMBER(G$108),G104,"") -> 10 | AJ104: =IF(ISNUMBER(H$108),H104,"") -> 10.4 | AK104: =IF(ISNUMBER(I$108),I104,"") -> 10.8 | AL104: =IF(ISNUMBER(J$108),J104,"") -> 10.2 | AM104: =IF(ISNUMBER(K$108),K104,"") -> 10.6 | AN104: =IF(ISNUMBER(L$108),L104,"") -> 11 | ... AP104: =IF(ISNUMBER(N$108),N104,"") -> 10.7 | AQ104: =IF(C104="Ручная",O104,0) -> 0
A105: — | B105: Вернуться к началу цикла | C105: Переход | D105: Возврат на исходную позицию | E105: 10.4 | F105: 10.8 | G105: 10.2 | H105: 10.6 | I105: 11 | J105: 10.3 | K105: 10.7 | L105: 10.1 | M105: 10.5 | N105: 10 | O105: =IF(COUNT(AG105:AP105)>0,MIN(AG105:AP105),"") -> 10 | P105: =IF(COUNT(AG105:AP105)>0,MAX(AG105:AP105),"") -> 11 | Q105: =IF(ISNUMBER(O105),P105-O105,"") -> 1 | R105: =IF(ISNUMBER(O105),IF(C105="Ручная",IF($S$108>0,$R$108*Q105/$S$108,IF($W$108=10,$R$108,0)),0),"") -> 0 | S105: =IF(ISNUMBER(O105),O105+R105,"") -> 10 | T105: =IF(ISNUMBER(S105),P105-S105,"") -> 1 | U105: =IF(COUNT(AG105:AP105)>0,AVERAGE(AG105:AP105),"") -> 10.46 | AG105: =IF(ISNUMBER(E$108),E105,"") -> 10.4 | AH105: =IF(ISNUMBER(F$108),F105,"") -> 10.8 | AI105: =IF(ISNUMBER(G$108),G105,"") -> 10.2 | AJ105: =IF(ISNUMBER(H$108),H105,"") -> 10.6 | AK105: =IF(ISNUMBER(I$108),I105,"") -> 11 | AL105: =IF(ISNUMBER(J$108),J105,"") -> 10.3 | AM105: =IF(ISNUMBER(K$108),K105,"") -> 10.7 | AN105: =IF(ISNUMBER(L$108),L105,"") -> 10.1 | ... AP105: =IF(ISNUMBER(N$108),N105,"") -> 10 | AQ105: =IF(C105="Ручная",O105,0) -> 0
A106: — | B106: Внеплановый поиск тары / ожидание | C106: Потери | D106: Причина задержки устранена | E106: 12.72 | F106: 13.2 | G106: 12.36 | H106: 12.84 | I106: 12.12 | J106: 12.6 | K106: 12 | L106: 12.48 | M106: 12.96 | N106: 12.24 | O106: =IF(COUNT(AG106:AP106)>0,MIN(AG106:AP106),"") -> 12 | P106: =IF(COUNT(AG106:AP106)>0,MAX(AG106:AP106),"") -> 13.2 | Q106: =IF(ISNUMBER(O106),P106-O106,"") -> 1.2 | R106: =IF(ISNUMBER(O106),IF(C106="Ручная",IF($S$108>0,$R$108*Q106/$S$108,IF($W$108=11,$R$108,0)),0),"") -> 0 | S106: =IF(ISNUMBER(O106),O106+R106,"") -> 12 | T106: =IF(ISNUMBER(S106),P106-S106,"") -> 1.2 | U106: =IF(COUNT(AG106:AP106)>0,AVERAGE(AG106:AP106),"") -> 12.552 | AG106: =IF(ISNUMBER(E$108),E106,"") -> 12.72 | AH106: =IF(ISNUMBER(F$108),F106,"") -> 13.2 | AI106: =IF(ISNUMBER(G$108),G106,"") -> 12.36 | AJ106: =IF(ISNUMBER(H$108),H106,"") -> 12.84 | AK106: =IF(ISNUMBER(I$108),I106,"") -> 12.12 | AL106: =IF(ISNUMBER(J$108),J106,"") -> 12.6 | AM106: =IF(ISNUMBER(K$108),K106,"") -> 12 | AN106: =IF(ISNUMBER(L$108),L106,"") -> 12.48 | ... AP106: =IF(ISNUMBER(N$108),N106,"") -> 12.24 | AQ106: =IF(C106="Ручная",O106,0) -> 0
B107: ИТОГИ: все элементы цикла | E107: =IF(COUNT(E96:E106)=11,SUM(E96:E106),"") -> 421.06 | F107: =IF(COUNT(F96:F106)=11,SUM(F96:F106),"") -> 419.74 | G107: =IF(COUNT(G96:G106)=11,SUM(G96:G106),"") -> 419.43 | H107: =IF(COUNT(H96:H106)=11,SUM(H96:H106),"") -> 418.32 | I107: =IF(COUNT(I96:I106)=11,SUM(I96:I106),"") -> 417.33 | J107: =IF(COUNT(J96:J106)=11,SUM(J96:J106),"") -> 421.57 | K107: =IF(COUNT(K96:K106)=11,SUM(K96:K106),"") -> 416.48 | L107: =IF(COUNT(L96:L106)=11,SUM(L96:L106),"") -> 420.06 | ... U107: =IF(COUNT(U96:U106)=11,SUM(U96:U106),"") -> 419.534
B108: ТОЛЬКО полные учтённые циклы | E108: =IF(AND(E94=1,COUNT(E96:E106)=11,MIN(E96:E106)>=0),E107,"") -> 421.06 | F108: =IF(AND(F94=1,COUNT(F96:F106)=11,MIN(F96:F106)>=0),F107,"") -> 419.74 | G108: =IF(AND(G94=1,COUNT(G96:G106)=11,MIN(G96:G106)>=0),G107,"") -> 419.43 | H108: =IF(AND(H94=1,COUNT(H96:H106)=11,MIN(H96:H106)>=0),H107,"") -> 418.32 | I108: =IF(AND(I94=1,COUNT(I96:I106)=11,MIN(I96:I106)>=0),I107,"") -> 417.33 | J108: =IF(AND(J94=1,COUNT(J96:J106)=11,MIN(J96:J106)>=0),J107,"") -> 421.57 | K108: =IF(AND(K94=1,COUNT(K96:K106)=11,MIN(K96:K106)>=0),K107,"") -> 416.48 | L108: =IF(AND(L94=1,COUNT(L96:L106)=11,MIN(L96:L106)>=0),L107,"") -> 420.06 | ... N108: =IF(AND(N94=1,COUNT(N96:N106)=11,MIN(N96:N106)>=0),N107,"") -> 419.93 | O108: =IF(COUNT(E108:N108)>0,MIN(E108:N108),"") -> 416.48 | P108: =IF(COUNT(E108:N108)>0,MAX(E108:N108),"") -> 421.57 | Q108: =IF(ISNUMBER(O108),P108-O108,"") -> 5.09 | R108: =IF(ISNUMBER(O108),MAX(0,O108-O107),"") -> 7.48 | S108: =SUMIF(C96:C106,"Ручная",Q96:Q106) -> 18.5 | T108: =COUNT(E108:N108) -> 10 | U108: =IF(COUNT(E108:N108)>0,AVERAGE(E108:N108),"") -> 419.534 | V108: =IF(ISNUMBER(O108),S107-O108,"") -> 0 | W108: =MATCH(MAX(AQ96:AQ106),AQ96:AQ106,0) -> 2 | X108: =IF(T108=0,"НЕТ ЗАМЕРОВ",IF(T108<10,"МЕНЕЕ 10 ЦИКЛОВ",IF(ABS(V108)<0.000001,"ОК","ОШИБКА РЕГУЛИРОВКИ"))) -> ОК
A109: В строке учтённых циклов: O = T min; P = T max; Q = размах цикла; R = T min − сумма t min; S = сумма размахов ручных элементов; T = число циклов; U = среднее; V = сумма t отрег − T min (должно быть 0).
A112: 06. Укроп · ДО · 10 демонстрационных циклов, заменить реальными
...

Sheet Замеры ЦЕЛЬ
A1: 04 / ПОЭЛЕМЕНТНЫЕ ЗАМЕРЫ · ЦЕЛЬ · ВСЕ 18 ПРОДУКТОВ
A2: ДЕМО / ПРОЕКТ • Жёлтые ячейки — ваш ввод. Расчёты не являются утверждёнными нормативами.
A3: ← Начало | B3: Синий фон — формула; серый — инструкция; жёлтый — ввод. Защита снимается без пароля.
A5: Вводите длительность каждого элемента в секундах, НЕ накопительные отсечки. Флаг 0 исключает ВЕСЬ цикл. Если хотя бы один элемент пустой/ошибочный — весь цикл автоматически исключается.
A7: 01. Латук · ЦЕЛЬ · 10 демонстрационных циклов, заменить реальными
A8: ="Масса замера, кг: "&'Ассортимент'!J8&". Все замеры одной партии/исполнителя/условий. Основание: "&'Ввод'!B15 -> Масса замера, кг: 1.5. Все замеры одной партии/исполнителя/условий. Основание: ДЕМО: прогноз; улучшения не внедрены
A9: № | B9: Рабочий элемент | C9: Тип | D9: Точка отсчёта | E9: 1 | F9: 2 | G9: 3 | H9: 4 | I9: 5 | J9: 6 | K9: 7 | L9: 8 | M9: 9 | N9: 10 | O9: t min | P9: t max | Q9: Размах | R9: Рег. с | S9: t отрег. | T9: Колебания | U9: Среднее | V9: Контроль | W9: Служебно | X9: Статус
B10: Учитывать цикл: 1 / 0 | E10: 1 | F10: 1 | G10: 1 | H10: 1 | I10: 1 | J10: 1 | K10: 1 | L10: 1 | M10: 1 | N10: 1
B11: Причина исключения / условия | E11: ДЕМО | F11: ДЕМО | G11: ДЕМО | H11: ДЕМО | I11: ДЕМО | J11: ДЕМО | K11: ДЕМО | L11: ДЕМО | M11: ДЕМО | N11: ДЕМО
A12: 1 | B12: Осмотреть упаковку и сырьё | C12: Ручная | D12: Осмотр партии завершён | E12: 25 | F12: 26 | G12: 27 | H12: 25.5 | I12: 26.5 | J12: 27.5 | K12: 25.75 | L12: 26.75 | M12: 25.25 | N12: 26.25 | O12: =IF(COUNT(AG12:AP12)>0,MIN(AG12:AP12),"") -> 25 | P12: =IF(COUNT(AG12:AP12)>0,MAX(AG12:AP12),"") -> 27.5 | Q12: =IF(ISNUMBER(O12),P12-O12,"") -> 2.5 | R12: =IF(ISNUMBER(O12),IF(C12="Ручная",IF($S$24>0,$R$24*Q12/$S$24,IF($W$24=1,$R$24,0)),0),"") -> 0.78665756 | S12: =IF(ISNUMBER(O12),O12+R12,"") -> 25.786658 | T12: =IF(ISNUMBER(S12),P12-S12,"") -> 1.7133424 | U12: =IF(COUNT(AG12:AP12)>0,AVERAGE(AG12:AP12),"") -> 26.15 | AG12: =IF(ISNUMBER(E$24),E12,"") -> 25 | AH12: =IF(ISNUMBER(F$24),F12,"") -> 26 | AI12: =IF(ISNUMBER(G$24),G12,"") -> 27 | AJ12: =IF(ISNUMBER(H$24),H12,"") -> 25.5 | AK12: =IF(ISNUMBER(I$24),I12,"") -> 26.5 | AL12: =IF(ISNUMBER(J$24),J12,"") -> 27.5 | AM12: =IF(ISNUMBER(K$24),K12,"") -> 25.75 | AN12: =IF(ISNUMBER(L$24),L12,"") -> 26.75 | ... AP12: =IF(ISNUMBER(N$24),N12,"") -> 26.25 | AQ12: =IF(C12="Ручная",O12,0) -> 25
A13: 2 | B13: Отсортировать / подготовить сырьё | C13: Ручная | D13: Подготовленное сырьё отложено | E13: 102 | F13: 106 | G13: 110 | H13: 103 | I13: 107 | J13: 101 | K13: 105 | L13: 100 | M13: 104 | N13: 108 | O13: =IF(COUNT(AG13:AP13)>0,MIN(AG13:AP13),"") -> 100 | P13: =IF(COUNT(AG13:AP13)>0,MAX(AG13:AP13),"") -> 110 | Q13: =IF(ISNUMBER(O13),P13-O13,"") -> 10 | R13: =IF(ISNUMBER(O13),IF(C13="Ручная",IF($S$24>0,$R$24*Q13/$S$24,IF($W$24=2,$R$24,0)),0),"") -> 3.1466302 | S13: =IF(ISNUMBER(O13),O13+R13,"") -> 103.14663 | T13: =IF(ISNUMBER(S13),P13-S13,"") -> 6.8533698 | U13: =IF(COUNT(AG13:AP13)>0,AVERAGE(AG13:AP13),"") -> 104.6 | AG13: =IF(ISNUMBER(E$24),E13,"") -> 102 | AH13: =IF(ISNUMBER(F$24),F13,"") -> 106 | AI13: =IF(ISNUMBER(G$24),G13,"") -> 110 | AJ13: =IF(ISNUMBER(H$24),H13,"") -> 103 | AK13: =IF(ISNUMBER(I$24),I13,"") -> 107 | AL13: =IF(ISNUMBER(J$24),J13,"") -> 101 | AM13: =IF(ISNUMBER(K$24),K13,"") -> 105 | AN13: =IF(ISNUMBER(L$24),L13,"") -> 100 | ... AP13: =IF(ISNUMBER(N$24),N13,"") -> 108 | AQ13: =IF(C13="Ручная",O13,0) -> 100
A14: 3 | B14: Отвесить допустимую партию | C14: Ручная | D14: Масса партии проверена | E14: 20.39 | F14: 21.19 | G14: 20 | H14: 20.79 | I14: 19.8 | J14: 20.59 | K14: 21.38 | L14: 20.2 | M14: 20.99 | N14: 21.78 | O14: =IF(COUNT(AG14:AP14)>0,MIN(AG14:AP14),"") -> 19.8 | P14: =IF(COUNT(AG14:AP14)>0,MAX(AG14:AP14),"") -> 21.78 | Q14: =IF(ISNUMBER(O14),P14-O14,"") -> 1.98 | R14: =IF(ISNUMBER(O14),IF(C14="Ручная",IF($S$24>0,$R$24*Q14/$S$24,IF($W$24=3,$R$24,0)),0),"") -> 0.62303279 | S14: =IF(ISNUMBER(O14),O14+R14,"") -> 20.423033 | T14: =IF(ISNUMBER(S14),P14-S14,"") -> 1.3569672 | U14: =IF(COUNT(AG14:AP14)>0,AVERAGE(AG14:AP14),"") -> 20.711 | AG14: =IF(ISNUMBER(E$24),E14,"") -> 20.39 | AH14: =IF(ISNUMBER(F$24),F14,"") -> 21.19 | AI14: =IF(ISNUMBER(G$24),G14,"") -> 20 | AJ14: =IF(ISNUMBER(H$24),H14,"") -> 20.79 | AK14: =IF(ISNUMBER(I$24),I14,"") -> 19.8 | AL14: =IF(ISNUMBER(J$24),J14,"") -> 20.59 | AM14: =IF(ISNUMBER(K$24),K14,"") -> 21.38 | AN14: =IF(ISNUMBER(L$24),L14,"") -> 20.2 | ... AP14: =IF(ISNUMBER(N$24),N14,"") -> 21.78 | AQ14: =IF(C14="Ручная",O14,0) -> 19.8
A15: — | B15: Перейти с партией к SOLIA | C15: Переход | D15: Оператор у SOLIA | E15: 6.3 | F15: 6 | G15: 6.24 | H15: 6.48 | I15: 6.12 | J15: 6.36 | K15: 6.6 | L15: 6.18 | M15: 6.42 | N15: 6.06 | O15: =IF(COUNT(AG15:AP15)>0,MIN(AG15:AP15),"") -> 6 | P15: =IF(COUNT(AG15:AP15)>0,MAX(AG15:AP15),"") -> 6.6 | Q15: =IF(ISNUMBER(O15),P15-O15,"") -> 0.6 | R15: =IF(ISNUMBER(O15),IF(C15="Ручная",IF($S$24>0,$R$24*Q15/$S$24,IF($W$24=4,$R$24,0)),0),"") -> 0 | S15: =IF(ISNUMBER(O15),O15+R15,"") -> 6 | T15: =IF(ISNUMBER(S15),P15-S15,"") -> 0.6 | U15: =IF(COUNT(AG15:AP15)>0,AVERAGE(AG15:AP15),"") -> 6.276 | AG15: =IF(ISNUMBER(E$24),E15,"") -> 6.3 | AH15: =IF(ISNUMBER(F$24),F15,"") -> 6 | AI15: =IF(ISNUMBER(G$24),G15,"") -> 6.24 | AJ15: =IF(ISNUMBER(H$24),H15,"") -> 6.48 | AK15: =IF(ISNUMBER(I$24),I15,"") -> 6.12 | AL15: =IF(ISNUMBER(J$24),J15,"") -> 6.36 | AM15: =IF(ISNUMBER(K$24),K15,"") -> 6.6 | AN15: =IF(ISNUMBER(L$24),L15,"") -> 6.18 | ... AP15: =IF(ISNUMBER(N$24),N15,"") -> 6.06 | AQ15: =IF(C15="Ручная",O15,0) -> 0
A16: 5 | B16: Загрузить, выбрать программу, запустить | C16: Ручная | D16: Программа запущена | E16: 32.13 | F16: 30.34 | G16: 31.54 | H16: 32.73 | I16: 30.64 | J16: 31.83 | K16: 30.05 | L16: 31.24 | M16: 29.75 | N16: 30.94 | O16: =IF(COUNT(AG16:AP16)>0,MIN(AG16:AP16),"") -> 29.75 | P16: =IF(COUNT(AG16:AP16)>0,MAX(AG16:AP16),"") -> 32.73 | Q16: =IF(ISNUMBER(O16),P16-O16,"") -> 2.98 | R16: =IF(ISNUMBER(O16),IF(C16="Ручная",IF($S$24>0,$R$24*Q16/$S$24,IF($W$24=5,$R$24,0)),0),"") -> 0.93769581 | S16: =IF(ISNUMBER(O16),O16+R16,"") -> 30.687696 | T16: =IF(ISNUMBER(S16),P16-S16,"") -> 2.0423042 | U16: =IF(COUNT(AG16:AP16)>0,AVERAGE(AG16:AP16),"") -> 31.119 | AG16: =IF(ISNUMBER(E$24),E16,"") -> 32.13 | AH16: =IF(ISNUMBER(F$24),F16,"") -> 30.34 | AI16: =IF(ISNUMBER(G$24),G16,"") -> 31.54 | AJ16: =IF(ISNUMBER(H$24),H16,"") -> 32.73 | AK16: =IF(ISNUMBER(I$24),I16,"") -> 30.64 | AL16: =IF(ISNUMBER(J$24),J16,"") -> 31.83 | AM16: =IF(ISNUMBER(K$24),K16,"") -> 30.05 | AN16: =IF(ISNUMBER(L$24),L16,"") -> 31.24 | ... AP16: =IF(ISNUMBER(N$24),N16,"") -> 30.94 | AQ16: =IF(C16="Ручная",O16,0) -> 29.75
A17: — | B17: Автоматическая программа / ожидание | C17: Авто/ожидание | D17: Полный цикл программы завершён | E17: ='Ассортимент'!R8 -> 450 | F17: ='Ассортимент'!R8 -> 450 | G17: ='Ассортимент'!R8 -> 450 | H17: ='Ассортимент'!R8 -> 450 | I17: ='Ассортимент'!R8 -> 450 | J17: ='Ассортимент'!R8 -> 450 | K17: ='Ассортимент'!R8 -> 450 | L17: ='Ассортимент'!R8 -> 450 | M17: ='Ассортимент'!R8 -> 450 | N17: ='Ассортимент'!R8 -> 450 | O17: =IF(COUNT(AG17:AP17)>0,MIN(AG17:AP17),"") -> 450 | P17: =IF(COUNT(AG17:AP17)>0,MAX(AG17:AP17),"") -> 450 | Q17: =IF(ISNUMBER(O17),P17-O17,"") -> 0 | R17: =IF(ISNUMBER(O17),IF(C17="Ручная",IF($S$24>0,$R$24*Q17/$S$24,IF($W$24=6,$R$24,0)),0),"") -> 0 | S17: =IF(ISNUMBER(O17),O17+R17,"") -> 450 | T17: =IF(ISNUMBER(S17),P17-S17,"") -> 0 | U17: =IF(COUNT(AG17:AP17)>0,AVERAGE(AG17:AP17),"") -> 450 | AG17: =IF(ISNUMBER(E$24),E17,"") -> 450 | AH17: =IF(ISNUMBER(F$24),F17,"") -> 450 | AI17: =IF(ISNUMBER(G$24),G17,"") -> 450 | AJ17: =IF(ISNUMBER(H$24),H17,"") -> 450 | AK17: =IF(ISNUMBER(I$24),I17,"") -> 450 | AL17: =IF(ISNUMBER(J$24),J17,"") -> 450 | AM17: =IF(ISNUMBER(K$24),K17,"") -> 450 | AN17: =IF(ISNUMBER(L$24),L17,"") -> 450 | ... AP17: =IF(ISNUMBER(N$24),N17,"") -> 450 | AQ17: =IF(C17="Ручная",O17,0) -> 0
A18: 7 | B18: Выгрузить в чистую маркированную тару | C18: Ручная | D18: Выгрузка завершена | E18: 27.27 | F18: 28.35 | G18: 27 | H18: 28.08 | I18: 29.16 | J18: 27.54 | K18: 28.62 | L18: 29.7 | M18: 27.81 | N18: 28.89 | O18: =IF(COUNT(AG18:AP18)>0,MIN(AG18:AP18),"") -> 27 | P18: =IF(COUNT(AG18:AP18)>0,MAX(AG18:AP18),"") -> 29.7 | Q18: =IF(ISNUMBER(O18),P18-O18,"") -> 2.7 | R18: =IF(ISNUMBER(O18),IF(C18="Ручная",IF($S$24>0,$R$24*Q18/$S$24,IF($W$24=7,$R$24,0)),0),"") -> 0.84959016 | S18: =IF(ISNUMBER(O18),O18+R18,"") -> 27.84959 | T18: =IF(ISNUMBER(S18),P18-S18,"") -> 1.8504098 | U18: =IF(COUNT(AG18:AP18)>0,AVERAGE(AG18:AP18),"") -> 28.242 | AG18: =IF(ISNUMBER(E$24),E18,"") -> 27.27 | AH18: =IF(ISNUMBER(F$24),F18,"") -> 28.35 | AI18: =IF(ISNUMBER(G$24),G18,"") -> 27 | AJ18: =IF(ISNUMBER(H$24),H18,"") -> 28.08 | AK18: =IF(ISNUMBER(I$24),I18,"") -> 29.16 | AL18: =IF(ISNUMBER(J$24),J18,"") -> 27.54 | AM18: =IF(ISNUMBER(K$24),K18,"") -> 28.62 | AN18: =IF(ISNUMBER(L$24),L18,"") -> 29.7 | ... AP18: =IF(ISNUMBER(N$24),N18,"") -> 28.89 | AQ18: =IF(C18="Ручная",O18,0) -> 27
A19: 8 | B19: Проверить качество и маркировку | C19: Ручная | D19: Результат проверки подтверждён | E19: 18.72 | F19: 19.44 | G19: 18.36 | H19: 19.08 | I19: 19.8 | J19: 18.54 | K19: 19.26 | L19: 18.18 | M19: 18.9 | N19: 18 | O19: =IF(COUNT(AG19:AP19)>0,MIN(AG19:AP19),"") -> 18 | P19: =IF(COUNT(AG19:AP19)>0,MAX(AG19:AP19),"") -> 19.8 | Q19: =IF(ISNUMBER(O19),P19-O19,"") -> 1.8 | R19: =IF(ISNUMBER(O19),IF(C19="Ручная",IF($S$24>0,$R$24*Q19/$S$24,IF($W$24=8,$R$24,0)),0),"") -> 0.56639344 | S19: =IF(ISNUMBER(O19),O19+R19,"") -> 18.566393 | T19: =IF(ISNUMBER(S19),P19-S19,"") -> 1.2336066 | U19: =IF(COUNT(AG19:AP19)>0,AVERAGE(AG19:AP19),"") -> 18.828 | AG19: =IF(ISNUMBER(E$24),E19,"") -> 18.72 | AH19: =IF(ISNUMBER(F$24),F19,"") -> 19.44 | AI19: =IF(ISNUMBER(G$24),G19,"") -> 18.36 | AJ19: =IF(ISNUMBER(H$24),H19,"") -> 19.08 | AK19: =IF(ISNUMBER(I$24),I19,"") -> 19.8 | AL19: =IF(ISNUMBER(J$24),J19,"") -> 18.54 | AM19: =IF(ISNUMBER(K$24),K19,"") -> 19.26 | AN19: =IF(ISNUMBER(L$24),L19,"") -> 18.18 | ... AP19: =IF(ISNUMBER(N$24),N19,"") -> 18 | AQ19: =IF(C19="Ручная",O19,0) -> 18
A20: — | B20: Передать в зону чистой продукции | C20: Переход | D20: Партия передана | E20: 5.3 | F20: 5.5 | G20: 5.15 | H20: 5.35 | I20: 5.05 | J20: 5.25 | K20: 5 | L20: 5.2 | M20: 5.4 | N20: 5.1 | O20: =IF(COUNT(AG20:AP20)>0,MIN(AG20:AP20),"") -> 5 | P20: =IF(COUNT(AG20:AP20)>0,MAX(AG20:AP20),"") -> 5.5 | Q20: =IF(ISNUMBER(O20),P20-O20,"") -> 0.5 | R20: =IF(ISNUMBER(O20),IF(C20="Ручная",IF($S$24>0,$R$24*Q20/$S$24,IF($W$24=9,$R$24,0)),0),"") -> 0 | S20: =IF(ISNUMBER(O20),O20+R20,"") -> 5 | T20: =IF(ISNUMBER(S20),P20-S20,"") -> 0.5 | U20: =IF(COUNT(AG20:AP20)>0,AVERAGE(AG20:AP20),"") -> 5.23 | AG20: =IF(ISNUMBER(E$24),E20,"") -> 5.3 | AH20: =IF(ISNUMBER(F$24),F20,"") -> 5.5 | AI20: =IF(ISNUMBER(G$24),G20,"") -> 5.15 | AJ20: =IF(ISNUMBER(H$24),H20,"") -> 5.35 | AK20: =IF(ISNUMBER(I$24),I20,"") -> 5.05 | AL20: =IF(ISNUMBER(J$24),J20,"") -> 5.25 | AM20: =IF(ISNUMBER(K$24),K20,"") -> 5 | AN20: =IF(ISNUMBER(L$24),L20,"") -> 5.2 | ... AP20: =IF(ISNUMBER(N$24),N20,"") -> 5.1 | AQ20: =IF(C20="Ручная",O20,0) -> 0
A21: — | B21: Вернуться к началу цикла | C21: Переход | D21: Возврат на исходную позицию | E21: 5.35 | F21: 5.05 | G21: 5.25 | H21: 5 | I21: 5.2 | J21: 5.4 | K21: 5.1 | L21: 5.3 | M21: 5.5 | N21: 5.15 | O21: =IF(COUNT(AG21:AP21)>0,MIN(AG21:AP21),"") -> 5 | P21: =IF(COUNT(AG21:AP21)>0,MAX(AG21:AP21),"") -> 5.5 | Q21: =IF(ISNUMBER(O21),P21-O21,"") -> 0.5 | R21: =IF(ISNUMBER(O21),IF(C21="Ручная",IF($S$24>0,$R$24*Q21/$S$24,IF($W$24=10,$R$24,0)),0),"") -> 0 | S21: =IF(ISNUMBER(O21),O21+R21,"") -> 5 | T21: =IF(ISNUMBER(S21),P21-S21,"") -> 0.5 | U21: =IF(COUNT(AG21:AP21)>0,AVERAGE(AG21:AP21),"") -> 5.23 | AG21: =IF(ISNUMBER(E$24),E21,"") -> 5.35 | AH21: =IF(ISNUMBER(F$24),F21,"") -> 5.05 | AI21: =IF(ISNUMBER(G$24),G21,"") -> 5.25 | AJ21: =IF(ISNUMBER(H$24),H21,"") -> 5 | AK21: =IF(ISNUMBER(I$24),I21,"") -> 5.2 | AL21: =IF(ISNUMBER(J$24),J21,"") -> 5.4 | AM21: =IF(ISNUMBER(K$24),K21,"") -> 5.1 | AN21: =IF(ISNUMBER(L$24),L21,"") -> 5.3 | ... AP21: =IF(ISNUMBER(N$24),N21,"") -> 5.15 | AQ21: =IF(C21="Ручная",O21,0) -> 0
A22: — | B22: Внеплановый поиск тары / ожидание | C22: Потери | D22: Причина задержки устранена | E22: 0 | F22: 0 | G22: 0 | H22: 0 | I22: 0 | J22: 0 | K22: 0 | L22: 0 | M22: 0 | N22: 0 | O22: =IF(COUNT(AG22:AP22)>0,MIN(AG22:AP22),"") -> 0 | P22: =IF(COUNT(AG22:AP22)>0,MAX(AG22:AP22),"") -> 0 | Q22: =IF(ISNUMBER(O22),P22-O22,"") -> 0 | R22: =IF(ISNUMBER(O22),IF(C22="Ручная",IF($S$24>0,$R$24*Q22/$S$24,IF($W$24=11,$R$24,0)),0),"") -> 0 | S22: =IF(ISNUMBER(O22),O22+R22,"") -> 0 | T22: =IF(ISNUMBER(S22),P22-S22,"") -> 0 | U22: =IF(COUNT(AG22:AP22)>0,AVERAGE(AG22:AP22),"") -> 0 | AG22: =IF(ISNUMBER(E$24),E22,"") -> 0 | AH22: =IF(ISNUMBER(F$24),F22,"") -> 0 | AI22: =IF(ISNUMBER(G$24),G22,"") -> 0 | AJ22: =IF(ISNUMBER(H$24),H22,"") -> 0 | AK22: =IF(ISNUMBER(I$24),I22,"") -> 0 | AL22: =IF(ISNUMBER(J$24),J22,"") -> 0 | AM22: =IF(ISNUMBER(K$24),K22,"") -> 0 | AN22: =IF(ISNUMBER(L$24),L22,"") -> 0 | ... AP22: =IF(ISNUMBER(N$24),N22,"") -> 0 | AQ22: =IF(C22="Ручная",O22,0) -> 0
B23: ИТОГИ: все элементы цикла | E23: =IF(COUNT(E12:E22)=11,SUM(E12:E22),"") -> 692.46 | F23: =IF(COUNT(F12:F22)=11,SUM(F12:F22),"") -> 697.87 | G23: =IF(COUNT(G12:G22)=11,SUM(G12:G22),"") -> 700.54 | H23: =IF(COUNT(H12:H22)=11,SUM(H12:H22),"") -> 696.01 | I23: =IF(COUNT(I12:I22)=11,SUM(I12:I22),"") -> 699.27 | J23: =IF(COUNT(J12:J22)=11,SUM(J12:J22),"") -> 694.01 | K23: =IF(COUNT(K12:K22)=11,SUM(K12:K22),"") -> 696.76 | L23: =IF(COUNT(L12:L22)=11,SUM(L12:L22),"") -> 692.75 | ... U23: =IF(COUNT(U12:U22)=11,SUM(U12:U22),"") -> 696.386
B24: ТОЛЬКО полные учтённые циклы | E24: =IF(AND(E10=1,COUNT(E12:E22)=11,MIN(E12:E22)>=0),E23,"") -> 692.46 | F24: =IF(AND(F10=1,COUNT(F12:F22)=11,MIN(F12:F22)>=0),F23,"") -> 697.87 | G24: =IF(AND(G10=1,COUNT(G12:G22)=11,MIN(G12:G22)>=0),G23,"") -> 700.54 | H24: =IF(AND(H10=1,COUNT(H12:H22)=11,MIN(H12:H22)>=0),H23,"") -> 696.01 | I24: =IF(AND(I10=1,COUNT(I12:I22)=11,MIN(I12:I22)>=0),I23,"") -> 699.27 | J24: =IF(AND(J10=1,COUNT(J12:J22)=11,MIN(J12:J22)>=0),J23,"") -> 694.01 | K24: =IF(AND(K10=1,COUNT(K12:K22)=11,MIN(K12:K22)>=0),K23,"") -> 696.76 | L24: =IF(AND(L10=1,COUNT(L12:L22)=11,MIN(L12:L22)>=0),L23,"") -> 692.75 | ... N24: =IF(AND(N10=1,COUNT(N12:N22)=11,MIN(N12:N22)>=0),N23,"") -> 700.17 | O24: =IF(COUNT(E24:N24)>0,MIN(E24:N24),"") -> 692.46 | P24: =IF(COUNT(E24:N24)>0,MAX(E24:N24),"") -> 700.54 | Q24: =IF(ISNUMBER(O24),P24-O24,"") -> 8.08 | R24: =IF(ISNUMBER(O24),MAX(0,O24-O23),"") -> 6.91 | S24: =SUMIF(C12:C22,"Ручная",Q12:Q22) -> 21.96 | T24: =COUNT(E24:N24) -> 10 | U24: =IF(COUNT(E24:N24)>0,AVERAGE(E24:N24),"") -> 696.386 | V24: =IF(ISNUMBER(O24),S23-O24,"") -> 1.1368684e-13 | W24: =MATCH(MAX(AQ12:AQ22),AQ12:AQ22,0) -> 2 | X24: =IF(T24=0,"НЕТ ЗАМЕРОВ",IF(T24<10,"МЕНЕЕ 10 ЦИКЛОВ",IF(ABS(V24)<0.000001,"ОК","ОШИБКА РЕГУЛИРОВКИ"))) -> ОК
A25: В строке учтённых циклов: O = T min; P = T max; Q = размах цикла; R = T min − сумма t min; S = сумма размахов ручных элементов; T = число циклов; U = среднее; V = сумма t отрег − T min (должно быть 0).
A28: 02. Базилик · ЦЕЛЬ · 10 демонстрационных циклов, заменить реальными
A29: ="Масса замера, кг: "&'Ассортимент'!J9&". Все замеры одной партии/исполнителя/условий. Основание: "&'Ввод'!B15 -> Масса замера, кг: 1.5. Все замеры одной партии/исполнителя/условий. Основание: ДЕМО: прогноз; улучшения не внедрены
A30: № | B30: Рабочий элемент | C30: Тип | D30: Точка отсчёта | E30: 1 | F30: 2 | G30: 3 | H30: 4 | I30: 5 | J30: 6 | K30: 7 | L30: 8 | M30: 9 | N30: 10 | O30: t min | P30: t max | Q30: Размах | R30: Рег. с | S30: t отрег. | T30: Колебания | U30: Среднее | V30: Контроль | W30: Служебно | X30: Статус
B31: Учитывать цикл: 1 / 0 | E31: 1 | F31: 1 | G31: 1 | H31: 1 | I31: 1 | J31: 1 | K31: 1 | L31: 1 | M31: 1 | N31: 1
B32: Причина исключения / условия | E32: ДЕМО | F32: ДЕМО | G32: ДЕМО | H32: ДЕМО | I32: ДЕМО | J32: ДЕМО | K32: ДЕМО | L32: ДЕМО | M32: ДЕМО | N32: ДЕМО
A33: 1 | B33: Осмотреть упаковку и сырьё | C33: Ручная | D33: Осмотр партии завершён | E33: 26 | F33: 27 | G33: 25.5 | H33: 26.5 | I33: 27.5 | J33: 25.75 | K33: 26.75 | L33: 25.25 | M33: 26.25 | N33: 25 | O33: =IF(COUNT(AG33:AP33)>0,MIN(AG33:AP33),"") -> 25 | P33: =IF(COUNT(AG33:AP33)>0,MAX(AG33:AP33),"") -> 27.5 | Q33: =IF(ISNUMBER(O33),P33-O33,"") -> 2.5 | R33: =IF(ISNUMBER(O33),IF(C33="Ручная",IF($S$45>0,$R$45*Q33/$S$45,IF($W$45=1,$R$45,0)),0),"") -> 0.77417247 | S33: =IF(ISNUMBER(O33),O33+R33,"") -> 25.774172 | T33: =IF(ISNUMBER(S33),P33-S33,"") -> 1.7258275 | U33: =IF(COUNT(AG33:AP33)>0,AVERAGE(AG33:AP33),"") -> 26.15 | AG33: =IF(ISNUMBER(E$45),E33,"") -> 26 | AH33: =IF(ISNUMBER(F$45),F33,"") -> 27 | AI33: =IF(ISNUMBER(G$45),G33,"") -> 25.5 | AJ33: =IF(ISNUMBER(H$45),H33,"") -> 26.5 | AK33: =IF(ISNUMBER(I$45),I33,"") -> 27.5 | AL33: =IF(ISNUMBER(J$45),J33,"") -> 25.75 | AM33: =IF(ISNUMBER(K$45),K33,"") -> 26.75 | AN33: =IF(ISNUMBER(L$45),L33,"") -> 25.25 | ... AP33: =IF(ISNUMBER(N$45),N33,"") -> 25 | AQ33: =IF(C33="Ручная",O33,0) -> 25
A34: 2 | B34: Отсортировать / подготовить сырьё | C34: Ручная | D34: Подготовленное сырьё отложено | E34: 116.6 | F34: 121 | G34: 113.3 | H34: 117.7 | I34: 111.1 | J34: 115.5 | K34: 110 | L34: 114.4 | M34: 118.8 | N34: 112.2 | O34: =IF(COUNT(AG34:AP34)>0,MIN(AG34:AP34),"") -> 110 | P34: =IF(COUNT(AG34:AP34)>0,MAX(AG34:AP34),"") -> 121 | Q34: =IF(ISNUMBER(O34),P34-O34,"") -> 11 | R34: =IF(ISNUMBER(O34),IF(C34="Ручная",IF($S$45>0,$R$45*Q34/$S$45,IF($W$45=2,$R$45,0)),0),"") -> 3.4063589 | S34: =IF(ISNUMBER(O34),O34+R34,"") -> 113.40636 | T34: =IF(ISNUMBER(S34),P34-S34,"") -> 7.5936411 | U34: =IF(COUNT(AG34:AP34)>0,AVERAGE(AG34:AP34),"") -> 115.06 | AG34: =IF(ISNUMBER(E$45),E34,"") -> 116.6 | AH34: =IF(ISNUMBER(F$45),F34,"") -> 121 | AI34: =IF(ISNUMBER(G$45),G34,"") -> 113.3 | AJ34: =IF(ISNUMBER(H$45),H34,"") -> 117.7 | AK34: =IF(ISNUMBER(I$45),I34,"") -> 111.1 | AL34: =IF(ISNUMBER(J$45),J34,"") -> 115.5 | AM34: =IF(ISNUMBER(K$45),K34,"") -> 110 | AN34: =IF(ISNUMBER(L$45),L34,"") -> 114.4 | ... AP34: =IF(ISNUMBER(N$45),N34,"") -> 112.2 | AQ34: =IF(C34="Ручная",O34,0) -> 110
A35: 3 | B35: Отвесить допустимую партию | C35: Ручная | D35: Масса партии проверена | E35: 21.19 | F35: 20 | G35: 20.79 | H35: 19.8 | I35: 20.59 | J35: 21.38 | K35: 20.2 | L35: 20.99 | M35: 21.78 | N35: 20.39 | O35: =IF(COUNT(AG35:AP35)>0,MIN(AG35:AP35),"") -> 19.8 | P35: =IF(COUNT(AG35:AP35)>0,MAX(AG35:AP35),"") -> 21.78 | Q35: =IF(ISNUMBER(O35),P35-O35,"") -> 1.98 | R35: =IF(ISNUMBER(O35),IF(C35="Ручная",IF($S$45>0,$R$45*Q35/$S$45,IF($W$45=3,$R$45,0)),0),"") -> 0.6131446 | S35: =IF(ISNUMBER(O35),O35+R35,"") -> 20.413145 | T35: =IF(ISNUMBER(S35),P35-S35,"") -> 1.3668554 | U35: =IF(COUNT(AG35:AP35)>0,AVERAGE(AG35:AP35),"") -> 20.711 | AG35: =IF(ISNUMBER(E$45),E35,"") -> 21.19 | AH35: =IF(ISNUMBER(F$45),F35,"") -> 20 | AI35: =IF(ISNUMBER(G$45),G35,"") -> 20.79 | AJ35: =IF(ISNUMBER(H$45),H35,"") -> 19.8 | AK35: =IF(ISNUMBER(I$45),I35,"") -> 20.59 | AL35: =IF(ISNUMBER(J$45),J35,"") -> 21.38 | AM35: =IF(ISNUMBER(K$45),K35,"") -> 20.2 | AN35: =IF(ISNUMBER(L$45),L35,"") -> 20.99 | ... AP35: =IF(ISNUMBER(N$45),N35,"") -> 20.39 | AQ35: =IF(C35="Ручная",O35,0) -> 19.8
A36: — | B36: Перейти с партией к SOLIA | C36: Переход | D36: Оператор у SOLIA | E36: 6 | F36: 6.24 | G36: 6.48 | H36: 6.12 | I36: 6.36 | J36: 6.6 | K36: 6.18 | L36: 6.42 | M36: 6.06 | N36: 6.3 | O36: =IF(COUNT(AG36:AP36)>0,MIN(AG36:AP36),"") -> 6 | P36: =IF(COUNT(AG36:AP36)>0,MAX(AG36:AP36),"") -> 6.6 | Q36: =IF(ISNUMBER(O36),P36-O36,"") -> 0.6 | R36: =IF(ISNUMBER(O36),IF(C36="Ручная",IF($S$45>0,$R$45*Q36/$S$45,IF($W$45=4,$R$45,0)),0),"") -> 0 | S36: =IF(ISNUMBER(O36),O36+R36,"") -> 6 | T36: =IF(ISNUMBER(S36),P36-S36,"") -> 0.6 | U36: =IF(COUNT(AG36:AP36)>0,AVERAGE(AG36:AP36),"") -> 6.276 | AG36: =IF(ISNUMBER(E$45),E36,"") -> 6 | AH36: =IF(ISNUMBER(F$45),F36,"") -> 6.24 | AI36: =IF(ISNUMBER(G$45),G36,"") -> 6.48 | AJ36: =IF(ISNUMBER(H$45),H36,"") -> 6.12 | AK36: =IF(ISNUMBER(I$45),I36,"") -> 6.36 | AL36: =IF(ISNUMBER(J$45),J36,"") -> 6.6 | AM36: =IF(ISNUMBER(K$45),K36,"") -> 6.18 | AN36: =IF(ISNUMBER(L$45),L36,"") -> 6.42 | ... AP36: =IF(ISNUMBER(N$45),N36,"") -> 6.3 | AQ36: =IF(C36="Ручная",O36,0) -> 0
A37: 5 | B37: Загрузить, выбрать программу, запустить | C37: Ручная | D37: Программа запущена | E37: 30.34 | F37: 31.54 | G37: 32.73 | H37: 30.64 | I37: 31.83 | J37: 30.05 | K37: 31.24 | L37: 29.75 | M37: 30.94 | N37: 32.13 | O37: =IF(COUNT(AG37:AP37)>0,MIN(AG37:AP37),"") -> 29.75 | P37: =IF(COUNT(AG37:AP37)>0,MAX(AG37:AP37),"") -> 32.73 | Q37: =IF(ISNUMBER(O37),P37-O37,"") -> 2.98 | R37: =IF(ISNUMBER(O37),IF(C37="Ручная",IF($S$45>0,$R$45*Q37/$S$45,IF($W$45=5,$R$45,0)),0),"") -> 0.92281359 | S37: =IF(ISNUMBER(O37),O37+R37,"") -> 30.672814 | T37: =IF(ISNUMBER(S37),P37-S37,"") -> 2.0571864 | U37: =IF(COUNT(AG37:AP37)>0,AVERAGE(AG37:AP37),"") -> 31.119 | AG37: =IF(ISNUMBER(E$45),E37,"") -> 30.34 | AH37: =IF(ISNUMBER(F$45),F37,"") -> 31.54 | AI37: =IF(ISNUMBER(G$45),G37,"") -> 32.73 | AJ37: =IF(ISNUMBER(H$45),H37,"") -> 30.64 | AK37: =IF(ISNUMBER(I$45),I37,"") -> 31.83 | AL37: =IF(ISNUMBER(J$45),J37,"") -> 30.05 | AM37: =IF(ISNUMBER(K$45),K37,"") -> 31.24 | AN37: =IF(ISNUMBER(L$45),L37,"") -> 29.75 | ... AP37: =IF(ISNUMBER(N$45),N37,"") -> 32.13 | AQ37: =IF(C37="Ручная",O37,0) -> 29.75
A38: — | B38: Автоматическая программа / ожидание | C38: Авто/ожидание | D38: Полный цикл программы завершён | E38: ='Ассортимент'!R9 -> 450 | F38: ='Ассортимент'!R9 -> 450 | G38: ='Ассортимент'!R9 -> 450 | H38: ='Ассортимент'!R9 -> 450 | I38: ='Ассортимент'!R9 -> 450 | J38: ='Ассортимент'!R9 -> 450 | K38: ='Ассортимент'!R9 -> 450 | L38: ='Ассортимент'!R9 -> 450 | M38: ='Ассортимент'!R9 -> 450 | N38: ='Ассортимент'!R9 -> 450 | O38: =IF(COUNT(AG38:AP38)>0,MIN(AG38:AP38),"") -> 450 | P38: =IF(COUNT(AG38:AP38)>0,MAX(AG38:AP38),"") -> 450 | Q38: =IF(ISNUMBER(O38),P38-O38,"") -> 0 | R38: =IF(ISNUMBER(O38),IF(C38="Ручная",IF($S$45>0,$R$45*Q38/$S$45,IF($W$45=6,$R$45,0)),0),"") -> 0 | S38: =IF(ISNUMBER(O38),O38+R38,"") -> 450 | T38: =IF(ISNUMBER(S38),P38-S38,"") -> 0 | U38: =IF(COUNT(AG38:AP38)>0,AVERAGE(AG38:AP38),"") -> 450 | AG38: =IF(ISNUMBER(E$45),E38,"") -> 450 | AH38: =IF(ISNUMBER(F$45),F38,"") -> 450 | AI38: =IF(ISNUMBER(G$45),G38,"") -> 450 | AJ38: =IF(ISNUMBER(H$45),H38,"") -> 450 | AK38: =IF(ISNUMBER(I$45),I38,"") -> 450 | AL38: =IF(ISNUMBER(J$45),J38,"") -> 450 | AM38: =IF(ISNUMBER(K$45),K38,"") -> 450 | AN38: =IF(ISNUMBER(L$45),L38,"") -> 450 | ... AP38: =IF(ISNUMBER(N$45),N38,"") -> 450 | AQ38: =IF(C38="Ручная",O38,0) -> 0
A39: 7 | B39: Выгрузить в чистую маркированную тару | C39: Ручная | D39: Выгрузка завершена | E39: 28.35 | F39: 27 | G39: 28.08 | H39: 29.16 | I39: 27.54 | J39: 28.62 | K39: 29.7 | L39: 27.81 | M39: 28.89 | N39: 27.27 | O39: =IF(COUNT(AG39:AP39)>0,MIN(AG39:AP39),"") -> 27 | P39: =IF(COUNT(AG39:AP39)>0,MAX(AG39:AP39),"") -> 29.7 | Q39: =IF(ISNUMBER(O39),P39-O39,"") -> 2.7 | R39: =IF(ISNUMBER(O39),IF(C39="Ручная",IF($S$45>0,$R$45*Q39/$S$45,IF($W$45=7,$R$45,0)),0),"") -> 0.83610627 | S39: =IF(ISNUMBER(O39),O39+R39,"") -> 27.836106 | T39: =IF(ISNUMBER(S39),P39-S39,"") -> 1.8638937 | U39: =IF(COUNT(AG39:AP39)>0,AVERAGE(AG39:AP39),"") -> 28.242 | AG39: =IF(ISNUMBER(E$45),E39,"") -> 28.35 | AH39: =IF(ISNUMBER(F$45),F39,"") -> 27 | AI39: =IF(ISNUMBER(G$45),G39,"") -> 28.08 | AJ39: =IF(ISNUMBER(H$45),H39,"") -> 29.16 | AK39: =IF(ISNUMBER(I$45),I39,"") -> 27.54 | AL39: =IF(ISNUMBER(J$45),J39,"") -> 28.62 | AM39: =IF(ISNUMBER(K$45),K39,"") -> 29.7 | AN39: =IF(ISNUMBER(L$45),L39,"") -> 27.81 | ... AP39: =IF(ISNUMBER(N$45),N39,"") -> 27.27 | AQ39: =IF(C39="Ручная",O39,0) -> 27
A40: 8 | B40: Проверить качество и маркировку | C40: Ручная | D40: Результат проверки подтверждён | E40: 19.44 | F40: 18.36 | G40: 19.08 | H40: 19.8 | I40: 18.54 | J40: 19.26 | K40: 18.18 | L40: 18.9 | M40: 18 | N40: 18.72 | O40: =IF(COUNT(AG40:AP40)>0,MIN(AG40:AP40),"") -> 18 | P40: =IF(COUNT(AG40:AP40)>0,MAX(AG40:AP40),"") -> 19.8 | Q40: =IF(ISNUMBER(O40),P40-O40,"") -> 1.8 | R40: =IF(ISNUMBER(O40),IF(C40="Ручная",IF($S$45>0,$R$45*Q40/$S$45,IF($W$45=8,$R$45,0)),0),"") -> 0.55740418 | S40: =IF(ISNUMBER(O40),O40+R40,"") -> 18.557404 | T40: =IF(ISNUMBER(S40),P40-S40,"") -> 1.2425958 | U40: =IF(COUNT(AG40:AP40)>0,AVERAGE(AG40:AP40),"") -> 18.828 | AG40: =IF(ISNUMBER(E$45),E40,"") -> 19.44 | AH40: =IF(ISNUMBER(F$45),F40,"") -> 18.36 | AI40: =IF(ISNUMBER(G$45),G40,"") -> 19.08 | AJ40: =IF(ISNUMBER(H$45),H40,"") -> 19.8 | AK40: =IF(ISNUMBER(I$45),I40,"") -> 18.54 | AL40: =IF(ISNUMBER(J$45),J40,"") -> 19.26 | AM40: =IF(ISNUMBER(K$45),K40,"") -> 18.18 | AN40: =IF(ISNUMBER(L$45),L40,"") -> 18.9 | ... AP40: =IF(ISNUMBER(N$45),N40,"") -> 18.72 | AQ40: =IF(C40="Ручная",O40,0) -> 18
A41: — | B41: Передать в зону чистой продукции | C41: Переход | D41: Партия передана | E41: 5.5 | F41: 5.15 | G41: 5.35 | H41: 5.05 | I41: 5.25 | J41: 5 | K41: 5.2 | L41: 5.4 | M41: 5.1 | N41: 5.3 | O41: =IF(COUNT(AG41:AP41)>0,MIN(AG41:AP41),"") -> 5 | P41: =IF(COUNT(AG41:AP41)>0,MAX(AG41:AP41),"") -> 5.5 | Q41: =IF(ISNUMBER(O41),P41-O41,"") -> 0.5 | R41: =IF(ISNUMBER(O41),IF(C41="Ручная",IF($S$45>0,$R$45*Q41/$S$45,IF($W$45=9,$R$45,0)),0),"") -> 0 | S41: =IF(ISNUMBER(O41),O41+R41,"") -> 5 | T41: =IF(ISNUMBER(S41),P41-S41,"") -> 0.5 | U41: =IF(COUNT(AG41:AP41)>0,AVERAGE(AG41:AP41),"") -> 5.23 | AG41: =IF(ISNUMBER(E$45),E41,"") -> 5.5 | AH41: =IF(ISNUMBER(F$45),F41,"") -> 5.15 | AI41: =IF(ISNUMBER(G$45),G41,"") -> 5.35 | AJ41: =IF(ISNUMBER(H$45),H41,"") -> 5.05 | AK41: =IF(ISNUMBER(I$45),I41,"") -> 5.25 | AL41: =IF(ISNUMBER(J$45),J41,"") -> 5 | AM41: =IF(ISNUMBER(K$45),K41,"") -> 5.2 | AN41: =IF(ISNUMBER(L$45),L41,"") -> 5.4 | ... AP41: =IF(ISNUMBER(N$45),N41,"") -> 5.3 | AQ41: =IF(C41="Ручная",O41,0) -> 0
A42: — | B42: Вернуться к началу цикла | C42: Переход | D42: Возврат на исходную позицию | E42: 5.05 | F42: 5.25 | G42: 5 | H42: 5.2 | I42: 5.4 | J42: 5.1 | K42: 5.3 | L42: 5.5 | M42: 5.15 | N42: 5.35 | O42: =IF(COUNT(AG42:AP42)>0,MIN(AG42:AP42),"") -> 5 | P42: =IF(COUNT(AG42:AP42)>0,MAX(AG42:AP42),"") -> 5.5 | Q42: =IF(ISNUMBER(O42),P42-O42,"") -> 0.5 | R42: =IF(ISNUMBER(O42),IF(C42="Ручная",IF($S$45>0,$R$45*Q42/$S$45,IF($W$45=10,$R$45,0)),0),"") -> 0 | S42: =IF(ISNUMBER(O42),O42+R42,"") -> 5 | T42: =IF(ISNUMBER(S42),P42-S42,"") -> 0.5 | U42: =IF(COUNT(AG42:AP42)>0,AVERAGE(AG42:AP42),"") -> 5.23 | AG42: =IF(ISNUMBER(E$45),E42,"") -> 5.05 | AH42: =IF(ISNUMBER(F$45),F42,"") -> 5.25 | AI42: =IF(ISNUMBER(G$45),G42,"") -> 5 | AJ42: =IF(ISNUMBER(H$45),H42,"") -> 5.2 | AK42: =IF(ISNUMBER(I$45),I42,"") -> 5.4 | AL42: =IF(ISNUMBER(J$45),J42,"") -> 5.1 | AM42: =IF(ISNUMBER(K$45),K42,"") -> 5.3 | AN42: =IF(ISNUMBER(L$45),L42,"") -> 5.5 | ... AP42: =IF(ISNUMBER(N$45),N42,"") -> 5.35 | AQ42: =IF(C42="Ручная",O42,0) -> 0
A43: — | B43: Внеплановый поиск тары / ожидание | C43: Потери | D43: Причина задержки устранена | E43: 0 | F43: 0 | G43: 0 | H43: 0 | I43: 0 | J43: 0 | K43: 0 | L43: 0 | M43: 0 | N43: 0 | O43: =IF(COUNT(AG43:AP43)>0,MIN(AG43:AP43),"") -> 0 | P43: =IF(COUNT(AG43:AP43)>0,MAX(AG43:AP43),"") -> 0 | Q43: =IF(ISNUMBER(O43),P43-O43,"") -> 0 | R43: =IF(ISNUMBER(O43),IF(C43="Ручная",IF($S$45>0,$R$45*Q43/$S$45,IF($W$45=11,$R$45,0)),0),"") -> 0 | S43: =IF(ISNUMBER(O43),O43+R43,"") -> 0 | T43: =IF(ISNUMBER(S43),P43-S43,"") -> 0 | U43: =IF(COUNT(AG43:AP43)>0,AVERAGE(AG43:AP43),"") -> 0 | AG43: =IF(ISNUMBER(E$45),E43,"") -> 0 | AH43: =IF(ISNUMBER(F$45),F43,"") -> 0 | AI43: =IF(ISNUMBER(G$45),G43,"") -> 0 | AJ43: =IF(ISNUMBER(H$45),H43,"") -> 0 | AK43: =IF(ISNUMBER(I$45),I43,"") -> 0 | AL43: =IF(ISNUMBER(J$45),J43,"") -> 0 | AM43: =IF(ISNUMBER(K$45),K43,"") -> 0 | AN43: =IF(ISNUMBER(L$45),L43,"") -> 0 | ... AP43: =IF(ISNUMBER(N$45),N43,"") -> 0 | AQ43: =IF(C43="Ручная",O43,0) -> 0
B44: ИТОГИ: все элементы цикла | E44: =IF(COUNT(E33:E43)=11,SUM(E33:E43),"") -> 708.47 | F44: =IF(COUNT(F33:F43)=11,SUM(F33:F43),"") -> 711.54 | G44: =IF(COUNT(G33:G43)=11,SUM(G33:G43),"") -> 706.31 | H44: =IF(COUNT(H33:H43)=11,SUM(H33:H43),"") -> 709.97 | I44: =IF(COUNT(I33:I43)=11,SUM(I33:I43),"") -> 704.11 | J44: =IF(COUNT(J33:J43)=11,SUM(J33:J43),"") -> 707.26 | K44: =IF(COUNT(K33:K43)=11,SUM(K33:K43),"") -> 702.75 | L44: =IF(COUNT(L33:L43)=11,SUM(L33:L43),"") -> 704.42 | ... U44: =IF(COUNT(U33:U43)=11,SUM(U33:U43),"") -> 706.846
B45: ТОЛЬКО полные учтённые циклы | E45: =IF(AND(E31=1,COUNT(E33:E43)=11,MIN(E33:E43)>=0),E44,"") -> 708.47 | F45: =IF(AND(F31=1,COUNT(F33:F43)=11,MIN(F33:F43)>=0),F44,"") -> 711.54 | G45: =IF(AND(G31=1,COUNT(G33:G43)=11,MIN(G33:G43)>=0),G44,"") -> 706.31 | H45: =IF(AND(H31=1,COUNT(H33:H43)=11,MIN(H33:H43)>=0),H44,"") -> 709.97 | I45: =IF(AND(I31=1,COUNT(I33:I43)=11,MIN(I33:I43)>=0),I44,"") -> 704.11 | J45: =IF(AND(J31=1,COUNT(J33:J43)=11,MIN(J33:J43)>=0),J44,"") -> 707.26 | K45: =IF(AND(K31=1,COUNT(K33:K43)=11,MIN(K33:K43)>=0),K44,"") -> 702.75 | L45: =IF(AND(L31=1,COUNT(L33:L43)=11,MIN(L33:L43)>=0),L44,"") -> 704.42 | ... N45: =IF(AND(N31=1,COUNT(N33:N43)=11,MIN(N33:N43)>=0),N44,"") -> 702.66 | O45: =IF(COUNT(E45:N45)>0,MIN(E45:N45),"") -> 702.66 | P45: =IF(COUNT(E45:N45)>0,MAX(E45:N45),"") -> 711.54 | Q45: =IF(ISNUMBER(O45),P45-O45,"") -> 8.88 | R45: =IF(ISNUMBER(O45),MAX(0,O45-O44),"") -> 7.11 | S45: =SUMIF(C33:C43,"Ручная",Q33:Q43) -> 22.96 | T45: =COUNT(E45:N45) -> 10 | U45: =IF(COUNT(E45:N45)>0,AVERAGE(E45:N45),"") -> 706.846 | V45: =IF(ISNUMBER(O45),S44-O45,"") -> 1.1368684e-13 | W45: =MATCH(MAX(AQ33:AQ43),AQ33:AQ43,0) -> 2 | X45: =IF(T45=0,"НЕТ ЗАМЕРОВ",IF(T45<10,"МЕНЕЕ 10 ЦИКЛОВ",IF(ABS(V45)<0.000001,"ОК","ОШИБКА РЕГУЛИРОВКИ"))) -> ОК
A46: В строке учтённых циклов: O = T min; P = T max; Q = размах цикла; R = T min − сумма t min; S = сумма размахов ручных элементов; T = число циклов; U = среднее; V = сумма t отрег − T min (должно быть 0).
A49: 03. Петрушка · ЦЕЛЬ · 10 демонстрационных циклов, заменить реальными
A50: ="Масса замера, кг: "&'Ассортимент'!J10&". Все замеры одной партии/исполнителя/условий. Основание: "&'Ввод'!B15 -> Масса замера, кг: 1.5. Все замеры одной партии/исполнителя/условий. Основание: ДЕМО: прогноз; улучшения не внедрены
A51: № | B51: Рабочий элемент | C51: Тип | D51: Точка отсчёта | E51: 1 | F51: 2 | G51: 3 | H51: 4 | I51: 5 | J51: 6 | K51: 7 | L51: 8 | M51: 9 | N51: 10 | O51: t min | P51: t max | Q51: Размах | R51: Рег. с | S51: t отрег. | T51: Колебания | U51: Среднее | V51: Контроль | W51: Служебно | X51: Статус
B52: Учитывать цикл: 1 / 0 | E52: 1 | F52: 1 | G52: 1 | H52: 1 | I52: 1 | J52: 1 | K52: 1 | L52: 1 | M52: 1 | N52: 1
B53: Причина исключения / условия | E53: ДЕМО | F53: ДЕМО | G53: ДЕМО | H53: ДЕМО | I53: ДЕМО | J53: ДЕМО | K53: ДЕМО | L53: ДЕМО | M53: ДЕМО | N53: ДЕМО
A54: 1 | B54: Осмотреть упаковку и сырьё | C54: Ручная | D54: Осмотр партии завершён | E54: 27 | F54: 25.5 | G54: 26.5 | H54: 27.5 | I54: 25.75 | J54: 26.75 | K54: 25.25 | L54: 26.25 | M54: 25 | N54: 26 | O54: =IF(COUNT(AG54:AP54)>0,MIN(AG54:AP54),"") -> 25 | P54: =IF(COUNT(AG54:AP54)>0,MAX(AG54:AP54),"") -> 27.5 | Q54: =IF(ISNUMBER(O54),P54-O54,"") -> 2.5 | R54: =IF(ISNUMBER(O54),IF(C54="Ручная",IF($S$66>0,$R$66*Q54/$S$66,IF($W$66=1,$R$66,0)),0),"") -> 0.75125209 | S54: =IF(ISNUMBER(O54),O54+R54,"") -> 25.751252 | T54: =IF(ISNUMBER(S54),P54-S54,"") -> 1.7487479 | U54: =IF(COUNT(AG54:AP54)>0,AVERAGE(AG54:AP54),"") -> 26.15 | AG54: =IF(ISNUMBER(E$66),E54,"") -> 27 | AH54: =IF(ISNUMBER(F$66),F54,"") -> 25.5 | AI54: =IF(ISNUMBER(G$66),G54,"") -> 26.5 | AJ54: =IF(ISNUMBER(H$66),H54,"") -> 27.5 | AK54: =IF(ISNUMBER(I$66),I54,"") -> 25.75 | AL54: =IF(ISNUMBER(J$66),J54,"") -> 26.75 | AM54: =IF(ISNUMBER(K$66),K54,"") -> 25.25 | AN54: =IF(ISNUMBER(L$66),L54,"") -> 26.25 | ... AP54: =IF(ISNUMBER(N$66),N54,"") -> 26 | AQ54: =IF(C54="Ручная",O54,0) -> 25
A55: 2 | B55: Отсортировать / подготовить сырьё | C55: Ручная | D55: Подготовленное сырьё отложено | E55: 132 | F55: 123.6 | G55: 128.4 | H55: 121.2 | I55: 126 | J55: 120 | K55: 124.8 | L55: 129.6 | M55: 122.4 | N55: 127.2 | O55: =IF(COUNT(AG55:AP55)>0,MIN(AG55:AP55),"") -> 120 | P55: =IF(COUNT(AG55:AP55)>0,MAX(AG55:AP55),"") -> 132 | Q55: =IF(ISNUMBER(O55),P55-O55,"") -> 12 | R55: =IF(ISNUMBER(O55),IF(C55="Ручная",IF($S$66>0,$R$66*Q55/$S$66,IF($W$66=2,$R$66,0)),0),"") -> 3.60601 | S55: =IF(ISNUMBER(O55),O55+R55,"") -> 123.60601 | T55: =IF(ISNUMBER(S55),P55-S55,"") -> 8.39399 | U55: =IF(COUNT(AG55:AP55)>0,AVERAGE(AG55:AP55),"") -> 125.52 | AG55: =IF(ISNUMBER(E$66),E55,"") -> 132 | AH55: =IF(ISNUMBER(F$66),F55,"") -> 123.6 | AI55: =IF(ISNUMBER(G$66),G55,"") -> 128.4 | AJ55: =IF(ISNUMBER(H$66),H55,"") -> 121.2 | AK55: =IF(ISNUMBER(I$66),I55,"") -> 126 | AL55: =IF(ISNUMBER(J$66),J55,"") -> 120 | AM55: =IF(ISNUMBER(K$66),K55,"") -> 124.8 | AN55: =IF(ISNUMBER(L$66),L55,"") -> 129.6 | ... AP55: =IF(ISNUMBER(N$66),N55,"") -> 127.2 | AQ55: =IF(C55="Ручная",O55,0) -> 120
A56: 3 | B56: Отвесить допустимую партию | C56: Ручная | D56: Масса партии проверена | E56: 20 | F56: 20.79 | G56: 19.8 | H56: 20.59 | I56: 21.38 | J56: 20.2 | K56: 20.99 | L56: 21.78 | M56: 20.39 | N56: 21.19 | O56: =IF(COUNT(AG56:AP56)>0,MIN(AG56:AP56),"") -> 19.8 | P56: =IF(COUNT(AG56:AP56)>0,MAX(AG56:AP56),"") -> 21.78 | Q56: =IF(ISNUMBER(O56),P56-O56,"") -> 1.98 | R56: =IF(ISNUMBER(O56),IF(C56="Ручная",IF($S$66>0,$R$66*Q56/$S$66,IF($W$66=3,$R$66,0)),0),"") -> 0.59499165 | S56: =IF(ISNUMBER(O56),O56+R56,"") -> 20.394992 | T56: =IF(ISNUMBER(S56),P56-S56,"") -> 1.3850083 | U56: =IF(COUNT(AG56:AP56)>0,AVERAGE(AG56:AP56),"") -> 20.711 | AG56: =IF(ISNUMBER(E$66),E56,"") -> 20 | AH56: =IF(ISNUMBER(F$66),F56,"") -> 20.79 | AI56: =IF(ISNUMBER(G$66),G56,"") -> 19.8 | AJ56: =IF(ISNUMBER(H$66),H56,"") -> 20.59 | AK56: =IF(ISNUMBER(I$66),I56,"") -> 21.38 | AL56: =IF(ISNUMBER(J$66),J56,"") -> 20.2 | AM56: =IF(ISNUMBER(K$66),K56,"") -> 20.99 | AN56: =IF(ISNUMBER(L$66),L56,"") -> 21.78 | ... AP56: =IF(ISNUMBER(N$66),N56,"") -> 21.19 | AQ56: =IF(C56="Ручная",O56,0) -> 19.8
A57: — | B57: Перейти с партией к SOLIA | C57: Переход | D57: Оператор у SOLIA | E57: 6.24 | F57: 6.48 | G57: 6.12 | H57: 6.36 | I57: 6.6 | J57: 6.18 | K57: 6.42 | L57: 6.06 | M57: 6.3 | N57: 6 | O57: =IF(COUNT(AG57:AP57)>0,MIN(AG57:AP57),"") -> 6 | P57: =IF(COUNT(AG57:AP57)>0,MAX(AG57:AP57),"") -> 6.6 | Q57: =IF(ISNUMBER(O57),P57-O57,"") -> 0.6 | R57: =IF(ISNUMBER(O57),IF(C57="Ручная",IF($S$66>0,$R$66*Q57/$S$66,IF($W$66=4,$R$66,0)),0),"") -> 0 | S57: =IF(ISNUMBER(O57),O57+R57,"") -> 6 | T57: =IF(ISNUMBER(S57),P57-S57,"") -> 0.6 | U57: =IF(COUNT(AG57:AP57)>0,AVERAGE(AG57:AP57),"") -> 6.276 | AG57: =IF(ISNUMBER(E$66),E57,"") -> 6.24 | AH57: =IF(ISNUMBER(F$66),F57,"") -> 6.48 | AI57: =IF(ISNUMBER(G$66),G57,"") -> 6.12 | AJ57: =IF(ISNUMBER(H$66),H57,"") -> 6.36 | AK57: =IF(ISNUMBER(I$66),I57,"") -> 6.6 | AL57: =IF(ISNUMBER(J$66),J57,"") -> 6.18 | AM57: =IF(ISNUMBER(K$66),K57,"") -> 6.42 | AN57: =IF(ISNUMBER(L$66),L57,"") -> 6.06 | ... AP57: =IF(ISNUMBER(N$66),N57,"") -> 6 | AQ57: =IF(C57="Ручная",O57,0) -> 0
A58: 5 | B58: Загрузить, выбрать программу, запустить | C58: Ручная | D58: Программа запущена | E58: 31.54 | F58: 32.73 | G58: 30.64 | H58: 31.83 | I58: 30.05 | J58: 31.24 | K58: 29.75 | L58: 30.94 | M58: 32.13 | N58: 30.34 | O58: =IF(COUNT(AG58:AP58)>0,MIN(AG58:AP58),"") -> 29.75 | P58: =IF(COUNT(AG58:AP58)>0,MAX(AG58:AP58),"") -> 32.73 | Q58: =IF(ISNUMBER(O58),P58-O58,"") -> 2.98 | R58: =IF(ISNUMBER(O58),IF(C58="Ручная",IF($S$66>0,$R$66*Q58/$S$66,IF($W$66=5,$R$66,0)),0),"") -> 0.89549249 | S58: =IF(ISNUMBER(O58),O58+R58,"") -> 30.645492 | T58: =IF(ISNUMBER(S58),P58-S58,"") -> 2.0845075 | U58: =IF(COUNT(AG58:AP58)>0,AVERAGE(AG58:AP58),"") -> 31.119 | AG58: =IF(ISNUMBER(E$66),E58,"") -> 31.54 | AH58: =IF(ISNUMBER(F$66),F58,"") -> 32.73 | AI58: =IF(ISNUMBER(G$66),G58,"") -> 30.64 | AJ58: =IF(ISNUMBER(H$66),H58,"") -> 31.83 | AK58: =IF(ISNUMBER(I$66),I58,"") -> 30.05 | AL58: =IF(ISNUMBER(J$66),J58,"") -> 31.24 | AM58: =IF(ISNUMBER(K$66),K58,"") -> 29.75 | AN58: =IF(ISNUMBER(L$66),L58,"") -> 30.94 | ... AP58: =IF(ISNUMBER(N$66),N58,"") -> 30.34 | AQ58: =IF(C58="Ручная",O58,0) -> 29.75
A59: — | B59: Автоматическая программа / ожидание | C59: Авто/ожидание | D59: Полный цикл программы завершён | E59: ='Ассортимент'!R10 -> 450 | F59: ='Ассортимент'!R10 -> 450 | G59: ='Ассортимент'!R10 -> 450 | H59: ='Ассортимент'!R10 -> 450 | I59: ='Ассортимент'!R10 -> 450 | J59: ='Ассортимент'!R10 -> 450 | K59: ='Ассортимент'!R10 -> 450 | L59: ='Ассортимент'!R10 -> 450 | M59: ='Ассортимент'!R10 -> 450 | N59: ='Ассортимент'!R10 -> 450 | O59: =IF(COUNT(AG59:AP59)>0,MIN(AG59:AP59),"") -> 450 | P59: =IF(COUNT(AG59:AP59)>0,MAX(AG59:AP59),"") -> 450 | Q59: =IF(ISNUMBER(O59),P59-O59,"") -> 0 | R59: =IF(ISNUMBER(O59),IF(C59="Ручная",IF($S$66>0,$R$66*Q59/$S$66,IF($W$66=6,$R$66,0)),0),"") -> 0 | S59: =IF(ISNUMBER(O59),O59+R59,"") -> 450 | T59: =IF(ISNUMBER(S59),P59-S59,"") -> 0 | U59: =IF(COUNT(AG59:AP59)>0,AVERAGE(AG59:AP59),"") -> 450 | AG59: =IF(ISNUMBER(E$66),E59,"") -> 450 | AH59: =IF(ISNUMBER(F$66),F59,"") -> 450 | AI59: =IF(ISNUMBER(G$66),G59,"") -> 450 | AJ59: =IF(ISNUMBER(H$66),H59,"") -> 450 | AK59: =IF(ISNUMBER(I$66),I59,"") -> 450 | AL59: =IF(ISNUMBER(J$66),J59,"") -> 450 | AM59: =IF(ISNUMBER(K$66),K59,"") -> 450 | AN59: =IF(ISNUMBER(L$66),L59,"") -> 450 | ... AP59: =IF(ISNUMBER(N$66),N59,"") -> 450 | AQ59: =IF(C59="Ручная",O59,0) -> 0
A60: 7 | B60: Выгрузить в чистую маркированную тару | C60: Ручная | D60: Выгрузка завершена | E60: 27 | F60: 28.08 | G60: 29.16 | H60: 27.54 | I60: 28.62 | J60: 29.7 | K60: 27.81 | L60: 28.89 | M60: 27.27 | N60: 28.35 | O60: =IF(COUNT(AG60:AP60)>0,MIN(AG60:AP60),"") -> 27 | P60: =IF(COUNT(AG60:AP60)>0,MAX(AG60:AP60),"") -> 29.7 | Q60: =IF(ISNUMBER(O60),P60-O60,"") -> 2.7 | R60: =IF(ISNUMBER(O60),IF(C60="Ручная",IF($S$66>0,$R$66*Q60/$S$66,IF($W$66=7,$R$66,0)),0),"") -> 0.81135225 | S60: =IF(ISNUMBER(O60),O60+R60,"") -> 27.811352 | T60: =IF(ISNUMBER(S60),P60-S60,"") -> 1.8886477 | U60: =IF(COUNT(AG60:AP60)>0,AVERAGE(AG60:AP60),"") -> 28.242 | AG60: =IF(ISNUMBER(E$66),E60,"") -> 27 | AH60: =IF(ISNUMBER(F$66),F60,"") -> 28.08 | AI60: =IF(ISNUMBER(G$66),G60,"") -> 29.16 | AJ60: =IF(ISNUMBER(H$66),H60,"") -> 27.54 | AK60: =IF(ISNUMBER(I$66),I60,"") -> 28.62 | AL60: =IF(ISNUMBER(J$66),J60,"") -> 29.7 | AM60: =IF(ISNUMBER(K$66),K60,"") -> 27.81 | AN60: =IF(ISNUMBER(L$66),L60,"") -> 28.89 | ... AP60: =IF(ISNUMBER(N$66),N60,"") -> 28.35 | AQ60: =IF(C60="Ручная",O60,0) -> 27
A61: 8 | B61: Проверить качество и маркировку | C61: Ручная | D61: Результат проверки подтверждён | E61: 18.36 | F61: 19.08 | G61: 19.8 | H61: 18.54 | I61: 19.26 | J61: 18.18 | K61: 18.9 | L61: 18 | M61: 18.72 | N61: 19.44 | O61: =IF(COUNT(AG61:AP61)>0,MIN(AG61:AP61),"") -> 18 | P61: =IF(COUNT(AG61:AP61)>0,MAX(AG61:AP61),"") -> 19.8 | Q61: =IF(ISNUMBER(O61),P61-O61,"") -> 1.8 | R61: =IF(ISNUMBER(O61),IF(C61="Ручная",IF($S$66>0,$R$66*Q61/$S$66,IF($W$66=8,$R$66,0)),0),"") -> 0.5409015 | S61: =IF(ISNUMBER(O61),O61+R61,"") -> 18.540902 | T61: =IF(ISNUMBER(S61),P61-S61,"") -> 1.2590985 | U61: =IF(COUNT(AG61:AP61)>0,AVERAGE(AG61:AP61),"") -> 18.828 | AG61: =IF(ISNUMBER(E$66),E61,"") -> 18.36 | AH61: =IF(ISNUMBER(F$66),F61,"") -> 19.08 | AI61: =IF(ISNUMBER(G$66),G61,"") -> 19.8 | AJ61: =IF(ISNUMBER(H$66),H61,"") -> 18.54 | AK61: =IF(ISNUMBER(I$66),I61,"") -> 19.26 | AL61: =IF(ISNUMBER(J$66),J61,"") -> 18.18 | AM61: =IF(ISNUMBER(K$66),K61,"") -> 18.9 | AN61: =IF(ISNUMBER(L$66),L61,"") -> 18 | ... AP61: =IF(ISNUMBER(N$66),N61,"") -> 19.44 | AQ61: =IF(C61="Ручная",O61,0) -> 18
A62: — | B62: Передать в зону чистой продукции | C62: Переход | D62: Партия передана | E62: 5.15 | F62: 5.35 | G62: 5.05 | H62: 5.25 | I62: 5 | J62: 5.2 | K62: 5.4 | L62: 5.1 | M62: 5.3 | N62: 5.5 | O62: =IF(COUNT(AG62:AP62)>0,MIN(AG62:AP62),"") -> 5 | P62: =IF(COUNT(AG62:AP62)>0,MAX(AG62:AP62),"") -> 5.5 | Q62: =IF(ISNUMBER(O62),P62-O62,"") -> 0.5 | R62: =IF(ISNUMBER(O62),IF(C62="Ручная",IF($S$66>0,$R$66*Q62/$S$66,IF($W$66=9,$R$66,0)),0),"") -> 0 | S62: =IF(ISNUMBER(O62),O62+R62,"") -> 5 | T62: =IF(ISNUMBER(S62),P62-S62,"") -> 0.5 | U62: =IF(COUNT(AG62:AP62)>0,AVERAGE(AG62:AP62),"") -> 5.23 | AG62: =IF(ISNUMBER(E$66),E62,"") -> 5.15 | AH62: =IF(ISNUMBER(F$66),F62,"") -> 5.35 | AI62: =IF(ISNUMBER(G$66),G62,"") -> 5.05 | AJ62: =IF(ISNUMBER(H$66),H62,"") -> 5.25 | AK62: =IF(ISNUMBER(I$66),I62,"") -> 5 | AL62: =IF(ISNUMBER(J$66),J62,"") -> 5.2 | AM62: =IF(ISNUMBER(K$66),K62,"") -> 5.4 | AN62: =IF(ISNUMBER(L$66),L62,"") -> 5.1 | ... AP62: =IF(ISNUMBER(N$66),N62,"") -> 5.5 | AQ62: =IF(C62="Ручная",O62,0) -> 0
A63: — | B63: Вернуться к началу цикла | C63: Переход | D63: Возврат на исходную позицию | E63: 5.25 | F63: 5 | G63: 5.2 | H63: 5.4 | I63: 5.1 | J63: 5.3 | K63: 5.5 | L63: 5.15 | M63: 5.35 | N63: 5.05 | O63: =IF(COUNT(AG63:AP63)>0,MIN(AG63:AP63),"") -> 5 | P63: =IF(COUNT(AG63:AP63)>0,MAX(AG63:AP63),"") -> 5.5 | Q63: =IF(ISNUMBER(O63),P63-O63,"") -> 0.5 | R63: =IF(ISNUMBER(O63),IF(C63="Ручная",IF($S$66>0,$R$66*Q63/$S$66,IF($W$66=10,$R$66,0)),0),"") -> 0 | S63: =IF(ISNUMBER(O63),O63+R63,"") -> 5 | T63: =IF(ISNUMBER(S63),P63-S63,"") -> 0.5 | U63: =IF(COUNT(AG63:AP63)>0,AVERAGE(AG63:AP63),"") -> 5.23 | AG63: =IF(ISNUMBER(E$66),E63,"") -> 5.25 | AH63: =IF(ISNUMBER(F$66),F63,"") -> 5 | AI63: =IF(ISNUMBER(G$66),G63,"") -> 5.2 | AJ63: =IF(ISNUMBER(H$66),H63,"") -> 5.4 | AK63: =IF(ISNUMBER(I$66),I63,"") -> 5.1 | AL63: =IF(ISNUMBER(J$66),J63,"") -> 5.3 | AM63: =IF(ISNUMBER(K$66),K63,"") -> 5.5 | AN63: =IF(ISNUMBER(L$66),L63,"") -> 5.15 | ... AP63: =IF(ISNUMBER(N$66),N63,"") -> 5.05 | AQ63: =IF(C63="Ручная",O63,0) -> 0
A64: — | B64: Внеплановый поиск тары / ожидание | C64: Потери | D64: Причина задержки устранена | E64: 0 | F64: 0 | G64: 0 | H64: 0 | I64: 0 | J64: 0 | K64: 0 | L64: 0 | M64: 0 | N64: 0 | O64: =IF(COUNT(AG64:AP64)>0,MIN(AG64:AP64),"") -> 0 | P64: =IF(COUNT(AG64:AP64)>0,MAX(AG64:AP64),"") -> 0 | Q64: =IF(ISNUMBER(O64),P64-O64,"") -> 0 | R64: =IF(ISNUMBER(O64),IF(C64="Ручная",IF($S$66>0,$R$66*Q64/$S$66,IF($W$66=11,$R$66,0)),0),"") -> 0 | S64: =IF(ISNUMBER(O64),O64+R64,"") -> 0 | T64: =IF(ISNUMBER(S64),P64-S64,"") -> 0 | U64: =IF(COUNT(AG64:AP64)>0,AVERAGE(AG64:AP64),"") -> 0 | AG64: =IF(ISNUMBER(E$66),E64,"") -> 0 | AH64: =IF(ISNUMBER(F$66),F64,"") -> 0 | AI64: =IF(ISNUMBER(G$66),G64,"") -> 0 | AJ64: =IF(ISNUMBER(H$66),H64,"") -> 0 | AK64: =IF(ISNUMBER(I$66),I64,"") -> 0 | AL64: =IF(ISNUMBER(J$66),J64,"") -> 0 | AM64: =IF(ISNUMBER(K$66),K64,"") -> 0 | AN64: =IF(ISNUMBER(L$66),L64,"") -> 0 | ... AP64: =IF(ISNUMBER(N$66),N64,"") -> 0 | AQ64: =IF(C64="Ручная",O64,0) -> 0
B65: ИТОГИ: все элементы цикла | E65: =IF(COUNT(E54:E64)=11,SUM(E54:E64),"") -> 722.54 | F65: =IF(COUNT(F54:F64)=11,SUM(F54:F64),"") -> 716.61 | G65: =IF(COUNT(G54:G64)=11,SUM(G54:G64),"") -> 720.67 | H65: =IF(COUNT(H54:H64)=11,SUM(H54:H64),"") -> 714.21 | I65: =IF(COUNT(I54:I64)=11,SUM(I54:I64),"") -> 717.76 | J65: =IF(COUNT(J54:J64)=11,SUM(J54:J64),"") -> 712.75 | K65: =IF(COUNT(K54:K64)=11,SUM(K54:K64),"") -> 714.82 | L65: =IF(COUNT(L54:L64)=11,SUM(L54:L64),"") -> 721.77 | ... U65: =IF(COUNT(U54:U64)=11,SUM(U54:U64),"") -> 717.306
B66: ТОЛЬКО полные учтённые циклы | E66: =IF(AND(E52=1,COUNT(E54:E64)=11,MIN(E54:E64)>=0),E65,"") -> 722.54 | F66: =IF(AND(F52=1,COUNT(F54:F64)=11,MIN(F54:F64)>=0),F65,"") -> 716.61 | G66: =IF(AND(G52=1,COUNT(G54:G64)=11,MIN(G54:G64)>=0),G65,"") -> 720.67 | H66: =IF(AND(H52=1,COUNT(H54:H64)=11,MIN(H54:H64)>=0),H65,"") -> 714.21 | I66: =IF(AND(I52=1,COUNT(I54:I64)=11,MIN(I54:I64)>=0),I65,"") -> 717.76 | J66: =IF(AND(J52=1,COUNT(J54:J64)=11,MIN(J54:J64)>=0),J65,"") -> 712.75 | K66: =IF(AND(K52=1,COUNT(K54:K64)=11,MIN(K54:K64)>=0),K65,"") -> 714.82 | L66: =IF(AND(L52=1,COUNT(L54:L64)=11,MIN(L54:L64)>=0),L65,"") -> 721.77 | ... N66: =IF(AND(N52=1,COUNT(N54:N64)=11,MIN(N54:N64)>=0),N65,"") -> 719.07 | O66: =IF(COUNT(E66:N66)>0,MIN(E66:N66),"") -> 712.75 | P66: =IF(COUNT(E66:N66)>0,MAX(E66:N66),"") -> 722.54 | Q66: =IF(ISNUMBER(O66),P66-O66,"") -> 9.79 | R66: =IF(ISNUMBER(O66),MAX(0,O66-O65),"") -> 7.2 | S66: =SUMIF(C54:C64,"Ручная",Q54:Q64) -> 23.96 | T66: =COUNT(E66:N66) -> 10 | U66: =IF(COUNT(E66:N66)>0,AVERAGE(E66:N66),"") -> 717.306 | V66: =IF(ISNUMBER(O66),S65-O66,"") -> 0 | W66: =MATCH(MAX(AQ54:AQ64),AQ54:AQ64,0) -> 2 | X66: =IF(T66=0,"НЕТ ЗАМЕРОВ",IF(T66<10,"МЕНЕЕ 10 ЦИКЛОВ",IF(ABS(V66)<0.000001,"ОК","ОШИБКА РЕГУЛИРОВКИ"))) -> ОК
A67: В строке учтённых циклов: O = T min; P = T max; Q = размах цикла; R = T min − сумма t min; S = сумма размахов ручных элементов; T = число циклов; U = среднее; V = сумма t отрег − T min (должно быть 0).
A70: 04. Томат · ЦЕЛЬ · 10 демонстрационных циклов, заменить реальными
A71: ="Масса замера, кг: "&'Ассортимент'!J11&". Все замеры одной партии/исполнителя/условий. Основание: "&'Ввод'!B15 -> Масса замера, кг: 5. Все замеры одной партии/исполнителя/условий. Основание: ДЕМО: прогноз; улучшения не внедрены
A72: № | B72: Рабочий элемент | C72: Тип | D72: Точка отсчёта | E72: 1 | F72: 2 | G72: 3 | H72: 4 | I72: 5 | J72: 6 | K72: 7 | L72: 8 | M72: 9 | N72: 10 | O72: t min | P72: t max | Q72: Размах | R72: Рег. с | S72: t отрег. | T72: Колебания | U72: Среднее | V72: Контроль | W72: Служебно | X72: Статус
B73: Учитывать цикл: 1 / 0 | E73: 1 | F73: 1 | G73: 1 | H73: 1 | I73: 1 | J73: 1 | K73: 1 | L73: 1 | M73: 1 | N73: 1
B74: Причина исключения / условия | E74: ДЕМО | F74: ДЕМО | G74: ДЕМО | H74: ДЕМО | I74: ДЕМО | J74: ДЕМО | K74: ДЕМО | L74: ДЕМО | M74: ДЕМО | N74: ДЕМО
A75: 1 | B75: Осмотреть упаковку и сырьё | C75: Ручная | D75: Осмотр партии завершён | E75: 25.5 | F75: 26.5 | G75: 27.5 | H75: 25.75 | I75: 26.75 | J75: 25.25 | K75: 26.25 | L75: 25 | M75: 26 | N75: 27 | O75: =IF(COUNT(AG75:AP75)>0,MIN(AG75:AP75),"") -> 25 | P75: =IF(COUNT(AG75:AP75)>0,MAX(AG75:AP75),"") -> 27.5 | Q75: =IF(ISNUMBER(O75),P75-O75,"") -> 2.5 | R75: =IF(ISNUMBER(O75),IF(C75="Ручная",IF($S$87>0,$R$87*Q75/$S$87,IF($W$87=1,$R$87,0)),0),"") -> 0.90717982 | S75: =IF(ISNUMBER(O75),O75+R75,"") -> 25.90718 | T75: =IF(ISNUMBER(S75),P75-S75,"") -> 1.5928202 | U75: =IF(COUNT(AG75:AP75)>0,AVERAGE(AG75:AP75),"") -> 26.15 | AG75: =IF(ISNUMBER(E$87),E75,"") -> 25.5 | AH75: =IF(ISNUMBER(F$87),F75,"") -> 26.5 | AI75: =IF(ISNUMBER(G$87),G75,"") -> 27.5 | AJ75: =IF(ISNUMBER(H$87),H75,"") -> 25.75 | AK75: =IF(ISNUMBER(I$87),I75,"") -> 26.75 | AL75: =IF(ISNUMBER(J$87),J75,"") -> 25.25 | AM75: =IF(ISNUMBER(K$87),K75,"") -> 26.25 | AN75: =IF(ISNUMBER(L$87),L75,"") -> 25 | ... AP75: =IF(ISNUMBER(N$87),N75,"") -> 27 | AQ75: =IF(C75="Ручная",O75,0) -> 25
A76: 2 | B76: Отсортировать / подготовить сырьё | C76: Ручная | D76: Подготовленное сырьё отложено | E76: 36.05 | F76: 37.45 | G76: 35.35 | H76: 36.75 | I76: 35 | J76: 36.4 | K76: 37.8 | L76: 35.7 | M76: 37.1 | N76: 38.5 | O76: =IF(COUNT(AG76:AP76)>0,MIN(AG76:AP76),"") -> 35 | P76: =IF(COUNT(AG76:AP76)>0,MAX(AG76:AP76),"") -> 38.5 | Q76: =IF(ISNUMBER(O76),P76-O76,"") -> 3.5 | R76: =IF(ISNUMBER(O76),IF(C76="Ручная",IF($S$87>0,$R$87*Q76/$S$87,IF($W$87=2,$R$87,0)),0),"") -> 1.2700517 | S76: =IF(ISNUMBER(O76),O76+R76,"") -> 36.270052 | T76: =IF(ISNUMBER(S76),P76-S76,"") -> 2.2299483 | U76: =IF(COUNT(AG76:AP76)>0,AVERAGE(AG76:AP76),"") -> 36.61 | AG76: =IF(ISNUMBER(E$87),E76,"") -> 36.05 | AH76: =IF(ISNUMBER(F$87),F76,"") -> 37.45 | AI76: =IF(ISNUMBER(G$87),G76,"") -> 35.35 | AJ76: =IF(ISNUMBER(H$87),H76,"") -> 36.75 | AK76: =IF(ISNUMBER(I$87),I76,"") -> 35 | AL76: =IF(ISNUMBER(J$87),J76,"") -> 36.4 | AM76: =IF(ISNUMBER(K$87),K76,"") -> 37.8 | AN76: =IF(ISNUMBER(L$87),L76,"") -> 35.7 | ... AP76: =IF(ISNUMBER(N$87),N76,"") -> 38.5 | AQ76: =IF(C76="Ручная",O76,0) -> 35
A77: 3 | B77: Отвесить допустимую партию | C77: Ручная | D77: Масса партии проверена | E77: 20.79 | F77: 19.8 | G77: 20.59 | H77: 21.38 | I77: 20.2 | J77: 20.99 | K77: 21.78 | L77: 20.39 | M77: 21.19 | N77: 20 | O77: =IF(COUNT(AG77:AP77)>0,MIN(AG77:AP77),"") -> 19.8 | P77: =IF(COUNT(AG77:AP77)>0,MAX(AG77:AP77),"") -> 21.78 | Q77: =IF(ISNUMBER(O77),P77-O77,"") -> 1.98 | R77: =IF(ISNUMBER(O77),IF(C77="Ручная",IF($S$87>0,$R$87*Q77/$S$87,IF($W$87=3,$R$87,0)),0),"") -> 0.71848642 | S77: =IF(ISNUMBER(O77),O77+R77,"") -> 20.518486 | T77: =IF(ISNUMBER(S77),P77-S77,"") -> 1.2615136 | U77: =IF(COUNT(AG77:AP77)>0,AVERAGE(AG77:AP77),"") -> 20.711 | AG77: =IF(ISNUMBER(E$87),E77,"") -> 20.79 | AH77: =IF(ISNUMBER(F$87),F77,"") -> 19.8 | AI77: =IF(ISNUMBER(G$87),G77,"") -> 20.59 | AJ77: =IF(ISNUMBER(H$87),H77,"") -> 21.38 | AK77: =IF(ISNUMBER(I$87),I77,"") -> 20.2 | AL77: =IF(ISNUMBER(J$87),J77,"") -> 20.99 | AM77: =IF(ISNUMBER(K$87),K77,"") -> 21.78 | AN77: =IF(ISNUMBER(L$87),L77,"") -> 20.39 | ... AP77: =IF(ISNUMBER(N$87),N77,"") -> 20 | AQ77: =IF(C77="Ручная",O77,0) -> 19.8
A78: — | B78: Перейти с партией к SOLIA | C78: Переход | D78: Оператор у SOLIA | E78: 6.48 | F78: 6.12 | G78: 6.36 | H78: 6.6 | I78: 6.18 | J78: 6.42 | K78: 6.06 | L78: 6.3 | M78: 6 | N78: 6.24 | O78: =IF(COUNT(AG78:AP78)>0,MIN(AG78:AP78),"") -> 6 | P78: =IF(COUNT(AG78:AP78)>0,MAX(AG78:AP78),"") -> 6.6 | Q78: =IF(ISNUMBER(O78),P78-O78,"") -> 0.6 | R78: =IF(ISNUMBER(O78),IF(C78="Ручная",IF($S$87>0,$R$87*Q78/$S$87,IF($W$87=4,$R$87,0)),0),"") -> 0 | S78: =IF(ISNUMBER(O78),O78+R78,"") -> 6 | T78: =IF(ISNUMBER(S78),P78-S78,"") -> 0.6 | U78: =IF(COUNT(AG78:AP78)>0,AVERAGE(AG78:AP78),"") -> 6.276 | AG78: =IF(ISNUMBER(E$87),E78,"") -> 6.48 | AH78: =IF(ISNUMBER(F$87),F78,"") -> 6.12 | AI78: =IF(ISNUMBER(G$87),G78,"") -> 6.36 | AJ78: =IF(ISNUMBER(H$87),H78,"") -> 6.6 | AK78: =IF(ISNUMBER(I$87),I78,"") -> 6.18 | AL78: =IF(ISNUMBER(J$87),J78,"") -> 6.42 | AM78: =IF(ISNUMBER(K$87),K78,"") -> 6.06 | AN78: =IF(ISNUMBER(L$87),L78,"") -> 6.3 | ... AP78: =IF(ISNUMBER(N$87),N78,"") -> 6.24 | AQ78: =IF(C78="Ручная",O78,0) -> 0
A79: 5 | B79: Загрузить, выбрать программу, запустить | C79: Ручная | D79: Программа запущена | E79: 32.73 | F79: 30.64 | G79: 31.83 | H79: 30.05 | I79: 31.24 | J79: 29.75 | K79: 30.94 | L79: 32.13 | M79: 30.34 | N79: 31.54 | O79: =IF(COUNT(AG79:AP79)>0,MIN(AG79:AP79),"") -> 29.75 | P79: =IF(COUNT(AG79:AP79)>0,MAX(AG79:AP79),"") -> 32.73 | Q79: =IF(ISNUMBER(O79),P79-O79,"") -> 2.98 | R79: =IF(ISNUMBER(O79),IF(C79="Ручная",IF($S$87>0,$R$87*Q79/$S$87,IF($W$87=5,$R$87,0)),0),"") -> 1.0813583 | S79: =IF(ISNUMBER(O79),O79+R79,"") -> 30.831358 | T79: =IF(ISNUMBER(S79),P79-S79,"") -> 1.8986417 | U79: =IF(COUNT(AG79:AP79)>0,AVERAGE(AG79:AP79),"") -> 31.119 | AG79: =IF(ISNUMBER(E$87),E79,"") -> 32.73 | AH79: =IF(ISNUMBER(F$87),F79,"") -> 30.64 | AI79: =IF(ISNUMBER(G$87),G79,"") -> 31.83 | AJ79: =IF(ISNUMBER(H$87),H79,"") -> 30.05 | AK79: =IF(ISNUMBER(I$87),I79,"") -> 31.24 | AL79: =IF(ISNUMBER(J$87),J79,"") -> 29.75 | AM79: =IF(ISNUMBER(K$87),K79,"") -> 30.94 | AN79: =IF(ISNUMBER(L$87),L79,"") -> 32.13 | ... AP79: =IF(ISNUMBER(N$87),N79,"") -> 31.54 | AQ79: =IF(C79="Ручная",O79,0) -> 29.75
A80: — | B80: Автоматическая программа / ожидание | C80: Авто/ожидание | D80: Полный цикл программы завершён | E80: ='Ассортимент'!R11 -> 180 | F80: ='Ассортимент'!R11 -> 180 | G80: ='Ассортимент'!R11 -> 180 | H80: ='Ассортимент'!R11 -> 180 | I80: ='Ассортимент'!R11 -> 180 | J80: ='Ассортимент'!R11 -> 180 | K80: ='Ассортимент'!R11 -> 180 | L80: ='Ассортимент'!R11 -> 180 | M80: ='Ассортимент'!R11 -> 180 | N80: ='Ассортимент'!R11 -> 180 | O80: =IF(COUNT(AG80:AP80)>0,MIN(AG80:AP80),"") -> 180 | P80: =IF(COUNT(AG80:AP80)>0,MAX(AG80:AP80),"") -> 180 | Q80: =IF(ISNUMBER(O80),P80-O80,"") -> 0 | R80: =IF(ISNUMBER(O80),IF(C80="Ручная",IF($S$87>0,$R$87*Q80/$S$87,IF($W$87=6,$R$87,0)),0),"") -> 0 | S80: =IF(ISNUMBER(O80),O80+R80,"") -> 180 | T80: =IF(ISNUMBER(S80),P80-S80,"") -> 0 | U80: =IF(COUNT(AG80:AP80)>0,AVERAGE(AG80:AP80),"") -> 180 | AG80: =IF(ISNUMBER(E$87),E80,"") -> 180 | AH80: =IF(ISNUMBER(F$87),F80,"") -> 180 | AI80: =IF(ISNUMBER(G$87),G80,"") -> 180 | AJ80: =IF(ISNUMBER(H$87),H80,"") -> 180 | AK80: =IF(ISNUMBER(I$87),I80,"") -> 180 | AL80: =IF(ISNUMBER(J$87),J80,"") -> 180 | AM80: =IF(ISNUMBER(K$87),K80,"") -> 180 | AN80: =IF(ISNUMBER(L$87),L80,"") -> 180 | ... AP80: =IF(ISNUMBER(N$87),N80,"") -> 180 | AQ80: =IF(C80="Ручная",O80,0) -> 0
A81: 7 | B81: Выгрузить в чистую маркированную тару | C81: Ручная | D81: Выгрузка завершена | E81: 28.08 | F81: 29.16 | G81: 27.54 | H81: 28.62 | I81: 29.7 | J81: 27.81 | K81: 28.89 | L81: 27.27 | M81: 28.35 | N81: 27 | O81: =IF(COUNT(AG81:AP81)>0,MIN(AG81:AP81),"") -> 27 | P81: =IF(COUNT(AG81:AP81)>0,MAX(AG81:AP81),"") -> 29.7 | Q81: =IF(ISNUMBER(O81),P81-O81,"") -> 2.7 | R81: =IF(ISNUMBER(O81),IF(C81="Ручная",IF($S$87>0,$R$87*Q81/$S$87,IF($W$87=7,$R$87,0)),0),"") -> 0.9797542 | S81: =IF(ISNUMBER(O81),O81+R81,"") -> 27.979754 | T81: =IF(ISNUMBER(S81),P81-S81,"") -> 1.7202458 | U81: =IF(COUNT(AG81:AP81)>0,AVERAGE(AG81:AP81),"") -> 28.242 | AG81: =IF(ISNUMBER(E$87),E81,"") -> 28.08 | AH81: =IF(ISNUMBER(F$87),F81,"") -> 29.16 | AI81: =IF(ISNUMBER(G$87),G81,"") -> 27.54 | AJ81: =IF(ISNUMBER(H$87),H81,"") -> 28.62 | AK81: =IF(ISNUMBER(I$87),I81,"") -> 29.7 | AL81: =IF(ISNUMBER(J$87),J81,"") -> 27.81 | AM81: =IF(ISNUMBER(K$87),K81,"") -> 28.89 | AN81: =IF(ISNUMBER(L$87),L81,"") -> 27.27 | ... AP81: =IF(ISNUMBER(N$87),N81,"") -> 27 | AQ81: =IF(C81="Ручная",O81,0) -> 27
A82: 8 | B82: Проверить качество и маркировку | C82: Ручная | D82: Результат проверки подтверждён | E82: 19.08 | F82: 19.8 | G82: 18.54 | H82: 19.26 | I82: 18.18 | J82: 18.9 | K82: 18 | L82: 18.72 | M82: 19.44 | N82: 18.36 | O82: =IF(COUNT(AG82:AP82)>0,MIN(AG82:AP82),"") -> 18 | P82: =IF(COUNT(AG82:AP82)>0,MAX(AG82:AP82),"") -> 19.8 | Q82: =IF(ISNUMBER(O82),P82-O82,"") -> 1.8 | R82: =IF(ISNUMBER(O82),IF(C82="Ручная",IF($S$87>0,$R$87*Q82/$S$87,IF($W$87=8,$R$87,0)),0),"") -> 0.65316947 | S82: =IF(ISNUMBER(O82),O82+R82,"") -> 18.653169 | T82: =IF(ISNUMBER(S82),P82-S82,"") -> 1.1468305 | U82: =IF(COUNT(AG82:AP82)>0,AVERAGE(AG82:AP82),"") -> 18.828 | AG82: =IF(ISNUMBER(E$87),E82,"") -> 19.08 | AH82: =IF(ISNUMBER(F$87),F82,"") -> 19.8 | AI82: =IF(ISNUMBER(G$87),G82,"") -> 18.54 | AJ82: =IF(ISNUMBER(H$87),H82,"") -> 19.26 | AK82: =IF(ISNUMBER(I$87),I82,"") -> 18.18 | AL82: =IF(ISNUMBER(J$87),J82,"") -> 18.9 | AM82: =IF(ISNUMBER(K$87),K82,"") -> 18 | AN82: =IF(ISNUMBER(L$87),L82,"") -> 18.72 | ... AP82: =IF(ISNUMBER(N$87),N82,"") -> 18.36 | AQ82: =IF(C82="Ручная",O82,0) -> 18
A83: — | B83: Передать в зону чистой продукции | C83: Переход | D83: Партия передана | E83: 5.35 | F83: 5.05 | G83: 5.25 | H83: 5 | I83: 5.2 | J83: 5.4 | K83: 5.1 | L83: 5.3 | M83: 5.5 | N83: 5.15 | O83: =IF(COUNT(AG83:AP83)>0,MIN(AG83:AP83),"") -> 5 | P83: =IF(COUNT(AG83:AP83)>0,MAX(AG83:AP83),"") -> 5.5 | Q83: =IF(ISNUMBER(O83),P83-O83,"") -> 0.5 | R83: =IF(ISNUMBER(O83),IF(C83="Ручная",IF($S$87>0,$R$87*Q83/$S$87,IF($W$87=9,$R$87,0)),0),"") -> 0 | S83: =IF(ISNUMBER(O83),O83+R83,"") -> 5 | T83: =IF(ISNUMBER(S83),P83-S83,"") -> 0.5 | U83: =IF(COUNT(AG83:AP83)>0,AVERAGE(AG83:AP83),"") -> 5.23 | AG83: =IF(ISNUMBER(E$87),E83,"") -> 5.35 | AH83: =IF(ISNUMBER(F$87),F83,"") -> 5.05 | AI83: =IF(ISNUMBER(G$87),G83,"") -> 5.25 | AJ83: =IF(ISNUMBER(H$87),H83,"") -> 5 | AK83: =IF(ISNUMBER(I$87),I83,"") -> 5.2 | AL83: =IF(ISNUMBER(J$87),J83,"") -> 5.4 | AM83: =IF(ISNUMBER(K$87),K83,"") -> 5.1 | AN83: =IF(ISNUMBER(L$87),L83,"") -> 5.3 | ... AP83: =IF(ISNUMBER(N$87),N83,"") -> 5.15 | AQ83: =IF(C83="Ручная",O83,0) -> 0
A84: — | B84: Вернуться к началу цикла | C84: Переход | D84: Возврат на исходную позицию | E84: 5 | F84: 5.2 | G84: 5.4 | H84: 5.1 | I84: 5.3 | J84: 5.5 | K84: 5.15 | L84: 5.35 | M84: 5.05 | N84: 5.25 | O84: =IF(COUNT(AG84:AP84)>0,MIN(AG84:AP84),"") -> 5 | P84: =IF(COUNT(AG84:AP84)>0,MAX(AG84:AP84),"") -> 5.5 | Q84: =IF(ISNUMBER(O84),P84-O84,"") -> 0.5 | R84: =IF(ISNUMBER(O84),IF(C84="Ручная",IF($S$87>0,$R$87*Q84/$S$87,IF($W$87=10,$R$87,0)),0),"") -> 0 | S84: =IF(ISNUMBER(O84),O84+R84,"") -> 5 | T84: =IF(ISNUMBER(S84),P84-S84,"") -> 0.5 | U84: =IF(COUNT(AG84:AP84)>0,AVERAGE(AG84:AP84),"") -> 5.23 | AG84: =IF(ISNUMBER(E$87),E84,"") -> 5 | AH84: =IF(ISNUMBER(F$87),F84,"") -> 5.2 | AI84: =IF(ISNUMBER(G$87),G84,"") -> 5.4 | AJ84: =IF(ISNUMBER(H$87),H84,"") -> 5.1 | AK84: =IF(ISNUMBER(I$87),I84,"") -> 5.3 | AL84: =IF(ISNUMBER(J$87),J84,"") -> 5.5 | AM84: =IF(ISNUMBER(K$87),K84,"") -> 5.15 | AN84: =IF(ISNUMBER(L$87),L84,"") -> 5.35 | ... AP84: =IF(ISNUMBER(N$87),N84,"") -> 5.25 | AQ84: =IF(C84="Ручная",O84,0) -> 0
A85: — | B85: Внеплановый поиск тары / ожидание | C85: Потери | D85: Причина задержки устранена | E85: 0 | F85: 0 | G85: 0 | H85: 0 | I85: 0 | J85: 0 | K85: 0 | L85: 0 | M85: 0 | N85: 0 | O85: =IF(COUNT(AG85:AP85)>0,MIN(AG85:AP85),"") -> 0 | P85: =IF(COUNT(AG85:AP85)>0,MAX(AG85:AP85),"") -> 0 | Q85: =IF(ISNUMBER(O85),P85-O85,"") -> 0 | R85: =IF(ISNUMBER(O85),IF(C85="Ручная",IF($S$87>0,$R$87*Q85/$S$87,IF($W$87=11,$R$87,0)),0),"") -> 0 | S85: =IF(ISNUMBER(O85),O85+R85,"") -> 0 | T85: =IF(ISNUMBER(S85),P85-S85,"") -> 0 | U85: =IF(COUNT(AG85:AP85)>0,AVERAGE(AG85:AP85),"") -> 0 | AG85: =IF(ISNUMBER(E$87),E85,"") -> 0 | AH85: =IF(ISNUMBER(F$87),F85,"") -> 0 | AI85: =IF(ISNUMBER(G$87),G85,"") -> 0 | AJ85: =IF(ISNUMBER(H$87),H85,"") -> 0 | AK85: =IF(ISNUMBER(I$87),I85,"") -> 0 | AL85: =IF(ISNUMBER(J$87),J85,"") -> 0 | AM85: =IF(ISNUMBER(K$87),K85,"") -> 0 | AN85: =IF(ISNUMBER(L$87),L85,"") -> 0 | ... AP85: =IF(ISNUMBER(N$87),N85,"") -> 0 | AQ85: =IF(C85="Ручная",O85,0) -> 0
B86: ИТОГИ: все элементы цикла | E86: =IF(COUNT(E75:E85)=11,SUM(E75:E85),"") -> 359.06 | F86: =IF(COUNT(F75:F85)=11,SUM(F75:F85),"") -> 359.72 | G86: =IF(COUNT(G75:G85)=11,SUM(G75:G85),"") -> 358.36 | H86: =IF(COUNT(H75:H85)=11,SUM(H75:H85),"") -> 358.51 | I86: =IF(COUNT(I75:I85)=11,SUM(I75:I85),"") -> 357.75 | J86: =IF(COUNT(J75:J85)=11,SUM(J75:J85),"") -> 356.42 | K86: =IF(COUNT(K75:K85)=11,SUM(K75:K85),"") -> 359.97 | L86: =IF(COUNT(L75:L85)=11,SUM(L75:L85),"") -> 356.16 | ... U86: =IF(COUNT(U75:U85)=11,SUM(U75:U85),"") -> 358.396
B87: ТОЛЬКО полные учтённые циклы | E87: =IF(AND(E73=1,COUNT(E75:E85)=11,MIN(E75:E85)>=0),E86,"") -> 359.06 | F87: =IF(AND(F73=1,COUNT(F75:F85)=11,MIN(F75:F85)>=0),F86,"") -> 359.72 | G87: =IF(AND(G73=1,COUNT(G75:G85)=11,MIN(G75:G85)>=0),G86,"") -> 358.36 | H87: =IF(AND(H73=1,COUNT(H75:H85)=11,MIN(H75:H85)>=0),H86,"") -> 358.51 | I87: =IF(AND(I73=1,COUNT(I75:I85)=11,MIN(I75:I85)>=0),I86,"") -> 357.75 | J87: =IF(AND(J73=1,COUNT(J75:J85)=11,MIN(J75:J85)>=0),J86,"") -> 356.42 | K87: =IF(AND(K73=1,COUNT(K75:K85)=11,MIN(K75:K85)>=0),K86,"") -> 359.97 | L87: =IF(AND(L73=1,COUNT(L75:L85)=11,MIN(L75:L85)>=0),L86,"") -> 356.16 | ... N87: =IF(AND(N73=1,COUNT(N75:N85)=11,MIN(N75:N85)>=0),N86,"") -> 359.04 | O87: =IF(COUNT(E87:N87)>0,MIN(E87:N87),"") -> 356.16 | P87: =IF(COUNT(E87:N87)>0,MAX(E87:N87),"") -> 359.97 | Q87: =IF(ISNUMBER(O87),P87-O87,"") -> 3.81 | R87: =IF(ISNUMBER(O87),MAX(0,O87-O86),"") -> 5.61 | S87: =SUMIF(C75:C85,"Ручная",Q75:Q85) -> 15.46 | T87: =COUNT(E87:N87) -> 10 | U87: =IF(COUNT(E87:N87)>0,AVERAGE(E87:N87),"") -> 358.396 | V87: =IF(ISNUMBER(O87),S86-O87,"") -> -5.6843419e-14 | W87: =MATCH(MAX(AQ75:AQ85),AQ75:AQ85,0) -> 2 | X87: =IF(T87=0,"НЕТ ЗАМЕРОВ",IF(T87<10,"МЕНЕЕ 10 ЦИКЛОВ",IF(ABS(V87)<0.000001,"ОК","ОШИБКА РЕГУЛИРОВКИ"))) -> ОК
A88: В строке учтённых циклов: O = T min; P = T max; Q = размах цикла; R = T min − сумма t min; S = сумма размахов ручных элементов; T = число циклов; U = среднее; V = сумма t отрег − T min (должно быть 0).
A91: 05. Белокочанная капуста · ЦЕЛЬ · 10 демонстрационных циклов, заменить реальными
A92: ="Масса замера, кг: "&'Ассортимент'!J12&". Все замеры одной партии/исполнителя/условий. Основание: "&'Ввод'!B15 -> Масса замера, кг: 3. Все замеры одной партии/исполнителя/условий. Основание: ДЕМО: прогноз; улучшения не внедрены
A93: № | B93: Рабочий элемент | C93: Тип | D93: Точка отсчёта | E93: 1 | F93: 2 | G93: 3 | H93: 4 | I93: 5 | J93: 6 | K93: 7 | L93: 8 | M93: 9 | N93: 10 | O93: t min | P93: t max | Q93: Размах | R93: Рег. с | S93: t отрег. | T93: Колебания | U93: Среднее | V93: Контроль | W93: Служебно | X93: Статус
B94: Учитывать цикл: 1 / 0 | E94: 1 | F94: 1 | G94: 1 | H94: 1 | I94: 1 | J94: 1 | K94: 1 | L94: 1 | M94: 1 | N94: 1
B95: Причина исключения / условия | E95: ДЕМО | F95: ДЕМО | G95: ДЕМО | H95: ДЕМО | I95: ДЕМО | J95: ДЕМО | K95: ДЕМО | L95: ДЕМО | M95: ДЕМО | N95: ДЕМО
A96: 1 | B96: Осмотреть упаковку и сырьё | C96: Ручная | D96: Осмотр партии завершён | E96: 26.5 | F96: 27.5 | G96: 25.75 | H96: 26.75 | I96: 25.25 | J96: 26.25 | K96: 25 | L96: 26 | M96: 27 | N96: 25.5 | O96: =IF(COUNT(AG96:AP96)>0,MIN(AG96:AP96),"") -> 25 | P96: =IF(COUNT(AG96:AP96)>0,MAX(AG96:AP96),"") -> 27.5 | Q96: =IF(ISNUMBER(O96),P96-O96,"") -> 2.5 | R96: =IF(ISNUMBER(O96),IF(C96="Ручная",IF($S$108>0,$R$108*Q96/$S$108,IF($W$108=1,$R$108,0)),0),"") -> 0.86053837 | S96: =IF(ISNUMBER(O96),O96+R96,"") -> 25.860538 | T96: =IF(ISNUMBER(S96),P96-S96,"") -> 1.6394616 | U96: =IF(COUNT(AG96:AP96)>0,AVERAGE(AG96:AP96),"") -> 26.15 | AG96: =IF(ISNUMBER(E$108),E96,"") -> 26.5 | AH96: =IF(ISNUMBER(F$108),F96,"") -> 27.5 | AI96: =IF(ISNUMBER(G$108),G96,"") -> 25.75 | AJ96: =IF(ISNUMBER(H$108),H96,"") -> 26.75 | AK96: =IF(ISNUMBER(I$108),I96,"") -> 25.25 | AL96: =IF(ISNUMBER(J$108),J96,"") -> 26.25 | AM96: =IF(ISNUMBER(K$108),K96,"") -> 25 | AN96: =IF(ISNUMBER(L$108),L96,"") -> 26 | ... AP96: =IF(ISNUMBER(N$108),N96,"") -> 25.5 | AQ96: =IF(C96="Ручная",O96,0) -> 25
A97: 2 | B97: Отсортировать / подготовить сырьё | C97: Ручная | D97: Подготовленное сырьё отложено | E97: 58.85 | F97: 55.55 | G97: 57.75 | H97: 55 | I97: 57.2 | J97: 59.4 | K97: 56.1 | L97: 58.3 | M97: 60.5 | N97: 56.65 | O97: =IF(COUNT(AG97:AP97)>0,MIN(AG97:AP97),"") -> 55 | P97: =IF(COUNT(AG97:AP97)>0,MAX(AG97:AP97),"") -> 60.5 | Q97: =IF(ISNUMBER(O97),P97-O97,"") -> 5.5 | R97: =IF(ISNUMBER(O97),IF(C97="Ручная",IF($S$108>0,$R$108*Q97/$S$108,IF($W$108=2,$R$108,0)),0),"") -> 1.8931844 | S97: =IF(ISNUMBER(O97),O97+R97,"") -> 56.893184 | T97: =IF(ISNUMBER(S97),P97-S97,"") -> 3.6068156 | U97: =IF(COUNT(AG97:AP97)>0,AVERAGE(AG97:AP97),"") -> 57.53 | AG97: =IF(ISNUMBER(E$108),E97,"") -> 58.85 | AH97: =IF(ISNUMBER(F$108),F97,"") -> 55.55 | AI97: =IF(ISNUMBER(G$108),G97,"") -> 57.75 | AJ97: =IF(ISNUMBER(H$108),H97,"") -> 55 | AK97: =IF(ISNUMBER(I$108),I97,"") -> 57.2 | AL97: =IF(ISNUMBER(J$108),J97,"") -> 59.4 | AM97: =IF(ISNUMBER(K$108),K97,"") -> 56.1 | AN97: =IF(ISNUMBER(L$108),L97,"") -> 58.3 | ... AP97: =IF(ISNUMBER(N$108),N97,"") -> 56.65 | AQ97: =IF(C97="Ручная",O97,0) -> 55
A98: 3 | B98: Отвесить допустимую партию | C98: Ручная | D98: Масса партии проверена | E98: 19.8 | F98: 20.59 | G98: 21.38 | H98: 20.2 | I98: 20.99 | J98: 21.78 | K98: 20.39 | L98: 21.19 | M98: 20 | N98: 20.79 | O98: =IF(COUNT(AG98:AP98)>0,MIN(AG98:AP98),"") -> 19.8 | P98: =IF(COUNT(AG98:AP98)>0,MAX(AG98:AP98),"") -> 21.78 | Q98: =IF(ISNUMBER(O98),P98-O98,"") -> 1.98 | R98: =IF(ISNUMBER(O98),IF(C98="Ручная",IF($S$108>0,$R$108*Q98/$S$108,IF($W$108=3,$R$108,0)),0),"") -> 0.68154639 | S98: =IF(ISNUMBER(O98),O98+R98,"") -> 20.481546 | T98: =IF(ISNUMBER(S98),P98-S98,"") -> 1.2984536 | U98: =IF(COUNT(AG98:AP98)>0,AVERAGE(AG98:AP98),"") -> 20.711 | AG98: =IF(ISNUMBER(E$108),E98,"") -> 19.8 | AH98: =IF(ISNUMBER(F$108),F98,"") -> 20.59 | AI98: =IF(ISNUMBER(G$108),G98,"") -> 21.38 | AJ98: =IF(ISNUMBER(H$108),H98,"") -> 20.2 | AK98: =IF(ISNUMBER(I$108),I98,"") -> 20.99 | AL98: =IF(ISNUMBER(J$108),J98,"") -> 21.78 | AM98: =IF(ISNUMBER(K$108),K98,"") -> 20.39 | AN98: =IF(ISNUMBER(L$108),L98,"") -> 21.19 | ... AP98: =IF(ISNUMBER(N$108),N98,"") -> 20.79 | AQ98: =IF(C98="Ручная",O98,0) -> 19.8
A99: — | B99: Перейти с партией к SOLIA | C99: Переход | D99: Оператор у SOLIA | E99: 6.12 | F99: 6.36 | G99: 6.6 | H99: 6.18 | I99: 6.42 | J99: 6.06 | K99: 6.3 | L99: 6 | M99: 6.24 | N99: 6.48 | O99: =IF(COUNT(AG99:AP99)>0,MIN(AG99:AP99),"") -> 6 | P99: =IF(COUNT(AG99:AP99)>0,MAX(AG99:AP99),"") -> 6.6 | Q99: =IF(ISNUMBER(O99),P99-O99,"") -> 0.6 | R99: =IF(ISNUMBER(O99),IF(C99="Ручная",IF($S$108>0,$R$108*Q99/$S$108,IF($W$108=4,$R$108,0)),0),"") -> 0 | S99: =IF(ISNUMBER(O99),O99+R99,"") -> 6 | T99: =IF(ISNUMBER(S99),P99-S99,"") -> 0.6 | U99: =IF(COUNT(AG99:AP99)>0,AVERAGE(AG99:AP99),"") -> 6.276 | AG99: =IF(ISNUMBER(E$108),E99,"") -> 6.12 | AH99: =IF(ISNUMBER(F$108),F99,"") -> 6.36 | AI99: =IF(ISNUMBER(G$108),G99,"") -> 6.6 | AJ99: =IF(ISNUMBER(H$108),H99,"") -> 6.18 | AK99: =IF(ISNUMBER(I$108),I99,"") -> 6.42 | AL99: =IF(ISNUMBER(J$108),J99,"") -> 6.06 | AM99: =IF(ISNUMBER(K$108),K99,"") -> 6.3 | AN99: =IF(ISNUMBER(L$108),L99,"") -> 6 | ... AP99: =IF(ISNUMBER(N$108),N99,"") -> 6.48 | AQ99: =IF(C99="Ручная",O99,0) -> 0
A100: 5 | B100: Загрузить, выбрать программу, запустить | C100: Ручная | D100: Программа запущена | E100: 30.64 | F100: 31.83 | G100: 30.05 | H100: 31.24 | I100: 29.75 | J100: 30.94 | K100: 32.13 | L100: 30.34 | M100: 31.54 | N100: 32.73 | O100: =IF(COUNT(AG100:AP100)>0,MIN(AG100:AP100),"") -> 29.75 | P100: =IF(COUNT(AG100:AP100)>0,MAX(AG100:AP100),"") -> 32.73 | Q100: =IF(ISNUMBER(O100),P100-O100,"") -> 2.98 | R100: =IF(ISNUMBER(O100),IF(C100="Ручная",IF($S$108>0,$R$108*Q100/$S$108,IF($W$108=5,$R$108,0)),0),"") -> 1.0257617 | S100: =IF(ISNUMBER(O100),O100+R100,"") -> 30.775762 | T100: =IF(ISNUMBER(S100),P100-S100,"") -> 1.9542383 | U100: =IF(COUNT(AG100:AP100)>0,AVERAGE(AG100:AP100),"") -> 31.119 | AG100: =IF(ISNUMBER(E$108),E100,"") -> 30.64 | AH100: =IF(ISNUMBER(F$108),F100,"") -> 31.83 | AI100: =IF(ISNUMBER(G$108),G100,"") -> 30.05 | AJ100: =IF(ISNUMBER(H$108),H100,"") -> 31.24 | AK100: =IF(ISNUMBER(I$108),I100,"") -> 29.75 | AL100: =IF(ISNUMBER(J$108),J100,"") -> 30.94 | AM100: =IF(ISNUMBER(K$108),K100,"") -> 32.13 | AN100: =IF(ISNUMBER(L$108),L100,"") -> 30.34 | ... AP100: =IF(ISNUMBER(N$108),N100,"") -> 32.73 | AQ100: =IF(C100="Ручная",O100,0) -> 29.75
A101: — | B101: Автоматическая программа / ожидание | C101: Авто/ожидание | D101: Полный цикл программы завершён | E101: ='Ассортимент'!R12 -> 180 | F101: ='Ассортимент'!R12 -> 180 | G101: ='Ассортимент'!R12 -> 180 | H101: ='Ассортимент'!R12 -> 180 | I101: ='Ассортимент'!R12 -> 180 | J101: ='Ассортимент'!R12 -> 180 | K101: ='Ассортимент'!R12 -> 180 | L101: ='Ассортимент'!R12 -> 180 | M101: ='Ассортимент'!R12 -> 180 | N101: ='Ассортимент'!R12 -> 180 | O101: =IF(COUNT(AG101:AP101)>0,MIN(AG101:AP101),"") -> 180 | P101: =IF(COUNT(AG101:AP101)>0,MAX(AG101:AP101),"") -> 180 | Q101: =IF(ISNUMBER(O101),P101-O101,"") -> 0 | R101: =IF(ISNUMBER(O101),IF(C101="Ручная",IF($S$108>0,$R$108*Q101/$S$108,IF($W$108=6,$R$108,0)),0),"") -> 0 | S101: =IF(ISNUMBER(O101),O101+R101,"") -> 180 | T101: =IF(ISNUMBER(S101),P101-S101,"") -> 0 | U101: =IF(COUNT(AG101:AP101)>0,AVERAGE(AG101:AP101),"") -> 180 | AG101: =IF(ISNUMBER(E$108),E101,"") -> 180 | AH101: =IF(ISNUMBER(F$108),F101,"") -> 180 | AI101: =IF(ISNUMBER(G$108),G101,"") -> 180 | AJ101: =IF(ISNUMBER(H$108),H101,"") -> 180 | AK101: =IF(ISNUMBER(I$108),I101,"") -> 180 | AL101: =IF(ISNUMBER(J$108),J101,"") -> 180 | AM101: =IF(ISNUMBER(K$108),K101,"") -> 180 | AN101: =IF(ISNUMBER(L$108),L101,"") -> 180 | ... AP101: =IF(ISNUMBER(N$108),N101,"") -> 180 | AQ101: =IF(C101="Ручная",O101,0) -> 0
A102: 7 | B102: Выгрузить в чистую маркированную тару | C102: Ручная | D102: Выгрузка завершена | E102: 29.16 | F102: 27.54 | G102: 28.62 | H102: 29.7 | I102: 27.81 | J102: 28.89 | K102: 27.27 | L102: 28.35 | M102: 27 | N102: 28.08 | O102: =IF(COUNT(AG102:AP102)>0,MIN(AG102:AP102),"") -> 27 | P102: =IF(COUNT(AG102:AP102)>0,MAX(AG102:AP102),"") -> 29.7 | Q102: =IF(ISNUMBER(O102),P102-O102,"") -> 2.7 | R102: =IF(ISNUMBER(O102),IF(C102="Ручная",IF($S$108>0,$R$108*Q102/$S$108,IF($W$108=7,$R$108,0)),0),"") -> 0.92938144 | S102: =IF(ISNUMBER(O102),O102+R102,"") -> 27.929381 | T102: =IF(ISNUMBER(S102),P102-S102,"") -> 1.7706186 | U102: =IF(COUNT(AG102:AP102)>0,AVERAGE(AG102:AP102),"") -> 28.242 | AG102: =IF(ISNUMBER(E$108),E102,"") -> 29.16 | AH102: =IF(ISNUMBER(F$108),F102,"") -> 27.54 | AI102: =IF(ISNUMBER(G$108),G102,"") -> 28.62 | AJ102: =IF(ISNUMBER(H$108),H102,"") -> 29.7 | AK102: =IF(ISNUMBER(I$108),I102,"") -> 27.81 | AL102: =IF(ISNUMBER(J$108),J102,"") -> 28.89 | AM102: =IF(ISNUMBER(K$108),K102,"") -> 27.27 | AN102: =IF(ISNUMBER(L$108),L102,"") -> 28.35 | ... AP102: =IF(ISNUMBER(N$108),N102,"") -> 28.08 | AQ102: =IF(C102="Ручная",O102,0) -> 27
A103: 8 | B103: Проверить качество и маркировку | C103: Ручная | D103: Результат проверки подтверждён | E103: 19.8 | F103: 18.54 | G103: 19.26 | H103: 18.18 | I103: 18.9 | J103: 18 | K103: 18.72 | L103: 19.44 | M103: 18.36 | N103: 19.08 | O103: =IF(COUNT(AG103:AP103)>0,MIN(AG103:AP103),"") -> 18 | P103: =IF(COUNT(AG103:AP103)>0,MAX(AG103:AP103),"") -> 19.8 | Q103: =IF(ISNUMBER(O103),P103-O103,"") -> 1.8 | R103: =IF(ISNUMBER(O103),IF(C103="Ручная",IF($S$108>0,$R$108*Q103/$S$108,IF($W$108=8,$R$108,0)),0),"") -> 0.61958763 | S103: =IF(ISNUMBER(O103),O103+R103,"") -> 18.619588 | T103: =IF(ISNUMBER(S103),P103-S103,"") -> 1.1804124 | U103: =IF(COUNT(AG103:AP103)>0,AVERAGE(AG103:AP103),"") -> 18.828 | AG103: =IF(ISNUMBER(E$108),E103,"") -> 19.8 | AH103: =IF(ISNUMBER(F$108),F103,"") -> 18.54 | AI103: =IF(ISNUMBER(G$108),G103,"") -> 19.26 | AJ103: =IF(ISNUMBER(H$108),H103,"") -> 18.18 | AK103: =IF(ISNUMBER(I$108),I103,"") -> 18.9 | AL103: =IF(ISNUMBER(J$108),J103,"") -> 18 | AM103: =IF(ISNUMBER(K$108),K103,"") -> 18.72 | AN103: =IF(ISNUMBER(L$108),L103,"") -> 19.44 | ... AP103: =IF(ISNUMBER(N$108),N103,"") -> 19.08 | AQ103: =IF(C103="Ручная",O103,0) -> 18
A104: — | B104: Передать в зону чистой продукции | C104: Переход | D104: Партия передана | E104: 5.05 | F104: 5.25 | G104: 5 | H104: 5.2 | I104: 5.4 | J104: 5.1 | K104: 5.3 | L104: 5.5 | M104: 5.15 | N104: 5.35 | O104: =IF(COUNT(AG104:AP104)>0,MIN(AG104:AP104),"") -> 5 | P104: =IF(COUNT(AG104:AP104)>0,MAX(AG104:AP104),"") -> 5.5 | Q104: =IF(ISNUMBER(O104),P104-O104,"") -> 0.5 | R104: =IF(ISNUMBER(O104),IF(C104="Ручная",IF($S$108>0,$R$108*Q104/$S$108,IF($W$108=9,$R$108,0)),0),"") -> 0 | S104: =IF(ISNUMBER(O104),O104+R104,"") -> 5 | T104: =IF(ISNUMBER(S104),P104-S104,"") -> 0.5 | U104: =IF(COUNT(AG104:AP104)>0,AVERAGE(AG104:AP104),"") -> 5.23 | AG104: =IF(ISNUMBER(E$108),E104,"") -> 5.05 | AH104: =IF(ISNUMBER(F$108),F104,"") -> 5.25 | AI104: =IF(ISNUMBER(G$108),G104,"") -> 5 | AJ104: =IF(ISNUMBER(H$108),H104,"") -> 5.2 | AK104: =IF(ISNUMBER(I$108),I104,"") -> 5.4 | AL104: =IF(ISNUMBER(J$108),J104,"") -> 5.1 | AM104: =IF(ISNUMBER(K$108),K104,"") -> 5.3 | AN104: =IF(ISNUMBER(L$108),L104,"") -> 5.5 | ... AP104: =IF(ISNUMBER(N$108),N104,"") -> 5.35 | AQ104: =IF(C104="Ручная",O104,0) -> 0
A105: — | B105: Вернуться к началу цикла | C105: Переход | D105: Возврат на исходную позицию | E105: 5.2 | F105: 5.4 | G105: 5.1 | H105: 5.3 | I105: 5.5 | J105: 5.15 | K105: 5.35 | L105: 5.05 | M105: 5.25 | N105: 5 | O105: =IF(COUNT(AG105:AP105)>0,MIN(AG105:AP105),"") -> 5 | P105: =IF(COUNT(AG105:AP105)>0,MAX(AG105:AP105),"") -> 5.5 | Q105: =IF(ISNUMBER(O105),P105-O105,"") -> 0.5 | R105: =IF(ISNUMBER(O105),IF(C105="Ручная",IF($S$108>0,$R$108*Q105/$S$108,IF($W$108=10,$R$108,0)),0),"") -> 0 | S105: =IF(ISNUMBER(O105),O105+R105,"") -> 5 | T105: =IF(ISNUMBER(S105),P105-S105,"") -> 0.5 | U105: =IF(COUNT(AG105:AP105)>0,AVERAGE(AG105:AP105),"") -> 5.23 | AG105: =IF(ISNUMBER(E$108),E105,"") -> 5.2 | AH105: =IF(ISNUMBER(F$108),F105,"") -> 5.4 | AI105: =IF(ISNUMBER(G$108),G105,"") -> 5.1 | AJ105: =IF(ISNUMBER(H$108),H105,"") -> 5.3 | AK105: =IF(ISNUMBER(I$108),I105,"") -> 5.5 | AL105: =IF(ISNUMBER(J$108),J105,"") -> 5.15 | AM105: =IF(ISNUMBER(K$108),K105,"") -> 5.35 | AN105: =IF(ISNUMBER(L$108),L105,"") -> 5.05 | ... AP105: =IF(ISNUMBER(N$108),N105,"") -> 5 | AQ105: =IF(C105="Ручная",O105,0) -> 0
A106: — | B106: Внеплановый поиск тары / ожидание | C106: Потери | D106: Причина задержки устранена | E106: 0 | F106: 0 | G106: 0 | H106: 0 | I106: 0 | J106: 0 | K106: 0 | L106: 0 | M106: 0 | N106: 0 | O106: =IF(COUNT(AG106:AP106)>0,MIN(AG106:AP106),"") -> 0 | P106: =IF(COUNT(AG106:AP106)>0,MAX(AG106:AP106),"") -> 0 | Q106: =IF(ISNUMBER(O106),P106-O106,"") -> 0 | R106: =IF(ISNUMBER(O106),IF(C106="Ручная",IF($S$108>0,$R$108*Q106/$S$108,IF($W$108=11,$R$108,0)),0),"") -> 0 | S106: =IF(ISNUMBER(O106),O106+R106,"") -> 0 | T106: =IF(ISNUMBER(S106),P106-S106,"") -> 0 | U106: =IF(COUNT(AG106:AP106)>0,AVERAGE(AG106:AP106),"") -> 0 | AG106: =IF(ISNUMBER(E$108),E106,"") -> 0 | AH106: =IF(ISNUMBER(F$108),F106,"") -> 0 | AI106: =IF(ISNUMBER(G$108),G106,"") -> 0 | AJ106: =IF(ISNUMBER(H$108),H106,"") -> 0 | AK106: =IF(ISNUMBER(I$108),I106,"") -> 0 | AL106: =IF(ISNUMBER(J$108),J106,"") -> 0 | AM106: =IF(ISNUMBER(K$108),K106,"") -> 0 | AN106: =IF(ISNUMBER(L$108),L106,"") -> 0 | ... AP106: =IF(ISNUMBER(N$108),N106,"") -> 0 | AQ106: =IF(C106="Ручная",O106,0) -> 0
B107: ИТОГИ: все элементы цикла | E107: =IF(COUNT(E96:E106)=11,SUM(E96:E106),"") -> 381.12 | F107: =IF(COUNT(F96:F106)=11,SUM(F96:F106),"") -> 378.56 | G107: =IF(COUNT(G96:G106)=11,SUM(G96:G106),"") -> 379.51 | H107: =IF(COUNT(H96:H106)=11,SUM(H96:H106),"") -> 377.75 | I107: =IF(COUNT(I96:I106)=11,SUM(I96:I106),"") -> 377.22 | J107: =IF(COUNT(J96:J106)=11,SUM(J96:J106),"") -> 381.57 | K107: =IF(COUNT(K96:K106)=11,SUM(K96:K106),"") -> 376.56 | L107: =IF(COUNT(L96:L106)=11,SUM(L96:L106),"") -> 380.17 | ... U107: =IF(COUNT(U96:U106)=11,SUM(U96:U106),"") -> 379.316
B108: ТОЛЬКО полные учтённые циклы | E108: =IF(AND(E94=1,COUNT(E96:E106)=11,MIN(E96:E106)>=0),E107,"") -> 381.12 | F108: =IF(AND(F94=1,COUNT(F96:F106)=11,MIN(F96:F106)>=0),F107,"") -> 378.56 | G108: =IF(AND(G94=1,COUNT(G96:G106)=11,MIN(G96:G106)>=0),G107,"") -> 379.51 | H108: =IF(AND(H94=1,COUNT(H96:H106)=11,MIN(H96:H106)>=0),H107,"") -> 377.75 | I108: =IF(AND(I94=1,COUNT(I96:I106)=11,MIN(I96:I106)>=0),I107,"") -> 377.22 | J108: =IF(AND(J94=1,COUNT(J96:J106)=11,MIN(J96:J106)>=0),J107,"") -> 381.57 | K108: =IF(AND(K94=1,COUNT(K96:K106)=11,MIN(K96:K106)>=0),K107,"") -> 376.56 | L108: =IF(AND(L94=1,COUNT(L96:L106)=11,MIN(L96:L106)>=0),L107,"") -> 380.17 | ... N108: =IF(AND(N94=1,COUNT(N96:N106)=11,MIN(N96:N106)>=0),N107,"") -> 379.66 | O108: =IF(COUNT(E108:N108)>0,MIN(E108:N108),"") -> 376.56 | P108: =IF(COUNT(E108:N108)>0,MAX(E108:N108),"") -> 381.57 | Q108: =IF(ISNUMBER(O108),P108-O108,"") -> 5.01 | R108: =IF(ISNUMBER(O108),MAX(0,O108-O107),"") -> 6.01 | S108: =SUMIF(C96:C106,"Ручная",Q96:Q106) -> 17.46 | T108: =COUNT(E108:N108) -> 10 | U108: =IF(COUNT(E108:N108)>0,AVERAGE(E108:N108),"") -> 379.316 | V108: =IF(ISNUMBER(O108),S107-O108,"") -> -5.6843419e-14 | W108: =MATCH(MAX(AQ96:AQ106),AQ96:AQ106,0) -> 2 | X108: =IF(T108=0,"НЕТ ЗАМЕРОВ",IF(T108<10,"МЕНЕЕ 10 ЦИКЛОВ",IF(ABS(V108)<0.000001,"ОК","ОШИБКА РЕГУЛИРОВКИ"))) -> ОК
A109: В строке учтённых циклов: O = T min; P = T max; Q = размах цикла; R = T min − сумма t min; S = сумма размахов ручных элементов; T = число циклов; U = среднее; V = сумма t отрег − T min (должно быть 0).
A112: 06. Укроп · ЦЕЛЬ · 10 демонстрационных циклов, заменить реальными
...

Sheet Периодическая работа
A1: 05 / ЛИСТ НАБЛЮДЕНИЯ ПЕРИОДИЧЕСКОЙ РАБОТЫ
A2: ДЕМО / ПРОЕКТ • Жёлтые ячейки — ваш ввод. Расчёты не являются утверждёнными нормативами.
A3: ← Начало | B3: Синий фон — формула; серый — инструкция; жёлтый — ввод. Защита снимается без пароля.
A5: Минимум из 3 замеров / периодичность = нормативное распределение на цикл. Для проверки плана применяются ЦЕЛЫЕ события и отдельный резерв завершения неполного блока.
A7: № | B7: Рабочий элемент | C7: Событие | D7: Каждые N циклов | E7: ДО 1, с | F7: ДО 2, с | G7: ДО 3, с | H7: min ДО, с | I7: ДО, с/цикл | J7: ЦЕЛЬ 1, с | K7: ЦЕЛЬ 2, с | L7: ЦЕЛЬ 3, с | M7: min ЦЕЛЬ, с | N7: ЦЕЛЬ, с/цикл | O7: Событий/смену | P7: ДО за смену, с | Q7: ЦЕЛЬ за смену, с | R7: Источник / ограничения
A8: 1 | B8: Слить бак после каждой 4-й помывки | C8: Санобработка | D8: ='Ввод'!B24 -> 4 | E8: 60 | F8: 65 | G8: 70 | H8: =IF(AND(COUNT(E8:G8)=3,MIN(E8:G8)>0),MIN(E8:G8),"") -> 60 | I8: =IF(AND(ISNUMBER(H8),ISNUMBER(D8),D8>0),H8/D8,"") -> 15 | J8: =E8 -> 60 | K8: =F8 -> 65 | L8: =G8 -> 70 | M8: =IF(AND(COUNT(J8:L8)=3,MIN(J8:L8)>0),MIN(J8:L8),"") -> 60 | N8: =IF(AND(ISNUMBER(M8),ISNUMBER(D8),D8>0),M8/D8,"") -> 15 | O8: =$B$20 -> 8 | P8: =IF(AND(ISNUMBER(H8),ISNUMBER(O8)),H8*O8,"") -> 480 | Q8: =IF(AND(ISNUMBER(M8),ISNUMBER(O8)),M8*O8,"") -> 480 | R8: И-ГЦ-02, стр. 3: обязательная последовательность; время — ДЕМО
A9: 2 | B9: После слива выключить и обесточить оборудование | C9: Санобработка | D9: ='Ввод'!B24 -> 4 | E9: 15 | F9: 18 | G9: 16 | H9: =IF(AND(COUNT(E9:G9)=3,MIN(E9:G9)>0),MIN(E9:G9),"") -> 15 | I9: =IF(AND(ISNUMBER(H9),ISNUMBER(D9),D9>0),H9/D9,"") -> 3.75 | J9: =E9 -> 15 | K9: =F9 -> 18 | L9: =G9 -> 16 | M9: =IF(AND(COUNT(J9:L9)=3,MIN(J9:L9)>0),MIN(J9:L9),"") -> 15 | N9: =IF(AND(ISNUMBER(M9),ISNUMBER(D9),D9>0),M9/D9,"") -> 3.75 | O9: =$B$20 -> 8 | P9: =IF(AND(ISNUMBER(H9),ISNUMBER(O9)),H9*O9,"") -> 120 | Q9: =IF(AND(ISNUMBER(M9),ISNUMBER(O9)),M9*O9,"") -> 120 | R9: И-ГЦ-02, стр. 3: обязательная последовательность; время — ДЕМО
A10: 3 | B10: Промыть бак моющими средствами | C10: Санобработка | D10: ='Ввод'!B24 -> 4 | E10: 240 | F10: 255 | G10: 250 | H10: =IF(AND(COUNT(E10:G10)=3,MIN(E10:G10)>0),MIN(E10:G10),"") -> 240 | I10: =IF(AND(ISNUMBER(H10),ISNUMBER(D10),D10>0),H10/D10,"") -> 60 | J10: =E10 -> 240 | K10: =F10 -> 255 | L10: =G10 -> 250 | M10: =IF(AND(COUNT(J10:L10)=3,MIN(J10:L10)>0),MIN(J10:L10),"") -> 240 | N10: =IF(AND(ISNUMBER(M10),ISNUMBER(D10),D10>0),M10/D10,"") -> 60 | O10: =$B$20 -> 8 | P10: =IF(AND(ISNUMBER(H10),ISNUMBER(O10)),H10*O10,"") -> 1920 | Q10: =IF(AND(ISNUMBER(M10),ISNUMBER(O10)),M10*O10,"") -> 1920 | R10: И-ГЦ-02, стр. 3; средство, режим и фактическое время уточнить
A11: 4 | B11: Продезинфицировать бак по утверждённой программе | C11: Санобработка | D11: ='Ввод'!B24 -> 4 | E11: 480 | F11: 500 | G11: 490 | H11: =IF(AND(COUNT(E11:G11)=3,MIN(E11:G11)>0),MIN(E11:G11),"") -> 480 | I11: =IF(AND(ISNUMBER(H11),ISNUMBER(D11),D11>0),H11/D11,"") -> 120 | J11: =E11 -> 480 | K11: =F11 -> 500 | L11: =G11 -> 490 | M11: =IF(AND(COUNT(J11:L11)=3,MIN(J11:L11)>0),MIN(J11:L11),"") -> 480 | N11: =IF(AND(ISNUMBER(M11),ISNUMBER(D11),D11>0),M11/D11,"") -> 120 | O11: =$B$20 -> 8 | P11: =IF(AND(ISNUMBER(H11),ISNUMBER(O11)),H11*O11,"") -> 3840 | Q11: =IF(AND(ISNUMBER(M11),ISNUMBER(O11)),M11*O11,"") -> 3840 | R11: Время — только ДЕМО, НЕ экспозиция средства. Не задаёт концентрацию, температуру или выдержку
A12: 5 | B12: Восстановить готовность SOLIA по паспорту оборудования | C12: Санобработка | D12: ='Ввод'!B24 -> 4 | E12: 120 | F12: 130 | G12: 125 | H12: =IF(AND(COUNT(E12:G12)=3,MIN(E12:G12)>0),MIN(E12:G12),"") -> 120 | I12: =IF(AND(ISNUMBER(H12),ISNUMBER(D12),D12>0),H12/D12,"") -> 30 | J12: =E12 -> 120 | K12: =F12 -> 130 | L12: =G12 -> 125 | M12: =IF(AND(COUNT(J12:L12)=3,MIN(J12:L12)>0),MIN(J12:L12),"") -> 120 | N12: =IF(AND(ISNUMBER(M12),ISNUMBER(D12),D12>0),M12/D12,"") -> 30 | O12: =$B$20 -> 8 | P12: =IF(AND(ISNUMBER(H12),ISNUMBER(O12)),H12*O12,"") -> 960 | Q12: =IF(AND(ISNUMBER(M12),ISNUMBER(O12)),M12*O12,"") -> 960 | R12: Плановое дополнение: действия и время сверить с паспортом SOLIA и санпрограммой
A13: 6 | B13: Подать комплект чистой тары до 1-го цикла и далее каждые 8 циклов | C13: Подача тары | D13: 8 | E13: 60 | F13: 65 | G13: 70 | H13: =IF(AND(COUNT(E13:G13)=3,MIN(E13:G13)>0),MIN(E13:G13),"") -> 60 | I13: =IF(AND(ISNUMBER(H13),ISNUMBER(D13),D13>0),H13/D13,"") -> 7.5 | J13: 45 | K13: 50 | L13: 48 | M13: =IF(AND(COUNT(J13:L13)=3,MIN(J13:L13)>0),MIN(J13:L13),"") -> 45 | N13: =IF(AND(ISNUMBER(M13),ISNUMBER(D13),D13>0),M13/D13,"") -> 5.625 | O13: =IF(AND(ISNUMBER('Ввод'!B28),'Ввод'!B28>=0,ISNUMBER(D13),D13>0),ROUNDUP('Ввод'!B28/D13,0),"") -> 4 | P13: =IF(AND(ISNUMBER(H13),ISNUMBER(O13)),H13*O13,"") -> 240 | Q13: =IF(AND(ISNUMBER(M13),ISNUMBER(O13)),M13*O13,"") -> 180 | R13: ДЕМО: периодичность и время заменить наблюдениями; не входит в фиксированную подготовку смены
B15: ИТОГО | I15: =IF(COUNT(I8:I13)=6,SUM(I8:I13),"") -> 236.25 | N15: =IF(COUNT(N8:N13)=6,SUM(N8:N13),"") -> 234.375 | P15: =IF(COUNT(P8:P13)=6,SUM(P8:P13),"") -> 7560 | Q15: =IF(COUNT(Q8:Q13)=6,SUM(Q8:Q13),"") -> 7500
B18: =IF(AND(ISNUMBER('Ввод'!B28),'Ввод'!B28>0,ISNUMBER('Ввод'!B25),'Ввод'!B25>=0,'Ввод'!B25<=3,MOD('Ввод'!B25,1)=0),INT(('Ввод'!B28+'Ввод'!B25)/4),IF('Ввод'!B28=0,0,"")) -> 8 | C18: Регулярных полных санобработок
B19: =IF(COUNT('Ввод'!B28,'Ввод'!B25)=2,IF(AND('Ввод'!B28>0,'Ввод'!B26=1,MOD('Ввод'!B28+'Ввод'!B25,4)>0),1,0),"") -> 0 | C19: Дополнительных после неполного блока
B20: =IF(ISNUMBER(B18),B18+B19,"") -> 8 | C20: Всего полных комплексов за смену
A22: Частота 4 — фиксированное требование И-ГЦ-02. Комплекс состоит из 5 строк, но число санобработок НЕ суммируется по этим строкам. Завершение неполного блока — отдельный резерв, не утверждённое требование источника. Не вычитать эти же секунды ещё раз из фонда рабочего времени.
A26: ДО и ЦЕЛЬ используют одинаковые санитарные времена. Улучшение не достигается за счёт экспозиции, концентрации, температуры или пропуска очистки. Обесточивание следует ПОСЛЕ слива, как указано в И-ГЦ-02. Восстановление готовности — проектное дополнение по паспорту машины, который требуется проверить.

Sheet Расчет ДО
A1: 06 / II ТИП · СРЕДНЕВЗВЕШЕННЫЕ ВРЕМЕНА · ДО
A2: ДЕМО / ПРОЕКТ • Жёлтые ячейки — ваш ввод. Расчёты не являются утверждёнными нормативами.
A3: ← Начало | B3: Синий фон — формула; серый — инструкция; жёлтый — ввод. Защита снимается без пароля.
A7: № | B7: Продукт | C7: Партий | D7: Вес | E7: Ручная, с | F7: Переходы, с | G7: Потери, с | H7: Авто/ожид., с | I7: Цикл min = отрег., с | J7: Цикл сред., с | K7: Цикл max, с | L7: Σ колебаний элементов, с | M7: Периодич. норматив, с/цикл | N7: Цикл + периодич., с | O7: Циклическое min, с/смену | P7: Циклическое сред., с/смену | Q7: Активное занятие, с/цикл | R7: Машина, с/цикл | S7: Учтено циклов | T7: Контроль регулировки | U7: Полнота данных
A8: 1 | B8: Латук | C8: ='Ассортимент'!O8 -> 2 | D8: ='Ассортимент'!Q8 -> 0.0625 | E8: =SUMIF('Замеры ДО'!C12:C22,"Ручная",'Замеры ДО'!S12:S22) -> 238.38 | F8: =SUMIF('Замеры ДО'!C12:C22,"Переход",'Замеры ДО'!S12:S22) -> 32 | G8: ='Замеры ДО'!S22 -> 12 | H8: ='Ассортимент'!R8 -> 450 | I8: ='Замеры ДО'!O24 -> 732.38 | J8: ='Замеры ДО'!U24 -> 736.604 | K8: ='Замеры ДО'!P24 -> 740.92 | L8: ='Замеры ДО'!T23 -> 19.02 | M8: ='Периодическая работа'!I15 -> 236.25 | N8: =IF(AND(ISNUMBER(I8),ISNUMBER(M8)),I8+M8,"") -> 968.63 | O8: =IF(AND(ISNUMBER(C8),ISNUMBER(I8)),C8*I8,IF(C8=0,0,"")) -> 1464.76 | P8: =IF(AND(ISNUMBER(C8),ISNUMBER(J8)),C8*J8,IF(C8=0,0,"")) -> 1473.208 | Q8: =IF(ISNUMBER(I8),SUM(E8:G8),"") -> 282.38 | R8: =IF(ISNUMBER(I8),'Замеры ДО'!S16+'Замеры ДО'!S18+H8,"") -> 517.36826 | S8: ='Замеры ДО'!T24 -> 10 | T8: ='Замеры ДО'!V24 -> 0 | U8: =IF(NOT(ISNUMBER(C8)),"ОШИБКА ПЛАНА",IF(C8=0,"Нет в плане",IF(AND(ISNUMBER(I8),S8>0),"ОК","НЕТ ЗАМЕРОВ"))) -> ОК
A9: 2 | B9: Базилик | C9: ='Ассортимент'!O9 -> 1 | D9: ='Ассортимент'!Q9 -> 0.03125 | E9: =SUMIF('Замеры ДО'!C33:C43,"Ручная",'Замеры ДО'!S33:S43) -> 248.58 | F9: =SUMIF('Замеры ДО'!C33:C43,"Переход",'Замеры ДО'!S33:S43) -> 32 | G9: ='Замеры ДО'!S43 -> 12 | H9: ='Ассортимент'!R9 -> 450 | I9: ='Замеры ДО'!O45 -> 742.58 | J9: ='Замеры ДО'!U45 -> 747.064 | K9: ='Замеры ДО'!P45 -> 751.92 | L9: ='Замеры ДО'!T44 -> 19.82 | M9: ='Периодическая работа'!I15 -> 236.25 | N9: =IF(AND(ISNUMBER(I9),ISNUMBER(M9)),I9+M9,"") -> 978.83 | O9: =IF(AND(ISNUMBER(C9),ISNUMBER(I9)),C9*I9,IF(C9=0,0,"")) -> 742.58 | P9: =IF(AND(ISNUMBER(C9),ISNUMBER(J9)),C9*J9,IF(C9=0,0,"")) -> 747.064 | Q9: =IF(ISNUMBER(I9),SUM(E9:G9),"") -> 292.58 | R9: =IF(ISNUMBER(I9),'Замеры ДО'!S37+'Замеры ДО'!S39+H9,"") -> 517.32375 | S9: ='Замеры ДО'!T45 -> 10 | T9: ='Замеры ДО'!V45 -> 0 | U9: =IF(NOT(ISNUMBER(C9)),"ОШИБКА ПЛАНА",IF(C9=0,"Нет в плане",IF(AND(ISNUMBER(I9),S9>0),"ОК","НЕТ ЗАМЕРОВ"))) -> ОК
A10: 3 | B10: Петрушка | C10: ='Ассортимент'!O10 -> 1 | D10: ='Ассортимент'!Q10 -> 0.03125 | E10: =SUMIF('Замеры ДО'!C54:C64,"Ручная",'Замеры ДО'!S54:S64) -> 258.78 | F10: =SUMIF('Замеры ДО'!C54:C64,"Переход",'Замеры ДО'!S54:S64) -> 32 | G10: ='Замеры ДО'!S64 -> 12 | H10: ='Ассортимент'!R10 -> 450 | I10: ='Замеры ДО'!O66 -> 752.78 | J10: ='Замеры ДО'!U66 -> 757.524 | K10: ='Замеры ДО'!P66 -> 762.92 | L10: ='Замеры ДО'!T65 -> 20.62 | M10: ='Периодическая работа'!I15 -> 236.25 | N10: =IF(AND(ISNUMBER(I10),ISNUMBER(M10)),I10+M10,"") -> 989.03 | O10: =IF(AND(ISNUMBER(C10),ISNUMBER(I10)),C10*I10,IF(C10=0,0,"")) -> 752.78 | P10: =IF(AND(ISNUMBER(C10),ISNUMBER(J10)),C10*J10,IF(C10=0,0,"")) -> 757.524 | Q10: =IF(ISNUMBER(I10),SUM(E10:G10),"") -> 302.78 | R10: =IF(ISNUMBER(I10),'Замеры ДО'!S58+'Замеры ДО'!S60+H10,"") -> 517.2828 | S10: ='Замеры ДО'!T66 -> 10 | T10: ='Замеры ДО'!V66 -> 1.1368684e-13 | U10: =IF(NOT(ISNUMBER(C10)),"ОШИБКА ПЛАНА",IF(C10=0,"Нет в плане",IF(AND(ISNUMBER(I10),S10>0),"ОК","НЕТ ЗАМЕРОВ"))) -> ОК
A11: 4 | B11: Томат | C11: ='Ассортимент'!O11 -> 5 | D11: ='Ассортимент'!Q11 -> 0.15625 | E11: =SUMIF('Замеры ДО'!C75:C85,"Ручная",'Замеры ДО'!S75:S85) -> 172.08 | F11: =SUMIF('Замеры ДО'!C75:C85,"Переход",'Замеры ДО'!S75:S85) -> 32 | G11: ='Замеры ДО'!S85 -> 12 | H11: ='Ассортимент'!R11 -> 180 | I11: ='Замеры ДО'!O87 -> 396.08 | J11: ='Замеры ДО'!U87 -> 398.614 | K11: ='Замеры ДО'!P87 -> 399.97 | L11: ='Замеры ДО'!T86 -> 13.82 | M11: ='Периодическая работа'!I15 -> 236.25 | N11: =IF(AND(ISNUMBER(I11),ISNUMBER(M11)),I11+M11,"") -> 632.33 | O11: =IF(AND(ISNUMBER(C11),ISNUMBER(I11)),C11*I11,IF(C11=0,0,"")) -> 1980.4 | P11: =IF(AND(ISNUMBER(C11),ISNUMBER(J11)),C11*J11,IF(C11=0,0,"")) -> 1993.07 | Q11: =IF(ISNUMBER(I11),SUM(E11:G11),"") -> 216.08 | R11: =IF(ISNUMBER(I11),'Замеры ДО'!S79+'Замеры ДО'!S81+H11,"") -> 247.78909 | S11: ='Замеры ДО'!T87 -> 10 | T11: ='Замеры ДО'!V87 -> 0 | U11: =IF(NOT(ISNUMBER(C11)),"ОШИБКА ПЛАНА",IF(C11=0,"Нет в плане",IF(AND(ISNUMBER(I11),S11>0),"ОК","НЕТ ЗАМЕРОВ"))) -> ОК
A12: 5 | B12: Белокочанная капуста | C12: ='Ассортимент'!O12 -> 3 | D12: ='Ассортимент'!Q12 -> 0.09375 | E12: =SUMIF('Замеры ДО'!C96:C106,"Ручная",'Замеры ДО'!S96:S106) -> 192.48 | F12: =SUMIF('Замеры ДО'!C96:C106,"Переход",'Замеры ДО'!S96:S106) -> 32 | G12: ='Замеры ДО'!S106 -> 12 | H12: ='Ассортимент'!R12 -> 180 | I12: ='Замеры ДО'!O108 -> 416.48 | J12: ='Замеры ДО'!U108 -> 419.534 | K12: ='Замеры ДО'!P108 -> 421.57 | L12: ='Замеры ДО'!T107 -> 15.42 | M12: ='Периодическая работа'!I15 -> 236.25 | N12: =IF(AND(ISNUMBER(I12),ISNUMBER(M12)),I12+M12,"") -> 652.73 | O12: =IF(AND(ISNUMBER(C12),ISNUMBER(I12)),C12*I12,IF(C12=0,0,"")) -> 1249.44 | P12: =IF(AND(ISNUMBER(C12),ISNUMBER(J12)),C12*J12,IF(C12=0,0,"")) -> 1258.602 | Q12: =IF(ISNUMBER(I12),SUM(E12:G12),"") -> 236.48 | R12: =IF(ISNUMBER(I12),'Замеры ДО'!S100+'Замеры ДО'!S102+H12,"") -> 247.62811 | S12: ='Замеры ДО'!T108 -> 10 | T12: ='Замеры ДО'!V108 -> 0 | U12: =IF(NOT(ISNUMBER(C12)),"ОШИБКА ПЛАНА",IF(C12=0,"Нет в плане",IF(AND(ISNUMBER(I12),S12>0),"ОК","НЕТ ЗАМЕРОВ"))) -> ОК
A13: 6 | B13: Укроп | C13: ='Ассортимент'!O13 -> 2 | D13: ='Ассортимент'!Q13 -> 0.0625 | E13: =SUMIF('Замеры ДО'!C117:C127,"Ручная",'Замеры ДО'!S117:S127) -> 253.68 | F13: =SUMIF('Замеры ДО'!C117:C127,"Переход",'Замеры ДО'!S117:S127) -> 32 | G13: ='Замеры ДО'!S127 -> 12 | H13: ='Ассортимент'!R13 -> 300 | I13: ='Замеры ДО'!O129 -> 597.68 | J13: ='Замеры ДО'!U129 -> 602.294 | K13: ='Замеры ДО'!P129 -> 607.42 | L13: ='Замеры ДО'!T128 -> 20.22 | M13: ='Периодическая работа'!I15 -> 236.25 | N13: =IF(AND(ISNUMBER(I13),ISNUMBER(M13)),I13+M13,"") -> 833.93 | O13: =IF(AND(ISNUMBER(C13),ISNUMBER(I13)),C13*I13,IF(C13=0,0,"")) -> 1195.36 | P13: =IF(AND(ISNUMBER(C13),ISNUMBER(J13)),C13*J13,IF(C13=0,0,"")) -> 1204.588 | Q13: =IF(ISNUMBER(I13),SUM(E13:G13),"") -> 297.68 | R13: =IF(ISNUMBER(I13),'Замеры ДО'!S121+'Замеры ДО'!S123+H13,"") -> 367.30286 | S13: ='Замеры ДО'!T129 -> 10 | T13: ='Замеры ДО'!V129 -> 0 | U13: =IF(NOT(ISNUMBER(C13)),"ОШИБКА ПЛАНА",IF(C13=0,"Нет в плане",IF(AND(ISNUMBER(I13),S13>0),"ОК","НЕТ ЗАМЕРОВ"))) -> ОК
A14: 7 | B14: Зеленый лук | C14: ='Ассортимент'!O14 -> 1 | D14: ='Ассортимент'!Q14 -> 0.03125 | E14: =SUMIF('Замеры ДО'!C138:C148,"Ручная",'Замеры ДО'!S138:S148) -> 238.38 | F14: =SUMIF('Замеры ДО'!C138:C148,"Переход",'Замеры ДО'!S138:S148) -> 32 | G14: ='Замеры ДО'!S148 -> 12 | H14: ='Ассортимент'!R14 -> 300 | I14: ='Замеры ДО'!O150 -> 582.38 | J14: ='Замеры ДО'!U150 -> 586.604 | K14: ='Замеры ДО'!P150 -> 590.92 | L14: ='Замеры ДО'!T149 -> 19.02 | M14: ='Периодическая работа'!I15 -> 236.25 | N14: =IF(AND(ISNUMBER(I14),ISNUMBER(M14)),I14+M14,"") -> 818.63 | O14: =IF(AND(ISNUMBER(C14),ISNUMBER(I14)),C14*I14,IF(C14=0,0,"")) -> 582.38 | P14: =IF(AND(ISNUMBER(C14),ISNUMBER(J14)),C14*J14,IF(C14=0,0,"")) -> 586.604 | Q14: =IF(ISNUMBER(I14),SUM(E14:G14),"") -> 282.38 | R14: =IF(ISNUMBER(I14),'Замеры ДО'!S142+'Замеры ДО'!S144+H14,"") -> 367.36826 | S14: ='Замеры ДО'!T150 -> 10 | T14: ='Замеры ДО'!V150 -> 0 | U14: =IF(NOT(ISNUMBER(C14)),"ОШИБКА ПЛАНА",IF(C14=0,"Нет в плане",IF(AND(ISNUMBER(I14),S14>0),"ОК","НЕТ ЗАМЕРОВ"))) -> ОК
A15: 8 | B15: Кинза | C15: ='Ассортимент'!O15 -> 1 | D15: ='Ассортимент'!Q15 -> 0.03125 | E15: =SUMIF('Замеры ДО'!C159:C169,"Ручная",'Замеры ДО'!S159:S169) -> 258.78 | F15: =SUMIF('Замеры ДО'!C159:C169,"Переход",'Замеры ДО'!S159:S169) -> 32 | G15: ='Замеры ДО'!S169 -> 12 | H15: ='Ассортимент'!R15 -> 300 | I15: ='Замеры ДО'!O171 -> 602.78 | J15: ='Замеры ДО'!U171 -> 607.524 | K15: ='Замеры ДО'!P171 -> 612.92 | L15: ='Замеры ДО'!T170 -> 20.62 | M15: ='Периодическая работа'!I15 -> 236.25 | N15: =IF(AND(ISNUMBER(I15),ISNUMBER(M15)),I15+M15,"") -> 839.03 | O15: =IF(AND(ISNUMBER(C15),ISNUMBER(I15)),C15*I15,IF(C15=0,0,"")) -> 602.78 | P15: =IF(AND(ISNUMBER(C15),ISNUMBER(J15)),C15*J15,IF(C15=0,0,"")) -> 607.524 | Q15: =IF(ISNUMBER(I15),SUM(E15:G15),"") -> 302.78 | R15: =IF(ISNUMBER(I15),'Замеры ДО'!S163+'Замеры ДО'!S165+H15,"") -> 367.2828 | S15: ='Замеры ДО'!T171 -> 10 | T15: ='Замеры ДО'!V171 -> 0 | U15: =IF(NOT(ISNUMBER(C15)),"ОШИБКА ПЛАНА",IF(C15=0,"Нет в плане",IF(AND(ISNUMBER(I15),S15>0),"ОК","НЕТ ЗАМЕРОВ"))) -> ОК
A16: 9 | B16: Шампиньоны | C16: ='Ассортимент'!O16 -> 2 | D16: ='Ассортимент'!Q16 -> 0.0625 | E16: =SUMIF('Замеры ДО'!C180:C190,"Ручная",'Замеры ДО'!S180:S190) -> 202.68 | F16: =SUMIF('Замеры ДО'!C180:C190,"Переход",'Замеры ДО'!S180:S190) -> 32 | G16: ='Замеры ДО'!S190 -> 12 | H16: ='Ассортимент'!R16 -> 300 | I16: ='Замеры ДО'!O192 -> 546.68 | J16: ='Замеры ДО'!U192 -> 549.994 | K16: ='Замеры ДО'!P192 -> 552.42 | L16: ='Замеры ДО'!T191 -> 16.22 | M16: ='Периодическая работа'!I15 -> 236.25 | N16: =IF(AND(ISNUMBER(I16),ISNUMBER(M16)),I16+M16,"") -> 782.93 | O16: =IF(AND(ISNUMBER(C16),ISNUMBER(I16)),C16*I16,IF(C16=0,0,"")) -> 1093.36 | P16: =IF(AND(ISNUMBER(C16),ISNUMBER(J16)),C16*J16,IF(C16=0,0,"")) -> 1099.988 | Q16: =IF(ISNUMBER(I16),SUM(E16:G16),"") -> 246.68 | R16: =IF(ISNUMBER(I16),'Замеры ДО'!S184+'Замеры ДО'!S186+H16,"") -> 367.56 | S16: ='Замеры ДО'!T192 -> 10 | T16: ='Замеры ДО'!V192 -> 0 | U16: =IF(NOT(ISNUMBER(C16)),"ОШИБКА ПЛАНА",IF(C16=0,"Нет в плане",IF(AND(ISNUMBER(I16),S16>0),"ОК","НЕТ ЗАМЕРОВ"))) -> ОК
A17: 10 | B17: Перец болгарский красный | C17: ='Ассортимент'!O17 -> 3 | D17: ='Ассортимент'!Q17 -> 0.09375 | E17: =SUMIF('Замеры ДО'!C201:C211,"Ручная",'Замеры ДО'!S201:S211) -> 182.28 | F17: =SUMIF('Замеры ДО'!C201:C211,"Переход",'Замеры ДО'!S201:S211) -> 32 | G17: ='Замеры ДО'!S211 -> 12 | H17: ='Ассортимент'!R17 -> 300 | I17: ='Замеры ДО'!O213 -> 526.28 | J17: ='Замеры ДО'!U213 -> 529.074 | K17: ='Замеры ДО'!P213 -> 530.77 | L17: ='Замеры ДО'!T212 -> 14.62 | M17: ='Периодическая работа'!I15 -> 236.25 | N17: =IF(AND(ISNUMBER(I17),ISNUMBER(M17)),I17+M17,"") -> 762.53 | O17: =IF(AND(ISNUMBER(C17),ISNUMBER(I17)),C17*I17,IF(C17=0,0,"")) -> 1578.84 | P17: =IF(AND(ISNUMBER(C17),ISNUMBER(J17)),C17*J17,IF(C17=0,0,"")) -> 1587.222 | Q17: =IF(ISNUMBER(I17),SUM(E17:G17),"") -> 226.28 | R17: =IF(ISNUMBER(I17),'Замеры ДО'!S205+'Замеры ДО'!S207+H17,"") -> 367.704 | S17: ='Замеры ДО'!T213 -> 10 | T17: ='Замеры ДО'!V213 -> 0 | U17: =IF(NOT(ISNUMBER(C17)),"ОШИБКА ПЛАНА",IF(C17=0,"Нет в плане",IF(AND(ISNUMBER(I17),S17>0),"ОК","НЕТ ЗАМЕРОВ"))) -> ОК
A18: 11 | B18: Огурец | C18: ='Ассортимент'!O18 -> 4 | D18: ='Ассортимент'!Q18 -> 0.125 | E18: =SUMIF('Замеры ДО'!C222:C232,"Ручная",'Замеры ДО'!S222:S232) -> 172.08 | F18: =SUMIF('Замеры ДО'!C222:C232,"Переход",'Замеры ДО'!S222:S232) -> 32 | G18: ='Замеры ДО'!S232 -> 12 | H18: ='Ассортимент'!R18 -> 300 | I18: ='Замеры ДО'!O234 -> 516.08 | J18: ='Замеры ДО'!U234 -> 518.614 | K18: ='Замеры ДО'!P234 -> 519.97 | L18: ='Замеры ДО'!T233 -> 13.82 | M18: ='Периодическая работа'!I15 -> 236.25 | N18: =IF(AND(ISNUMBER(I18),ISNUMBER(M18)),I18+M18,"") -> 752.33 | O18: =IF(AND(ISNUMBER(C18),ISNUMBER(I18)),C18*I18,IF(C18=0,0,"")) -> 2064.32 | P18: =IF(AND(ISNUMBER(C18),ISNUMBER(J18)),C18*J18,IF(C18=0,0,"")) -> 2074.456 | Q18: =IF(ISNUMBER(I18),SUM(E18:G18),"") -> 216.08 | R18: =IF(ISNUMBER(I18),'Замеры ДО'!S226+'Замеры ДО'!S228+H18,"") -> 367.78909 | S18: ='Замеры ДО'!T234 -> 10 | T18: ='Замеры ДО'!V234 -> 0 | U18: =IF(NOT(ISNUMBER(C18)),"ОШИБКА ПЛАНА",IF(C18=0,"Нет в плане",IF(AND(ISNUMBER(I18),S18>0),"ОК","НЕТ ЗАМЕРОВ"))) -> ОК
A19: 12 | B19: Редис | C19: ='Ассортимент'!O19 -> 1 | D19: ='Ассортимент'!Q19 -> 0.03125 | E19: =SUMIF('Замеры ДО'!C243:C253,"Ручная",'Замеры ДО'!S243:S253) -> 197.58 | F19: =SUMIF('Замеры ДО'!C243:C253,"Переход",'Замеры ДО'!S243:S253) -> 32 | G19: ='Замеры ДО'!S253 -> 12 | H19: ='Ассортимент'!R19 -> 300 | I19: ='Замеры ДО'!O255 -> 541.58 | J19: ='Замеры ДО'!U255 -> 544.764 | K19: ='Замеры ДО'!P255 -> 546.97 | L19: ='Замеры ДО'!T254 -> 15.82 | M19: ='Периодическая работа'!I15 -> 236.25 | N19: =IF(AND(ISNUMBER(I19),ISNUMBER(M19)),I19+M19,"") -> 777.83 | O19: =IF(AND(ISNUMBER(C19),ISNUMBER(I19)),C19*I19,IF(C19=0,0,"")) -> 541.58 | P19: =IF(AND(ISNUMBER(C19),ISNUMBER(J19)),C19*J19,IF(C19=0,0,"")) -> 544.764 | Q19: =IF(ISNUMBER(I19),SUM(E19:G19),"") -> 241.58 | R19: =IF(ISNUMBER(I19),'Замеры ДО'!S247+'Замеры ДО'!S249+H19,"") -> 367.59316 | S19: ='Замеры ДО'!T255 -> 10 | T19: ='Замеры ДО'!V255 -> 0 | U19: =IF(NOT(ISNUMBER(C19)),"ОШИБКА ПЛАНА",IF(C19=0,"Нет в плане",IF(AND(ISNUMBER(I19),S19>0),"ОК","НЕТ ЗАМЕРОВ"))) -> ОК
A20: 13 | B20: Сельдерей ствол | C20: ='Ассортимент'!O20 -> 1 | D20: ='Ассортимент'!Q20 -> 0.03125 | E20: =SUMIF('Замеры ДО'!C264:C274,"Ручная",'Замеры ДО'!S264:S274) -> 207.78 | F20: =SUMIF('Замеры ДО'!C264:C274,"Переход",'Замеры ДО'!S264:S274) -> 32 | G20: ='Замеры ДО'!S274 -> 12 | H20: ='Ассортимент'!R20 -> 300 | I20: ='Замеры ДО'!O276 -> 551.78 | J20: ='Замеры ДО'!U276 -> 555.224 | K20: ='Замеры ДО'!P276 -> 557.92 | L20: ='Замеры ДО'!T275 -> 16.62 | M20: ='Периодическая работа'!I15 -> 236.25 | N20: =IF(AND(ISNUMBER(I20),ISNUMBER(M20)),I20+M20,"") -> 788.03 | O20: =IF(AND(ISNUMBER(C20),ISNUMBER(I20)),C20*I20,IF(C20=0,0,"")) -> 551.78 | P20: =IF(AND(ISNUMBER(C20),ISNUMBER(J20)),C20*J20,IF(C20=0,0,"")) -> 555.224 | Q20: =IF(ISNUMBER(I20),SUM(E20:G20),"") -> 251.78 | R20: =IF(ISNUMBER(I20),'Замеры ДО'!S268+'Замеры ДО'!S270+H20,"") -> 367.5285 | S20: ='Замеры ДО'!T276 -> 10 | T20: ='Замеры ДО'!V276 -> 0 | U20: =IF(NOT(ISNUMBER(C20)),"ОШИБКА ПЛАНА",IF(C20=0,"Нет в плане",IF(AND(ISNUMBER(I20),S20>0),"ОК","НЕТ ЗАМЕРОВ"))) -> ОК
A21: 14 | B21: Сельдерей корень | C21: ='Ассортимент'!O21 -> 1 | D21: ='Ассортимент'!Q21 -> 0.03125 | E21: =SUMIF('Замеры ДО'!C285:C295,"Ручная",'Замеры ДО'!S285:S295) -> 202.68 | F21: =SUMIF('Замеры ДО'!C285:C295,"Переход",'Замеры ДО'!S285:S295) -> 32 | G21: ='Замеры ДО'!S295 -> 12 | H21: ='Ассортимент'!R21 -> 300 | I21: ='Замеры ДО'!O297 -> 546.68 | J21: ='Замеры ДО'!U297 -> 549.994 | K21: ='Замеры ДО'!P297 -> 552.42 | L21: ='Замеры ДО'!T296 -> 16.22 | M21: ='Периодическая работа'!I15 -> 236.25 | N21: =IF(AND(ISNUMBER(I21),ISNUMBER(M21)),I21+M21,"") -> 782.93 | O21: =IF(AND(ISNUMBER(C21),ISNUMBER(I21)),C21*I21,IF(C21=0,0,"")) -> 546.68 | P21: =IF(AND(ISNUMBER(C21),ISNUMBER(J21)),C21*J21,IF(C21=0,0,"")) -> 549.994 | Q21: =IF(ISNUMBER(I21),SUM(E21:G21),"") -> 246.68 | R21: =IF(ISNUMBER(I21),'Замеры ДО'!S289+'Замеры ДО'!S291+H21,"") -> 367.56 | S21: ='Замеры ДО'!T297 -> 10 | T21: ='Замеры ДО'!V297 -> 0 | U21: =IF(NOT(ISNUMBER(C21)),"ОШИБКА ПЛАНА",IF(C21=0,"Нет в плане",IF(AND(ISNUMBER(I21),S21>0),"ОК","НЕТ ЗАМЕРОВ"))) -> ОК
A22: 15 | B22: Тыква | C22: ='Ассортимент'!O22 -> 1 | D22: ='Ассортимент'!Q22 -> 0.03125 | E22: =SUMIF('Замеры ДО'!C306:C316,"Ручная",'Замеры ДО'!S306:S316) -> 182.28 | F22: =SUMIF('Замеры ДО'!C306:C316,"Переход",'Замеры ДО'!S306:S316) -> 32 | G22: ='Замеры ДО'!S316 -> 12 | H22: ='Ассортимент'!R22 -> 300 | I22: ='Замеры ДО'!O318 -> 526.28 | J22: ='Замеры ДО'!U318 -> 529.074 | K22: ='Замеры ДО'!P318 -> 530.77 | L22: ='Замеры ДО'!T317 -> 14.62 | M22: ='Периодическая работа'!I15 -> 236.25 | N22: =IF(AND(ISNUMBER(I22),ISNUMBER(M22)),I22+M22,"") -> 762.53 | O22: =IF(AND(ISNUMBER(C22),ISNUMBER(I22)),C22*I22,IF(C22=0,0,"")) -> 526.28 | P22: =IF(AND(ISNUMBER(C22),ISNUMBER(J22)),C22*J22,IF(C22=0,0,"")) -> 529.074 | Q22: =IF(ISNUMBER(I22),SUM(E22:G22),"") -> 226.28 | R22: =IF(ISNUMBER(I22),'Замеры ДО'!S310+'Замеры ДО'!S312+H22,"") -> 367.704 | S22: ='Замеры ДО'!T318 -> 10 | T22: ='Замеры ДО'!V318 -> 0 | U22: =IF(NOT(ISNUMBER(C22)),"ОШИБКА ПЛАНА",IF(C22=0,"Нет в плане",IF(AND(ISNUMBER(I22),S22>0),"ОК","НЕТ ЗАМЕРОВ"))) -> ОК
A23: 16 | B23: Имбирь | C23: ='Ассортимент'!O23 -> 1 | D23: ='Ассортимент'!Q23 -> 0.03125 | E23: =SUMIF('Замеры ДО'!C327:C337,"Ручная",'Замеры ДО'!S327:S337) -> 192.48 | F23: =SUMIF('Замеры ДО'!C327:C337,"Переход",'Замеры ДО'!S327:S337) -> 32 | G23: ='Замеры ДО'!S337 -> 12 | H23: ='Ассортимент'!R23 -> 300 | I23: ='Замеры ДО'!O339 -> 536.48 | J23: ='Замеры ДО'!U339 -> 539.534 | K23: ='Замеры ДО'!P339 -> 541.57 | L23: ='Замеры ДО'!T338 -> 15.42 | M23: ='Периодическая работа'!I15 -> 236.25 | N23: =IF(AND(ISNUMBER(I23),ISNUMBER(M23)),I23+M23,"") -> 772.73 | O23: =IF(AND(ISNUMBER(C23),ISNUMBER(I23)),C23*I23,IF(C23=0,0,"")) -> 536.48 | P23: =IF(AND(ISNUMBER(C23),ISNUMBER(J23)),C23*J23,IF(C23=0,0,"")) -> 539.534 | Q23: =IF(ISNUMBER(I23),SUM(E23:G23),"") -> 236.48 | R23: =IF(ISNUMBER(I23),'Замеры ДО'!S331+'Замеры ДО'!S333+H23,"") -> 367.62811 | S23: ='Замеры ДО'!T339 -> 10 | T23: ='Замеры ДО'!V339 -> 0 | U23: =IF(NOT(ISNUMBER(C23)),"ОШИБКА ПЛАНА",IF(C23=0,"Нет в плане",IF(AND(ISNUMBER(I23),S23>0),"ОК","НЕТ ЗАМЕРОВ"))) -> ОК
A24: 17 | B24: Лимон | C24: ='Ассортимент'!O24 -> 1 | D24: ='Ассортимент'!Q24 -> 0.03125 | E24: =SUMIF('Замеры ДО'!C348:C358,"Ручная",'Замеры ДО'!S348:S358) -> 166.98 | F24: =SUMIF('Замеры ДО'!C348:C358,"Переход",'Замеры ДО'!S348:S358) -> 32 | G24: ='Замеры ДО'!S358 -> 12 | H24: ='Ассортимент'!R24 -> 300 | I24: ='Замеры ДО'!O360 -> 510.98 | J24: ='Замеры ДО'!U360 -> 513.384 | K24: ='Замеры ДО'!P360 -> 514.57 | L24: ='Замеры ДО'!T359 -> 13.42 | M24: ='Периодическая работа'!I15 -> 236.25 | N24: =IF(AND(ISNUMBER(I24),ISNUMBER(M24)),I24+M24,"") -> 747.23 | O24: =IF(AND(ISNUMBER(C24),ISNUMBER(I24)),C24*I24,IF(C24=0,0,"")) -> 510.98 | P24: =IF(AND(ISNUMBER(C24),ISNUMBER(J24)),C24*J24,IF(C24=0,0,"")) -> 513.384 | Q24: =IF(ISNUMBER(I24),SUM(E24:G24),"") -> 210.98 | R24: =IF(ISNUMBER(I24),'Замеры ДО'!S352+'Замеры ДО'!S354+H24,"") -> 367.83562 | S24: ='Замеры ДО'!T360 -> 10 | T24: ='Замеры ДО'!V360 -> 0 | U24: =IF(NOT(ISNUMBER(C24)),"ОШИБКА ПЛАНА",IF(C24=0,"Нет в плане",IF(AND(ISNUMBER(I24),S24>0),"ОК","НЕТ ЗАМЕРОВ"))) -> ОК
A25: 18 | B25: Апельсин | C25: ='Ассортимент'!O25 -> 1 | D25: ='Ассортимент'!Q25 -> 0.03125 | E25: =SUMIF('Замеры ДО'!C369:C379,"Ручная",'Замеры ДО'!S369:S379) -> 166.98 | F25: =SUMIF('Замеры ДО'!C369:C379,"Переход",'Замеры ДО'!S369:S379) -> 32 | G25: ='Замеры ДО'!S379 -> 12 | H25: ='Ассортимент'!R25 -> 300 | I25: ='Замеры ДО'!O381 -> 510.98 | J25: ='Замеры ДО'!U381 -> 513.384 | K25: ='Замеры ДО'!P381 -> 514.57 | L25: ='Замеры ДО'!T380 -> 13.42 | M25: ='Периодическая работа'!I15 -> 236.25 | N25: =IF(AND(ISNUMBER(I25),ISNUMBER(M25)),I25+M25,"") -> 747.23 | O25: =IF(AND(ISNUMBER(C25),ISNUMBER(I25)),C25*I25,IF(C25=0,0,"")) -> 510.98 | P25: =IF(AND(ISNUMBER(C25),ISNUMBER(J25)),C25*J25,IF(C25=0,0,"")) -> 513.384 | Q25: =IF(ISNUMBER(I25),SUM(E25:G25),"") -> 210.98 | R25: =IF(ISNUMBER(I25),'Замеры ДО'!S373+'Замеры ДО'!S375+H25,"") -> 367.83562 | S25: ='Замеры ДО'!T381 -> 10 | T25: ='Замеры ДО'!V381 -> 0 | U25: =IF(NOT(ISNUMBER(C25)),"ОШИБКА ПЛАНА",IF(C25=0,"Нет в плане",IF(AND(ISNUMBER(I25),S25>0),"ОК","НЕТ ЗАМЕРОВ"))) -> ОК
B27: Ср. вз. / итоги | C27: =IF(COUNT(C8:C25)=18,SUM(C8:C25),"") -> 32 | D27: =SUM(D8:D25) -> 1 | E27: =IF(AND(AND(ISNUMBER($C$27),$C$27>0,COUNTIF($U$8:$U$25,"НЕТ ЗАМЕРОВ")=0,COUNTIF($U$8:$U$25,"ОШИБКА ПЛАНА")=0),SUMPRODUCT($C$8:$C$25,ISNUMBER(E8:E25)*1)=$C$27),SUMPRODUCT($C$8:$C$25,E8:E25)/$C$27,"") -> 199.4925 | F27: =IF(AND(AND(ISNUMBER($C$27),$C$27>0,COUNTIF($U$8:$U$25,"НЕТ ЗАМЕРОВ")=0,COUNTIF($U$8:$U$25,"ОШИБКА ПЛАНА")=0),SUMPRODUCT($C$8:$C$25,ISNUMBER(F8:F25)*1)=$C$27),SUMPRODUCT($C$8:$C$25,F8:F25)/$C$27,"") -> 32 | G27: =IF(AND(AND(ISNUMBER($C$27),$C$27>0,COUNTIF($U$8:$U$25,"НЕТ ЗАМЕРОВ")=0,COUNTIF($U$8:$U$25,"ОШИБКА ПЛАНА")=0),SUMPRODUCT($C$8:$C$25,ISNUMBER(G8:G25)*1)=$C$27),SUMPRODUCT($C$8:$C$25,G8:G25)/$C$27,"") -> 12 | H27: =IF(AND(AND(ISNUMBER($C$27),$C$27>0,COUNTIF($U$8:$U$25,"НЕТ ЗАМЕРОВ")=0,COUNTIF($U$8:$U$25,"ОШИБКА ПЛАНА")=0),SUMPRODUCT($C$8:$C$25,ISNUMBER(H8:H25)*1)=$C$27),SUMPRODUCT($C$8:$C$25,H8:H25)/$C$27,"") -> 288.75 | I27: =IF(AND(AND(ISNUMBER($C$27),$C$27>0,COUNTIF($U$8:$U$25,"НЕТ ЗАМЕРОВ")=0,COUNTIF($U$8:$U$25,"ОШИБКА ПЛАНА")=0),SUMPRODUCT($C$8:$C$25,ISNUMBER(I8:I25)*1)=$C$27),SUMPRODUCT($C$8:$C$25,I8:I25)/$C$27,"") -> 532.2425 | J27: =IF(AND(AND(ISNUMBER($C$27),$C$27>0,COUNTIF($U$8:$U$25,"НЕТ ЗАМЕРОВ")=0,COUNTIF($U$8:$U$25,"ОШИБКА ПЛАНА")=0),SUMPRODUCT($C$8:$C$25,ISNUMBER(J8:J25)*1)=$C$27),SUMPRODUCT($C$8:$C$25,J8:J25)/$C$27,"") -> 535.47525 | K27: =IF(AND(AND(ISNUMBER($C$27),$C$27>0,COUNTIF($U$8:$U$25,"НЕТ ЗАМЕРОВ")=0,COUNTIF($U$8:$U$25,"ОШИБКА ПЛАНА")=0),SUMPRODUCT($C$8:$C$25,ISNUMBER(K8:K25)*1)=$C$27),SUMPRODUCT($C$8:$C$25,K8:K25)/$C$27,"") -> 537.99188 | L27: =IF(AND(AND(ISNUMBER($C$27),$C$27>0,COUNTIF($U$8:$U$25,"НЕТ ЗАМЕРОВ")=0,COUNTIF($U$8:$U$25,"ОШИБКА ПЛАНА")=0),SUMPRODUCT($C$8:$C$25,ISNUMBER(L8:L25)*1)=$C$27),SUMPRODUCT($C$8:$C$25,L8:L25)/$C$27,"") -> 15.97 | ... N27: =IF(AND(AND(ISNUMBER($C$27),$C$27>0,COUNTIF($U$8:$U$25,"НЕТ ЗАМЕРОВ")=0,COUNTIF($U$8:$U$25,"ОШИБКА ПЛАНА")=0),SUMPRODUCT($C$8:$C$25,ISNUMBER(N8:N25)*1)=$C$27),SUMPRODUCT($C$8:$C$25,N8:N25)/$C$27,"") -> 768.4925 | O27: =IF(AND(COUNT(O8:O25)=18,COUNT(C8:C25)=18),SUM(O8:O25),"") -> 17031.76 | P27: =IF(AND(COUNT(P8:P25)=18,COUNT(C8:C25)=18),SUM(P8:P25),"") -> 17135.208 | Q27: =IF(AND(AND(ISNUMBER($C$27),$C$27>0,COUNTIF($U$8:$U$25,"НЕТ ЗАМЕРОВ")=0,COUNTIF($U$8:$U$25,"ОШИБКА ПЛАНА")=0),SUMPRODUCT($C$8:$C$25,ISNUMBER(Q8:Q25)*1)=$C$27),SUMPRODUCT($C$8:$C$25,Q8:Q25)/$C$27,"") -> 243.4925 | R27: =IF(AND(AND(ISNUMBER($C$27),$C$27>0,COUNTIF($U$8:$U$25,"НЕТ ЗАМЕРОВ")=0,COUNTIF($U$8:$U$25,"ОШИБКА ПЛАНА")=0),SUMPRODUCT($C$8:$C$25,ISNUMBER(R8:R25)*1)=$C$27),SUMPRODUCT($C$8:$C$25,R8:R25)/$C$27,"") -> 356.35947
B30: =O27 -> 17031.76 | C30: Циклическое время плана по отрегулированному циклу | J30: с/смену
