Workbook
Name Время_такта: '[1]Время такта'!$T$13
Name Время_такта: 'Время такта'!$T$8
Name ФРВ: '[1]Время такта'!$T$6
Name ФРВ: 'Время такта'!$T$6

Sheet Время такта
A1: Лист вычисления времени такта.
A2: Продукт(ы): | F2: кирпичная стена | M2: Дата: | R2: 44377
A3: Линия/РМ: | F3: каменщик | M3: Подготовил: | R3: Иванов И.М.
A4: A | B4: Сколько секунд в смене(ах), сек? | T4: =(8,5 ч+7,5 ч) х 60 мин х 60 сек=57600 сек
A5: B | B5: Сколько секунд в смену(ах) уходит на перерывы, сек? | T5: = (30 мин+2 х 10 мин + 10 мин) х 2 х 60 сек= 7200 сек
A6: C | B6: Сколько рабочих секунд в смене (А-В), сек? | T6: =57600 сек -7200 сек=50400 сек
A7: D | B7: Укажите общее количество изделий всех типов, которое нужно произвести за смену(D), шт.?
A8: E | B8: Какое время такта (C/D), сек? | T8: =50400 сек/ 646 цикла = 78 сек

Sheet Лист наблюдений
C1: ПОДГОТОВИТЕЛЬНЫЙ ЛИСТ НАБЛЮДЕНИЯ
C2: Продукт(ы): | I2: кирпичная стена | J2: Рабочее место: | O2: каменщик | T2: Дата: | Z2: 43646
C3: № операции:
C4: Границы | G4: От: | I4: набрать раствор | J4: Время такта: | O4: 78 " | T4: Подготовлено: | Z4: Иванов И.М.
G5: До: | I5: убрать излишки раствора после укладки кирпича
A6: № | B6: Общее время цикла | C6: Причина колебаний | J6: Список рабочих элементов и переходов
A7: 1 | B7: 82 | C7: Слишком много раствора | J7: 1. положить мастерком раствор из ведра на место укладки для 3х кирпичей 2. распределить равномерно раствор на месте укладки для трех кирпичей - положить мастерок и подойти к месту хранения кирпичей 3. взять3 кирпича - перенести кирпичи к месту укладки 4. взять 1й кирпич, нанести раствор на его торец мастерком 5. уложить 1й кирпич на место укладки 6. взять 2й кирпич, нанести раствор на торец 7.уложить 2й кирпич на место укладки 8. взять 3й кирпич, нанести раствор на торец 9.уложить 3й кирпич на место укладки 10. выровнить кирпичи, постукивая по ним мастерком 11. убрать мастерком излишки раствора в ведро
A8: 2 | B8: 120 | C8: Отвлекли во время цикла
A9: 3 | B9: 68
A10: 4 | B10: 70 | C10: Долго выравнивал кирпичи
A11: 5 | B11: 71
A12: 6 | B12: 85 | C12: Раствора недостаточно
A13: 7 | B13: 68
A14: 8 | B14: 71 | C14: Долго выравнивал кирпичи
A15: 9 | B15: 63
A16: 10 | B16: 68
A17: Колебания, сек | C17: 85 " - 63 " = 22 " | J17: Объяснение условных знаков:
A18: Уровень колебаний, % | M18: - наибольшее время цикла - наименьшее время цикла - ошибка

Sheet Карта СР 
M1: Карта стандартизированной работы
A2: Продукт(ы): | G2: ='Лист наблюдений'!I2 -> кирпичная стена | U2: Рабочее место: | Z2: ='Лист наблюдений'!O2 -> каменщик | AJ2: Дата: | AP2: ='Лист наблюдений'!Z2 -> 43646
A3: № операции:
A4: Границы | E4: От: | G4: ='Лист наблюдений'!I4 -> набрать раствор | U4: Время такта: | Z4: ='Лист наблюдений'!O4 -> 78 " | AJ4: Подготовлено: | AP4: ='Лист наблюдений'!Z4 -> Иванов И.М.
E5: До: | G5: ='Лист наблюдений'!I5 -> убрать излишки раствора после укладки кирпича
W31: Переходы в цикле | AB31: Переход в начало цикла | AG31: Проверка качества | AL31: Внимание вопросам безопасности | AQ31: Стандартный запас

Sheet Ручная работа 
C1: ЛИСТ НАБЛЮДЕНИЯ РУЧНОЙ РАБОТЫ
C2: Границы | D2: От: | E2: ='Карта СР '!G4 -> набрать раствор | I2: Рабочее место: | K2: ='Карта СР '!Z2 -> каменщик | N2: Продукт(ы): | P2: ='Карта СР '!G2 -> кирпичная стена | S2: Дата: | U2: ='Карта СР '!AP2 -> 43646
D3: До: | E3: ='Карта СР '!G5 -> убрать излишки раствора после укладки кирпича | I3: Время такта: | K3: ='Карта СР '!Z4 -> 78 " | N3: № операции: | P3: кладка кирпича | S3: Подготовлено: | U3: ='Карта СР '!AP4 -> Иванов И.М.
A4: № | B4: Рабочий элемент | C4: Точка отсчета | D4: 1 | E4: 2 | F4: 3 | G4: 4 | H4: 5 | I4: 6 | J4: 7 | K4: 8 | L4: 9 | M4: 10 | N4: t мин | O4: t макс-t мин | P4: Кол-во рег.сек. | Q4: t отрег | R4: Колебания | S4: Комментарии
A5: 1 | B5: положить мастерком раствор из ведра на место укладки для 3х кирпичей | C5: рука - мастерок | D5: 10 | E5: 7 | F5: 9 | G5: 8 | H5: 7 | I5: 10 | J5: 13 | K5: 8 | L5: 17 | M5: 9 | N5: 7 | O5: =J5-N5 -> 6 | P5: =6"×0,24=1,05"≈1" | Q5: =1+N5 -> 8 | R5: =J5-Q5 -> 5 | S5: 9 цикл - уронил мастерок с раствором
A6: 2 | B6: распределить равномерно раствор на месте укладки для трех кирпичей | C6: мастерок -раствор | D6: 4 | E6: 5 | F6: 5 | G6: 5 | H6: 7 | I6: 4 | J6: 5 | K6: 4 | L6: 4 | M6: 5 | N6: 4 | O6: =H6-N6 -> 3 | P6: =ROUND(O6*7/($O$5+$O$6+$O$8+$O$10+$O$11+$O$12+$O$13+$O$14+$O$15+$O$16+$O$17),0) -> 1 | Q6: =P6+N6 -> 5 | R6: =H6-Q6 -> 2
A7: - | B7: положить мастерок в ведро и подойти к месту хранения кирпичей | C7: мастерок - ведро | D7: 3 | E7: 4 | F7: 3 | G7: 4 | H7: 3 | I7: 7 | J7: 6 | K7: 9 | L7: 4 | M7: 8 | N7: 3 | O7: =K7-H7 -> 6 | Q7: =P7+N7 -> 3 | R7: =K7-Q7 -> 6
A8: 3 | B8: взять3 кирпича | C8: рука-кирпич | D8: 6 | E8: 2 | F8: 5 | G8: 6 | H8: 6 | I8: 6 | J8: 6 | K8: 6 | L8: 6 | M8: 7 | N8: 5 | O8: 2 | P8: 0 | Q8: =P8+N8 -> 5 | R8: =M8-Q8 -> 2 | S8: 2 цикл - использовал заранее подготовленные кирпичи
A9: - | B9: перенести кирпичи к месту укладки | C9: кирпичи - место | D9: 5 | E9: 0 | F9: 6 | G9: 6 | H9: 4 | I9: 9 | J9: 7 | K9: 7 | L9: 5 | M9: 7 | N9: =H9 -> 4 | O9: =I9-H9 -> 5 | Q9: =P9+N9 -> 4 | R9: =I9-Q9 -> 5
A10: 4 | B10: взять 1й кирпич, нанести раствор на его торец мастерком | C10: рука-мастерок | D10: 7 | E10: 5 | F10: 4 | G10: 5 | H10: 6 | I10: 6 | J10: 5 | K10: 6 | L10: 6 | M10: 5 | N10: =G10 -> 5 | O10: 2 | P10: 0 | Q10: =P10+N10 -> 5 | R10: =D10-Q10 -> 2
A11: 5 | B11: уложить 1й кирпич на место укладки | C11: движение руки с кирпичем | D11: 3 | E11: 4 | F11: 3 | G11: 3 | H11: 4 | I11: 3 | J11: 4 | K11: 3 | L11: 3 | M11: 3 | N11: 3 | O11: 1 | P11: 0 | Q11: =P11+N11 -> 3 | R11: =H11-Q11 -> 1
A12: 6 | B12: взять 2й кирпич, нанести раствор на торец | C12: рука-кирпич | D12: 4 | E12: 7 | F12: 4 | G12: 4 | H12: 4 | I12: 5 | J12: 5 | K12: 4 | L12: 4 | M12: 4 | N12: 4 | O12: 1 | P12: 0 | Q12: =P12+N12 -> 4 | R12: =J12-Q12 -> 1
A13: 7 | B13: уложить 2й кирпич на место укладки | C13: движение руки с кирпичем | D13: 3 | E13: 4 | F13: 3 | G13: 4 | H13: 4 | I13: 5 | J13: 3 | K13: 4 | L13: 3 | M13: 4 | N13: 3 | O13: 2 | P13: 0 | Q13: =P13+N13 -> 3 | R13: =I13-Q13 -> 2
A14: 8 | B14: взять 3й кирпич, нанести раствор на торец | C14: мастерок-кирпич | D14: 4 | E14: 3 | F14: 4 | G14: 3 | H14: 4 | I14: 4 | J14: 4 | K14: 4 | L14: 4 | M14: 4 | N14: 3 | O14: 1 | P14: 0 | Q14: =P14+N14 -> 3 | R14: =F14-Q14 -> 1
A15: 9 | B15: уложить 3й кирпич на место укладки | C15: мастерок - стена | D15: 3 | E15: 3 | F15: 4 | G15: 3 | H15: 4 | I15: 4 | J15: 3 | K15: 4 | L15: 3 | M15: 4 | N15: 3 | O15: 1 | P15: 0 | Q15: =P15+N15 -> 3 | R15: =H15-Q15 -> 1
A16: 10 | B16: выровнить кирпичи, постукивая по ним мастерком | C16: мастерок-кирпич | D16: 10 | E16: 14 | F16: 14 | G16: 8 | H16: 15 | I16: 9 | J16: 8 | K16: 10 | L16: 9 | M16: 9 | N16: 8 | O16: 7 | P16: =2"+2" | Q16: 12 | R16: =H16-Q16 -> 3 | S16: 5 цикл - слишком много раствора 2 цикл - раствора не достаточно
A17: 11 | B17: убрать мастерком излишки раствора | C17: мастерок - стена | D17: 5 | E17: 5 | F17: 7 | G17: 4 | H17: 4 | I17: 5 | J17: 5 | K17: 5 | L17: 4 | M17: 5 | N17: 4 | O17: 3 | P17: =ROUND(O17*7/($O$5+$O$6+$O$8+$O$10+$O$11+$O$12+$O$13+$O$14+$O$15+$O$16+$O$17),0) -> 1 | Q17: =P17+N17 -> 5 | R17: =F17-P17 -> 6
C18: Σ | D18: =SUM(D5:D17) -> 67 | E18: =SUM(E5:E17) -> 63 | F18: =SUM(F5:F17) -> 71 | G18: =SUM(G5:G17) -> 63 | H18: =SUM(H5:H17) -> 72 | I18: =SUM(I5:I17) -> 77 | J18: =SUM(J5:J17) -> 74 | K18: =SUM(K5:K17) -> 74 | ... N18: =SUM(N5:N17) -> 56 | P18: 7 | Q18: =SUM(Q5:Q17) -> 63 | R18: =SUM(R5:R17) -> 37
C19: Σtмин= | F19: =N18 -> 56 | J19: (Т-Σtмин)/å(t макс-t мин) не относящиеся к потерям= | P19: 7"/29"=0,24 | S19: Объяснение условных знаков: - наибольшее время элемента - наименьшее время цикла - ошибка
C20: Т-Σtмин= | F20: =63''-56''=7''

Sheet Периодическая работа
D1: Лист периодических работ
A2: Продукт(ы): | F2: Кирпичная стена | N2: Рабочее место: | O2: ='Лист наблюдений'!O2 -> каменщик | P2: Дата: | Q2: ='Ручная работа '!U2 -> 43646
A3: № операции:
A4: Границы | E4: От: | F4: ='Лист наблюдений'!I4 -> набрать раствор | N4: Время такта: | O4: ='Лист наблюдений'!O4 -> 78 " | P4: Подготовлено: | Q4: ='Ручная работа '!U3 -> Иванов И.М.
E5: До: | F5: ='Лист наблюдений'!I5 -> убрать излишки раствора после укладки кирпича
A6: № | B6: Рабочий элемент | M6: Частота повторения (количество циклов) | N6: Время | Q6: Время периодической работы на цикл
N7: 1 | O7: 2 | P7: 3
A8: 1 | B8: Резка кирпича | M8: 160 | N8: =10*60 -> 600 | O8: =7*60 -> 420 | P8: =6.5*60 -> 390 | Q8: 390''/160=2,4''
A9: 2 | B9: Установка армирующей сетки | M9: 240 | N9: 1620 | O9: 950 | P9: 1500 | Q9: 950''/240=3,95''
A10: 3 | B10: Установка направляющей нитки | M10: 120 | N10: =7.5*60 -> 450 | O10: =8.5*60 -> 510 | P10: =10*60 -> 600 | Q10: 450''/120=3,75''
A11: 4 | B11: Набрать раствор в ведро | M11: 60 | N11: 150 | O11: 300 | P11: 230 | Q11: 150''/60=2,5''
A12: Объяснение условных знаков: - наименьшее время цикла | P12: Σ | Q12: =2.4+3.95+3.75+2.5 -> 12.6

Sheet Производственная способность
D1: Лист производственной способности оборудования
A3: Участок | C3: токарная обработка | E3: Необходимое кол-во. изделий в смену, шт | H3: 510 | J3: Дата: | L3: ='Периодическая работа'!Q2 -> 43646
A4: Изделие | C4: Деталь №1 | E4: ФРВ, сек | H4: 27000 | J4: Составил: | L4: ='Периодическая работа'!Q4 -> Иванов И.М.
A5: Порядок операций | B5: Наименование операций | D5: Модель станка | E5: Базовое время | H5: Замена инструмента | J5: Производственная способность, шт | L5: Графическое отображение Ручная работа Машинная работа
E6: Время ручной работы, сек | F6: Время машинной работы, сек | G6: Общее время, сек | H6: Переодич. (кол-во. деталей) | I6: Время замены, сек
E7: А | F7: В | G7: Г | H7: Д | I7: Е
A8: 010 | B8: Токарная обработка | D8: Станок №1 | E8: 20 | F8: 45 | G8: 45 | H8: 100 | I8: 600 | J8: 600/100=6
H9: 20 | I9: 5 | J9: 5/20=0,25
H10: 200 | I10: 150 | J10: 150/200=0,75
J11: 27000/(45+6+0,25+0,75)=519
A12: 010 | B12: Токарная обработка | D12: Станок №2 | E12: 60 | F12: 120 | G12: =E12+F12 -> 180 | H12: 100 | I12: 30 | J12: 30/100=0,3
H13: 60 | I13: 120 | J13: 120/60=2
J14: 27000/(180+0,3+2)=148

Sheet Объедененная таблица (1 опер)
A1: Объединённая таблица стандартизированной работы
A3: Продукт(ы): | V3: Жил дом проект № П II-97 | BT3: Рабочее место: | CI3: Каменщики | DX3: Дата: | EQ3: 43646 | GH3: Ручная раб.
A4: № операции: | V4: Кладка 1/2 кирпича | GH4: Автом. раб.
A5: Границы | P5: От: | V5: набрать раствор | BT5: Время такта: | CI5: ='Ручная работа '!K3 -> 78 " | DX5: Подготовлено: | EQ5: Иванов И.М. | GH5: Переход
P6: До: | V6: убрать излишки раствора после укладки кирпича | GH6: Ожидание
A7: № п/п. | H7: Наименование выполняемых элементов | BE7: Время | CL7: Цена деления = | DA7: 1 | DD7: "
BE8: Руч. раб. | BK8: Авто. раб. | BQ8: Ожид. | BW8: Пере-ход | CK8: =10*$DA$7 -> 10 | CU8: =CK8+10*$DA$7 -> 20 | DE8: =CU8+10*$DA$7 -> 30 | DO8: =DE8+10*$DA$7 -> 40 | DY8: =DO8+10*$DA$7 -> 50 | EI8: =DY8+10*$DA$7 -> 60 | ES8: =EI8+10*$DA$7 -> 70 | FC8: =ES8+10*$DA$7 -> 80 | FM8: =FC8+10*$DA$7 -> 90 | FW8: =FM8+10*$DA$7 -> 100 | GG8: =FW8+10*$DA$7 -> 110
CF9: =5*$DA$7 -> 5 | CP9: =CF9+10*$DA$7 -> 15 | CZ9: =CP9+10*$DA$7 -> 25 | DJ9: =CZ9+10*$DA$7 -> 35 | DT9: =DJ9+10*$DA$7 -> 45 | ED9: =DT9+10*$DA$7 -> 55 | EN9: =ED9+10*$DA$7 -> 65 | EX9: =EN9+10*$DA$7 -> 75 | FH9: =EX9+10*$DA$7 -> 85 | FR9: =FH9+10*$DA$7 -> 95 | GB9: =FR9+10*$DA$7 -> 105 | GL9: =GB9+10*$DA$7 -> 115
A14: 1 | H14: положить мастерком раствор из ведра на место укладки для 3х кирпичей | BE14: 8
A16: 2 | H16: распределить равномерно раствор на месте укладки для трех кирпичей | BE16: 5
BW17: 4
A18: 3 | H18: взять3 кирпича | BE18: 6
A20: 4 | H20: взять 1й кирпич, нанести раствор на его торец мастерком | BE20: 5
BW21: 5
A22: 5 | H22: уложить 1й кирпич на место укладки | BE22: 3
A24: 6 | H24: взять 2й кирпич, нанести раствор на торец | BE24: 4
A26: 7 | H26: уложить 2й кирпич на место укладки | BE26: 4
A28: 8 | H28: взять 3й кирпич, нанести раствор на торец | BE28: 3
A30: 9 | H30: уложить 3й кирпич на место укладки | BE30: 3
A32: 10 | H32: выровнить кирпичи, постукивая по ним мастерком | BE32: 8
A34: 11 | H34: убрать мастерком излишки раствора | BE34: 5 | BQ34: 15
A38: ='[2]1 опер'!A38 -> 0
A40: ='[2]1 опер'!A40 -> 0
A42: ='[2]1 опер'!A42 -> 0
A44: ='[2]1 опер'!A44 -> 0
A46: ='[2]1 опер'!A46 -> 0
A48: ='[2]1 опер'!A48 -> 0
A50: ='[2]1 опер'!A50 -> 0
A52: ='[2]1 опер'!A52 -> 0
AU54: Итого: | BE54: =SUM(BE14:BJ53) -> 54 | BK54: =SUM(BK14:BP53) -> 0 | BQ54: =SUM(BQ14:BV53) -> 15 | BW54: =SUM(BW14:CB53) -> 9

Sheet Объедененная таблица (2 опер)
A1: Объединённая таблица стандартизированной работы
A3: Продукт(ы): | V3: Жил дом проект № П II-97 | BT3: Рабочее место: | CI3: Каменщики | DX3: Дата: | EQ3: 43646 | GH3: Ручная раб.
A4: № операции: | V4: Кладка 1/2 кирпича | GH4: Автом. раб.
A5: Границы | P5: От: | V5: набрать раствор | BT5: Время такта: | CI5: 78 сек | DX5: Подготовлено: | EQ5: Иванов И.М. | GH5: Переход
P6: До: | V6: убрать излишки раствора после укладки кирпича | GH6: Ожидание
A7: № п/п. Опер. | H7: Наименование выполняемых элементов | BE7: Время | CL7: Цена деления = | DA7: 1 | DD7: "
BE8: Руч. раб. | BK8: Авто. раб. | BQ8: Ожид. | BW8: Пере-ход | CK8: =10*$DA$7 -> 10 | CU8: =CK8+10*$DA$7 -> 20 | DE8: =CU8+10*$DA$7 -> 30 | DO8: =DE8+10*$DA$7 -> 40 | DY8: =DO8+10*$DA$7 -> 50 | EI8: =DY8+10*$DA$7 -> 60 | ES8: =EI8+10*$DA$7 -> 70 | FC8: =ES8+10*$DA$7 -> 80 | FM8: =FC8+10*$DA$7 -> 90 | FW8: =FM8+10*$DA$7 -> 100 | GG8: =FW8+10*$DA$7 -> 110
CF9: =5*$DA$7 -> 5 | CP9: =CF9+10*$DA$7 -> 15 | CZ9: =CP9+10*$DA$7 -> 25 | DJ9: =CZ9+10*$DA$7 -> 35 | DT9: =DJ9+10*$DA$7 -> 45 | ED9: =DT9+10*$DA$7 -> 55 | EN9: =ED9+10*$DA$7 -> 65 | EX9: =EN9+10*$DA$7 -> 75 | FH9: =EX9+10*$DA$7 -> 85 | FR9: =FH9+10*$DA$7 -> 95 | GB9: =FR9+10*$DA$7 -> 105 | GL9: =GB9+10*$DA$7 -> 115
A14: 1.1 | H14: положить мастерком раствор из ведра на место укладки для 3х кирпичей | BE14: 8 | BQ14: 5.8
A16: 1.2 | H16: распределить равномерно раствор на месте укладки для трех кирпичей | BE16: 5
A18: 1.3 | H18: взять3 кирпича | BE18: 4
A20: 1.4 | H20: уложить 1й кирпич на место укладки | BE20: 6
A22: 1.5 | H22: взять 2й кирпич, нанести раствор на торец | BE22: 5
A24: 1.6 | H24: уложить 2й кирпич на место укладки | BE24: 5
A26: 1.7 | H26: взять 3й кирпич, нанести раствор на торец | BE26: 3.2
A28: 1.8 | H28: уложить 3й кирпич на место укладки | BE28: 4 | BQ28: 36
A30: 2.1 | H30: взять3 кирпича | BE30: 4
BW31: 3.7
A32: 2.2 | H32: положить кирпичи рядом с каменщиком №1 | BE32: 7.2 | BQ32: 21
A34: 2.3 | H34: выровнить кирпичи, постукивая по ним мастерком | BE34: 12
A36: 2.4 | H36: убрать мастерком излишки раствора | BE36: 3.9 | BQ36: 24.7
A38: ='[2]1 опер'!A38 -> 0
A40: ='[2]1 опер'!A40 -> 0
A42: ='[2]1 опер'!A42 -> 0
A44: ='[2]1 опер'!A44 -> 0
A46: ='[2]1 опер'!A46 -> 0
A48: ='[2]1 опер'!A48 -> 0
A50: ='[2]1 опер'!A50 -> 0
A52: ='[2]1 опер'!A52 -> 0
AU54: Итого: | BE54: =SUM(BE14:BJ53) -> 67.3 | BK54: =SUM(BK14:BP53) -> 0 | BQ54: =SUM(BQ14:BV53) -> 87.5 | BW54: =SUM(BW14:CB53) -> 3.7

Sheet Диаграмма
F1: Диаграмма сбалансированной работы
A2: Дата | G2: 43646
Y3: Колебания | AG3: Цикл.р. + Период.р. | AM3: = | AN3: кол-во человек
A4: Участок | G4: Укладка кирпичной стены | Y4: Периодическая работа | AG4: Время такта
Y5: Цикл. работа
AG6: 63 | AI6: + | AK6: 12.6 | AM6: = | AN6: =(AG6+AK6)/AG7 -> 0.96923077
AG7: 78
D17: =D22+5 -> 120
D22: =D27+5 -> 115
D27: =D32+5 -> 110
D32: =D37+5 -> 105
D37: =D42+5 -> 100
D42: =D47+5 -> 95
D47: =D52+5 -> 90
D52: =D57+5 -> 85
D57: =D62+5 -> 80
D62: =D67+5 -> 75
D67: =D72+5 -> 70
D72: =D77+5 -> 65
... D132: =D137+5 -> 5
D137: 0

Sheet Отчет об улучшении
H1: Отчет о внедрении улучшения
A3: Участок: | F3: ='Периодическая работа'!O2 -> каменщик | O3: Операция: | AC3: Дата: | AH3: ='Производственная способность'!L3 -> 43646 | AR3: №
A4: Направленность: | F4: производительность | O4: Виды потерь: | T4: лишний этап обработки | AC4: Подготовлено: | AH4: ='Периодическая работа'!Q4 -> Иванов И.М.
A5: До усовершенствования | O5: Эскиз (фото) | AC5: После усовершенствования
A21: Проблема | P21: Внедренное изменение | AE21: Результат
A22: Каменщик тратит много времени на выравнивание кирпичей, | P22: 1. Изготовлен деревянные шаблоны для равномерного | AE22: Снижено время цикла за счет снижения колебаний и времени
A23: подстукивая мастерком в нескольких точках каждого кирпича, | P23: нанесения раствора на поверхности А и В. | AE23: выполнения элементов работы, связанных с выравниванием
A24: (3-5 удара на один кирпич) из-за неравномерного слоя | P24: 2. Каменщик кладет раствор на шаблоны и выравнивает его | AE24: кирпичей.
A25: раствора на поверхностях А и В. | P25: заподлицо мастерком.
A26: Толщина слоя зависит от квалификации каменщика, есть риск | P26: Толщина слоя раствора постоянна и определяется высотой
A27: недостаточной толщины раствора для сцепки кирпичей, либо | P27: выступа шаблона над поверхностью кирпича.
A28: излишней толщины раствора, приводящей к повышенному
A29: расходу материала.
M30: До | AB30: ЦЕЛЬ | AQ30: ФАКТ
M31: 30 сек | AB31: 10 сек | AQ31: 4 сек

Sheet Общий список улучшений
C1: СПИСОК УЛУЧШЕНИЙ
A3: Участок/Бригада: | C3: Каменщики
A4: Операция: | C4: Укладка стены
A5: № | B5: Проблемы | D5: Внедренные изменения | E5: Время | H5: Отв./срок исполнения
E6: До | F6: Цель | G6: После
A7: 1 | B7: Потери времени каменщика на выравнивание кирпичей. | D7: Шаблоны для равномерного нанесения раствора на поверхности кирпичей и мест укладки. | E7: 93 | F7: 78 | G7: 85 | H7: Антипенко А.В. / 30.06.2019
A8: 2 | B8: Потери времени каменщика на вспомогательные операции. | C8: Потери времени каменщика на вспомогательные операции. | D8: Закрепить в стандарте за помощником каменщика установку армирующей сетки и подачу раствора к месту кладки в ведре. | E8: 85 | F8: 78 | G8: 80 | H8: Иванов И.М./ 25.06.2019
A9: 3 | B9: Потери времени каменщика на перенос кирпичей к месту укладки | C9: Потери времени каменщика на перенос кирпичей к месту укладки | D9: Закрепить в стандарте за помощником каменщика функцию расстановку кирпичей в ряд параллельно укладываемой стене на минимальном расстоянии. | E9: 80 | F9: 78 | G9: 70 | H9: Иванов И.М./ 25.06.2020

Sheet СОП 
A1: СТАНДАРТ ОПЕРАЦИОННОЙ ПРОЦЕДУРЫ
A3: Цех | C3: Жилой дом проект №П II-97 | J3: УТВЕРЖДАЮ:
A4: Участок/Бригада | C4: Каменщики | J4: Директор по производству
A5: Операция: | C5: Укаладка кирпича
A6: № документа | C6: 1-2 | J6: _______________________
A7: Время цикла, сек | C7: 37
A8: Исполнители | E8: Разработал | G8: Согласовано | H8: Лист/ листов | I8: Средства индивидуальной защиты
A9: I | B9: Каменщик | D9: Должность | E9: Прораб | G9: Нач. ПТО
A10: II | B10: Помощник каменщика | D10: ФИО | E10: Иванов А.И. | G10: Дятлов А.Ю.
A11: III | D11: Подпись
A12: IV | D12: Дата | E12: 43646 | G12: 43646 | H12: 1/2
A13: № | B13: Основные этапы | D13: Ключевые моменты | F13: Причины выделения ключевых моментов | G13: Инструмент | H13: Время, сек. | I13: Иллюстрация / Схема
A14: 1 | B14: Набрать и положить левой рукой мастерком раствор из ведра на место укладки три раза. | D14: Укладку раствора проводить вплотную к предыдущей кучке. | F14: Укаладка раствора с пустыми промежутками усложнит выравнивание кирпичей. | G14: Мастерок | H14: 4
A15: 2 | B15: Распределить равномерно раствор по шаблону | D15: Слой раствора должен иметь равномерную толщину вровень с выотой шаблона. | F15: Укладка не по уровню шаблона усложнит выравнивание кирпичей и приведет либо к перерасходу раствора, либо к недостаточной прочности возводимой стены. | G15: Мастерок, шаблон №1 | H15: 6
A16: 3 | B16: Передвинуть шаблон №1 правой рукой на расстояние, соответствующее длине кирпичей укаладыемых за цикл. | G16: Вручную | H16: 2
A17: 6 | B17: Уложить кирпич на место укладки | C17: кирпич уложить вплотную к предыдущему кирпичу | D17: кирпич укладывается вровень с предыдущим рядом | F17: неровная укладка приведет к потерям времени на последующее выравнивание | G17: Вручную | H17: 2 | J17: кирпич
A18: 7 | B18: Прижать кирпичи одним ударом по его поверхности | C18: верхняя плоскость кирпича должна быть вровень с направляющей нитью | D18: кирпич должен быть установлен на одинаковом уровне с предыдущим кирпичом | F18: неровная укладка приведет к потерям времени на последующее выравнивание | G18: Вручную | H18: 5
